Workbook

Sheet INICIO
A1: CANDYSHOTS — SISTEMA DE ADMINISTRACION
A2: Machala, Ecuador · v1.0 · Todos los valores en USD
B4: PARAMETROS GLOBALES | D4: Cambia estos valores y TODO el sistema se recalcula.
B5: IVA de venta (Ecuador 2026) | C5: 0.15 | D5: Tarifa vigente. Tus precios de carta se asumen CON IVA incluido.
B6: ¿Recuperas el IVA de tus compras? (SI/NO) | C6: SI | D6: CONFIRMADO 2026-09-07: SI. Regimen general con RUC, credito tributario. Si eso cambia, ponlo en NO.
B7: Dias de operacion al mes | C7: 26 | D7: Se usa para punto de equilibrio y proyecciones.
B8: Mes que analiza el DASHBOARD (AAAA-MM) | C8: 2026-09 | D8: Escribe el mes que quieres ver. Ej: 2026-10
B9: Margen objetivo por defecto | C9: 0.7 | D9: Se usa para calcular el PVP sugerido de productos nuevos.
B11: COMO USAR ESTE ARCHIVO
B12: Colores | D12: AZUL = escribes tu. NEGRO = formula, no tocar. VERDE = viene de otra hoja. FONDO AMARILLO = celda para llenar.
B14: ORDEN DE LLENADO (primera vez)
B15: 1. INSUMOS | D15: Cada cosa que compras: precio y cuanto rinde. Es la base de todo.
B16: 2. RECETAS | D16: Que insumos y cuanta cantidad lleva cada producto.
B17: 3. PRODUCTOS | D17: Precio de venta al publico. Te dice utilidad, margen y si el precio esta bien.
B18: 4. COMBOS | D18: Arma combos y ve cuanto margen sacrificas antes de lanzarlos.
B19: 5. GASTOS_FIJOS | D19: Arriendo, luz, sueldos. Alimenta el punto de equilibrio.
B21: USO DIARIO
B22: VENTAS | D22: Una fila por venta. Elige producto del desplegable y pon la cantidad. El resto se calcula solo.
B23: GASTOS | D23: Cada compra o pago que sale del negocio.
B24: CAJA | D24: Al cerrar el dia: cuanto habia, cuanto contaste. Te muestra el descuadre.
B26: SOLO LECTURA (no escribes nada)
B27: DASHBOARD | D27: Resumen del mes: venta, utilidad, top productos, alertas.
B28: EQUILIBRIO | D28: Cuantos vasos al dia necesitas para no perder plata. El numero mas importante.
B29: PYG | D29: Estado de resultados mes a mes con datos reales.
B30: PROYECCIONES | D30: 3 escenarios a 12 meses.
B31: INVENTARIO | D31: Stock y alertas de compra.
B33: REGLA DE ORO
D34: Si no registras las ventas todos los dias, este archivo no sirve para nada. 2 minutos al cierre.
B36: COMO ESTA CONECTADO TODO | D36: Cambias UN dato y se recalcula toda la cadena. Nunca escribas dos veces lo mismo.
B37: INSUMOS -> RECETAS | D37: Eliges el insumo de una LISTA. Trae solo su costo por ml/g/unidad.
B38: RECETAS -> PRODUCTOS | D38: Suma todas las lineas de la receta = costo del producto.
B39: PRODUCTOS -> COMBOS | D39: Eliges los items del combo de una LISTA. Trae precio y costo de cada uno.
B40: COMBOS -> PRODUCTOS | D40: El combo vuelve como un producto mas, para poder venderlo en VENTAS.
B41: PRODUCTOS -> VENTAS | D41: Eliges el producto de una LISTA. Trae precio Y costo. Tu solo pones la cantidad.
B42: VENTAS -> CAJA / DASHBOARD / PYG / EQUILIBRIO | D42: Todo el analisis sale de aqui. Por eso registrar ventas no es opcional.
B43: VENTAS + RECETAS -> INVENTARIO | D43: Calcula solo cuanto insumo consumiste segun lo que vendiste.
B44: GASTOS -> CAJA / DASHBOARD / PYG | D44: Los gastos reales bajan tu utilidad en todos los reportes.
B45: GASTOS_FIJOS -> EQUILIBRIO / PROYECCIONES | D45: Tu plan de fijos. Define cuantos vasos al dia necesitas vender.
B46: INSUMOS -> FICHAS_TECNICAS | D46: El costo impreso en la ficha se actualiza solo si sube un precio.
B48: SI ALGO NO TE APARECE EN UN DESPLEGABLE
B49: Producto que no sale en VENTAS | D49: Agregalo primero en PRODUCTOS (columna B). Aparece al instante en la lista.
B50: Insumo que no sale en RECETAS | D50: Agregalo primero en INSUMOS (columna B).
B51: Regla general | D51: Las listas se alimentan solas. Si falta algo, es porque no lo creaste en su hoja maestra.

Sheet DASHBOARD
A1: DASHBOARD
A2: Cambia el mes en la hoja INICIO (celda C8) y todo aqui se actualiza.
B3: MES ANALIZADO: | C3: =INICIO!$C$8
E4: RENDIMIENTO POR PRODUCTO (mes analizado)
B5: VENTA BRUTA DEL MES (c/IVA) | C5: =SUMIFS(VENTAS!$F$5:$F$504,VENTAS!$B$5:$B$504,INICIO!$C$8) | E5: Producto | F5: Unidades | G5: Venta c/IVA | H5: Utilidad
B6: IVA cobrado (esto NO es tuyo) | C6: =SUMIFS(VENTAS!$G$5:$G$504,VENTAS!$B$5:$B$504,INICIO!$C$8) | E6: =IF(PRODUCTOS!$B5="","",PRODUCTOS!$B5) | F6: =IF($E6="","",SUMIFS(VENTAS!$D$5:$D$504,VENTAS!$B$5:$B$504,INICIO!$C$8,VENTAS!$C$5:$C$504,$E6)) | G6: =IF($E6="","",SUMIFS(VENTAS!$F$5:$F$504,VENTAS!$B$5:$B$504,INICIO!$C$8,VENTAS!$C$5:$C$504,$E6)) | H6: =IF($E6="","",SUMIFS(VENTAS!$J$5:$J$504,VENTAS!$B$5:$B$504,INICIO!$C$8,VENTAS!$C$5:$C$504,$E6))
B7: INGRESO NETO (tuyo) | C7: =SUMIFS(VENTAS!$H$5:$H$504,VENTAS!$B$5:$B$504,INICIO!$C$8) | E7: =IF(PRODUCTOS!$B6="","",PRODUCTOS!$B6) | F7: =IF($E7="","",SUMIFS(VENTAS!$D$5:$D$504,VENTAS!$B$5:$B$504,INICIO!$C$8,VENTAS!$C$5:$C$504,$E7)) | G7: =IF($E7="","",SUMIFS(VENTAS!$F$5:$F$504,VENTAS!$B$5:$B$504,INICIO!$C$8,VENTAS!$C$5:$C$504,$E7)) | H7: =IF($E7="","",SUMIFS(VENTAS!$J$5:$J$504,VENTAS!$B$5:$B$504,INICIO!$C$8,VENTAS!$C$5:$C$504,$E7))
B8: Costo de ventas | C8: =SUMIFS(VENTAS!$I$5:$I$504,VENTAS!$B$5:$B$504,INICIO!$C$8) | E8: =IF(PRODUCTOS!$B7="","",PRODUCTOS!$B7) | F8: =IF($E8="","",SUMIFS(VENTAS!$D$5:$D$504,VENTAS!$B$5:$B$504,INICIO!$C$8,VENTAS!$C$5:$C$504,$E8)) | G8: =IF($E8="","",SUMIFS(VENTAS!$F$5:$F$504,VENTAS!$B$5:$B$504,INICIO!$C$8,VENTAS!$C$5:$C$504,$E8)) | H8: =IF($E8="","",SUMIFS(VENTAS!$J$5:$J$504,VENTAS!$B$5:$B$504,INICIO!$C$8,VENTAS!$C$5:$C$504,$E8))
B9: UTILIDAD BRUTA | C9: =$C$7-$C$8 | E9: =IF(PRODUCTOS!$B8="","",PRODUCTOS!$B8) | F9: =IF($E9="","",SUMIFS(VENTAS!$D$5:$D$504,VENTAS!$B$5:$B$504,INICIO!$C$8,VENTAS!$C$5:$C$504,$E9)) | G9: =IF($E9="","",SUMIFS(VENTAS!$F$5:$F$504,VENTAS!$B$5:$B$504,INICIO!$C$8,VENTAS!$C$5:$C$504,$E9)) | H9: =IF($E9="","",SUMIFS(VENTAS!$J$5:$J$504,VENTAS!$B$5:$B$504,INICIO!$C$8,VENTAS!$C$5:$C$504,$E9))
B10: Margen bruto | C10: =IFERROR($C$9/$C$7,0) | E10: =IF(PRODUCTOS!$B9="","",PRODUCTOS!$B9) | F10: =IF($E10="","",SUMIFS(VENTAS!$D$5:$D$504,VENTAS!$B$5:$B$504,INICIO!$C$8,VENTAS!$C$5:$C$504,$E10)) | G10: =IF($E10="","",SUMIFS(VENTAS!$F$5:$F$504,VENTAS!$B$5:$B$504,INICIO!$C$8,VENTAS!$C$5:$C$504,$E10)) | H10: =IF($E10="","",SUMIFS(VENTAS!$J$5:$J$504,VENTAS!$B$5:$B$504,INICIO!$C$8,VENTAS!$C$5:$C$504,$E10))
B11: Gastos operativos del mes | C11: =SUMIFS(GASTOS!$E$5:$E$304,GASTOS!$B$5:$B$304,INICIO!$C$8)-SUMIFS(GASTOS!$E$5:$E$304,GASTOS!$B$5:$B$304,INICIO!$C$8,GASTOS!$C$5:$C$304,"Insumos")-SUMIFS(GASTOS!$E$5:$E$304,GASTOS!$B$5:$B$304,INICIO!$C$8,GASTOS!$C$5:$C$304,"Descartables") | E11: =IF(PRODUCTOS!$B10="","",PRODUCTOS!$B10) | F11: =IF($E11="","",SUMIFS(VENTAS!$D$5:$D$504,VENTAS!$B$5:$B$504,INICIO!$C$8,VENTAS!$C$5:$C$504,$E11)) | G11: =IF($E11="","",SUMIFS(VENTAS!$F$5:$F$504,VENTAS!$B$5:$B$504,INICIO!$C$8,VENTAS!$C$5:$C$504,$E11)) | H11: =IF($E11="","",SUMIFS(VENTAS!$J$5:$J$504,VENTAS!$B$5:$B$504,INICIO!$C$8,VENTAS!$C$5:$C$504,$E11))
B12: UTILIDAD NETA DEL MES | C12: =$C$9-$C$11 | E12: =IF(PRODUCTOS!$B11="","",PRODUCTOS!$B11) | F12: =IF($E12="","",SUMIFS(VENTAS!$D$5:$D$504,VENTAS!$B$5:$B$504,INICIO!$C$8,VENTAS!$C$5:$C$504,$E12)) | G12: =IF($E12="","",SUMIFS(VENTAS!$F$5:$F$504,VENTAS!$B$5:$B$504,INICIO!$C$8,VENTAS!$C$5:$C$504,$E12)) | H12: =IF($E12="","",SUMIFS(VENTAS!$J$5:$J$504,VENTAS!$B$5:$B$504,INICIO!$C$8,VENTAS!$C$5:$C$504,$E12))
B13: Unidades vendidas | C13: =SUMIFS(VENTAS!$D$5:$D$504,VENTAS!$B$5:$B$504,INICIO!$C$8) | E13: =IF(PRODUCTOS!$B12="","",PRODUCTOS!$B12) | F13: =IF($E13="","",SUMIFS(VENTAS!$D$5:$D$504,VENTAS!$B$5:$B$504,INICIO!$C$8,VENTAS!$C$5:$C$504,$E13)) | G13: =IF($E13="","",SUMIFS(VENTAS!$F$5:$F$504,VENTAS!$B$5:$B$504,INICIO!$C$8,VENTAS!$C$5:$C$504,$E13)) | H13: =IF($E13="","",SUMIFS(VENTAS!$J$5:$J$504,VENTAS!$B$5:$B$504,INICIO!$C$8,VENTAS!$C$5:$C$504,$E13))
B14: Ticket promedio (c/IVA) | C14: =IFERROR($C$5/$C$13,0) | E14: =IF(PRODUCTOS!$B13="","",PRODUCTOS!$B13) | F14: =IF($E14="","",SUMIFS(VENTAS!$D$5:$D$504,VENTAS!$B$5:$B$504,INICIO!$C$8,VENTAS!$C$5:$C$504,$E14)) | G14: =IF($E14="","",SUMIFS(VENTAS!$F$5:$F$504,VENTAS!$B$5:$B$504,INICIO!$C$8,VENTAS!$C$5:$C$504,$E14)) | H14: =IF($E14="","",SUMIFS(VENTAS!$J$5:$J$504,VENTAS!$B$5:$B$504,INICIO!$C$8,VENTAS!$C$5:$C$504,$E14))
B15: Venta promedio por dia (mes / dias operacion) | C15: =IFERROR($C$5/INICIO!$C$7,0) | E15: =IF(PRODUCTOS!$B14="","",PRODUCTOS!$B14) | F15: =IF($E15="","",SUMIFS(VENTAS!$D$5:$D$504,VENTAS!$B$5:$B$504,INICIO!$C$8,VENTAS!$C$5:$C$504,$E15)) | G15: =IF($E15="","",SUMIFS(VENTAS!$F$5:$F$504,VENTAS!$B$5:$B$504,INICIO!$C$8,VENTAS!$C$5:$C$504,$E15)) | H15: =IF($E15="","",SUMIFS(VENTAS!$J$5:$J$504,VENTAS!$B$5:$B$504,INICIO!$C$8,VENTAS!$C$5:$C$504,$E15))
E16: =IF(PRODUCTOS!$B15="","",PRODUCTOS!$B15) | F16: =IF($E16="","",SUMIFS(VENTAS!$D$5:$D$504,VENTAS!$B$5:$B$504,INICIO!$C$8,VENTAS!$C$5:$C$504,$E16)) | G16: =IF($E16="","",SUMIFS(VENTAS!$F$5:$F$504,VENTAS!$B$5:$B$504,INICIO!$C$8,VENTAS!$C$5:$C$504,$E16)) | H16: =IF($E16="","",SUMIFS(VENTAS!$J$5:$J$504,VENTAS!$B$5:$B$504,INICIO!$C$8,VENTAS!$C$5:$C$504,$E16))
B17: VS PUNTO DE EQUILIBRIO | E17: =IF(PRODUCTOS!$B16="","",PRODUCTOS!$B16) | F17: =IF($E17="","",SUMIFS(VENTAS!$D$5:$D$504,VENTAS!$B$5:$B$504,INICIO!$C$8,VENTAS!$C$5:$C$504,$E17)) | G17: =IF($E17="","",SUMIFS(VENTAS!$F$5:$F$504,VENTAS!$B$5:$B$504,INICIO!$C$8,VENTAS!$C$5:$C$504,$E17)) | H17: =IF($E17="","",SUMIFS(VENTAS!$J$5:$J$504,VENTAS!$B$5:$B$504,INICIO!$C$8,VENTAS!$C$5:$C$504,$E17))
B18: Unidades necesarias al mes | C18: =IFERROR(EQUILIBRIO!$C$18,0) | E18: =IF(PRODUCTOS!$B17="","",PRODUCTOS!$B17) | F18: =IF($E18="","",SUMIFS(VENTAS!$D$5:$D$504,VENTAS!$B$5:$B$504,INICIO!$C$8,VENTAS!$C$5:$C$504,$E18)) | G18: =IF($E18="","",SUMIFS(VENTAS!$F$5:$F$504,VENTAS!$B$5:$B$504,INICIO!$C$8,VENTAS!$C$5:$C$504,$E18)) | H18: =IF($E18="","",SUMIFS(VENTAS!$J$5:$J$504,VENTAS!$B$5:$B$504,INICIO!$C$8,VENTAS!$C$5:$C$504,$E18))
B19: % del punto de equilibrio alcanzado | C19: =IFERROR($C$13/EQUILIBRIO!$C$18,0) | E19: =IF(PRODUCTOS!$B18="","",PRODUCTOS!$B18) | F19: =IF($E19="","",SUMIFS(VENTAS!$D$5:$D$504,VENTAS!$B$5:$B$504,INICIO!$C$8,VENTAS!$C$5:$C$504,$E19)) | G19: =IF($E19="","",SUMIFS(VENTAS!$F$5:$F$504,VENTAS!$B$5:$B$504,INICIO!$C$8,VENTAS!$C$5:$C$504,$E19)) | H19: =IF($E19="","",SUMIFS(VENTAS!$J$5:$J$504,VENTAS!$B$5:$B$504,INICIO!$C$8,VENTAS!$C$5:$C$504,$E19))
B20: Estado | C20: =IF($C$12>0,"GANANDO PLATA",IF($C$13=0,"SIN DATOS","PERDIENDO PLATA")) | E20: =IF(PRODUCTOS!$B19="","",PRODUCTOS!$B19) | F20: =IF($E20="","",SUMIFS(VENTAS!$D$5:$D$504,VENTAS!$B$5:$B$504,INICIO!$C$8,VENTAS!$C$5:$C$504,$E20)) | G20: =IF($E20="","",SUMIFS(VENTAS!$F$5:$F$504,VENTAS!$B$5:$B$504,INICIO!$C$8,VENTAS!$C$5:$C$504,$E20)) | H20: =IF($E20="","",SUMIFS(VENTAS!$J$5:$J$504,VENTAS!$B$5:$B$504,INICIO!$C$8,VENTAS!$C$5:$C$504,$E20))
E21: =IF(PRODUCTOS!$B20="","",PRODUCTOS!$B20) | F21: =IF($E21="","",SUMIFS(VENTAS!$D$5:$D$504,VENTAS!$B$5:$B$504,INICIO!$C$8,VENTAS!$C$5:$C$504,$E21)) | G21: =IF($E21="","",SUMIFS(VENTAS!$F$5:$F$504,VENTAS!$B$5:$B$504,INICIO!$C$8,VENTAS!$C$5:$C$504,$E21)) | H21: =IF($E21="","",SUMIFS(VENTAS!$J$5:$J$504,VENTAS!$B$5:$B$504,INICIO!$C$8,VENTAS!$C$5:$C$504,$E21))
E22: =IF(PRODUCTOS!$B21="","",PRODUCTOS!$B21) | F22: =IF($E22="","",SUMIFS(VENTAS!$D$5:$D$504,VENTAS!$B$5:$B$504,INICIO!$C$8,VENTAS!$C$5:$C$504,$E22)) | G22: =IF($E22="","",SUMIFS(VENTAS!$F$5:$F$504,VENTAS!$B$5:$B$504,INICIO!$C$8,VENTAS!$C$5:$C$504,$E22)) | H22: =IF($E22="","",SUMIFS(VENTAS!$J$5:$J$504,VENTAS!$B$5:$B$504,INICIO!$C$8,VENTAS!$C$5:$C$504,$E22))
E23: =IF(PRODUCTOS!$B22="","",PRODUCTOS!$B22) | F23: =IF($E23="","",SUMIFS(VENTAS!$D$5:$D$504,VENTAS!$B$5:$B$504,INICIO!$C$8,VENTAS!$C$5:$C$504,$E23)) | G23: =IF($E23="","",SUMIFS(VENTAS!$F$5:$F$504,VENTAS!$B$5:$B$504,INICIO!$C$8,VENTAS!$C$5:$C$504,$E23)) | H23: =IF($E23="","",SUMIFS(VENTAS!$J$5:$J$504,VENTAS!$B$5:$B$504,INICIO!$C$8,VENTAS!$C$5:$C$504,$E23))
E24: =IF(PRODUCTOS!$B23="","",PRODUCTOS!$B23) | F24: =IF($E24="","",SUMIFS(VENTAS!$D$5:$D$504,VENTAS!$B$5:$B$504,INICIO!$C$8,VENTAS!$C$5:$C$504,$E24)) | G24: =IF($E24="","",SUMIFS(VENTAS!$F$5:$F$504,VENTAS!$B$5:$B$504,INICIO!$C$8,VENTAS!$C$5:$C$504,$E24)) | H24: =IF($E24="","",SUMIFS(VENTAS!$J$5:$J$504,VENTAS!$B$5:$B$504,INICIO!$C$8,VENTAS!$C$5:$C$504,$E24))
E25: =IF(PRODUCTOS!$B24="","",PRODUCTOS!$B24) | F25: =IF($E25="","",SUMIFS(VENTAS!$D$5:$D$504,VENTAS!$B$5:$B$504,INICIO!$C$8,VENTAS!$C$5:$C$504,$E25)) | G25: =IF($E25="","",SUMIFS(VENTAS!$F$5:$F$504,VENTAS!$B$5:$B$504,INICIO!$C$8,VENTAS!$C$5:$C$504,$E25)) | H25: =IF($E25="","",SUMIFS(VENTAS!$J$5:$J$504,VENTAS!$B$5:$B$504,INICIO!$C$8,VENTAS!$C$5:$C$504,$E25))
E26: =IF(PRODUCTOS!$B25="","",PRODUCTOS!$B25) | F26: =IF($E26="","",SUMIFS(VENTAS!$D$5:$D$504,VENTAS!$B$5:$B$504,INICIO!$C$8,VENTAS!$C$5:$C$504,$E26)) | G26: =IF($E26="","",SUMIFS(VENTAS!$F$5:$F$504,VENTAS!$B$5:$B$504,INICIO!$C$8,VENTAS!$C$5:$C$504,$E26)) | H26: =IF($E26="","",SUMIFS(VENTAS!$J$5:$J$504,VENTAS!$B$5:$B$504,INICIO!$C$8,VENTAS!$C$5:$C$504,$E26))
E27: =IF(PRODUCTOS!$B26="","",PRODUCTOS!$B26) | F27: =IF($E27="","",SUMIFS(VENTAS!$D$5:$D$504,VENTAS!$B$5:$B$504,INICIO!$C$8,VENTAS!$C$5:$C$504,$E27)) | G27: =IF($E27="","",SUMIFS(VENTAS!$F$5:$F$504,VENTAS!$B$5:$B$504,INICIO!$C$8,VENTAS!$C$5:$C$504,$E27)) | H27: =IF($E27="","",SUMIFS(VENTAS!$J$5:$J$504,VENTAS!$B$5:$B$504,INICIO!$C$8,VENTAS!$C$5:$C$504,$E27))
E28: =IF(PRODUCTOS!$B27="","",PRODUCTOS!$B27) | F28: =IF($E28="","",SUMIFS(VENTAS!$D$5:$D$504,VENTAS!$B$5:$B$504,INICIO!$C$8,VENTAS!$C$5:$C$504,$E28)) | G28: =IF($E28="","",SUMIFS(VENTAS!$F$5:$F$504,VENTAS!$B$5:$B$504,INICIO!$C$8,VENTAS!$C$5:$C$504,$E28)) | H28: =IF($E28="","",SUMIFS(VENTAS!$J$5:$J$504,VENTAS!$B$5:$B$504,INICIO!$C$8,VENTAS!$C$5:$C$504,$E28))
E29: =IF(PRODUCTOS!$B28="","",PRODUCTOS!$B28) | F29: =IF($E29="","",SUMIFS(VENTAS!$D$5:$D$504,VENTAS!$B$5:$B$504,INICIO!$C$8,VENTAS!$C$5:$C$504,$E29)) | G29: =IF($E29="","",SUMIFS(VENTAS!$F$5:$F$504,VENTAS!$B$5:$B$504,INICIO!$C$8,VENTAS!$C$5:$C$504,$E29)) | H29: =IF($E29="","",SUMIFS(VENTAS!$J$5:$J$504,VENTAS!$B$5:$B$504,INICIO!$C$8,VENTAS!$C$5:$C$504,$E29))
E30: =IF(PRODUCTOS!$B29="","",PRODUCTOS!$B29) | F30: =IF($E30="","",SUMIFS(VENTAS!$D$5:$D$504,VENTAS!$B$5:$B$504,INICIO!$C$8,VENTAS!$C$5:$C$504,$E30)) | G30: =IF($E30="","",SUMIFS(VENTAS!$F$5:$F$504,VENTAS!$B$5:$B$504,INICIO!$C$8,VENTAS!$C$5:$C$504,$E30)) | H30: =IF($E30="","",SUMIFS(VENTAS!$J$5:$J$504,VENTAS!$B$5:$B$504,INICIO!$C$8,VENTAS!$C$5:$C$504,$E30))
E31: =IF(PRODUCTOS!$B30="","",PRODUCTOS!$B30) | F31: =IF($E31="","",SUMIFS(VENTAS!$D$5:$D$504,VENTAS!$B$5:$B$504,INICIO!$C$8,VENTAS!$C$5:$C$504,$E31)) | G31: =IF($E31="","",SUMIFS(VENTAS!$F$5:$F$504,VENTAS!$B$5:$B$504,INICIO!$C$8,VENTAS!$C$5:$C$504,$E31)) | H31: =IF($E31="","",SUMIFS(VENTAS!$J$5:$J$504,VENTAS!$B$5:$B$504,INICIO!$C$8,VENTAS!$C$5:$C$504,$E31))
E32: =IF(PRODUCTOS!$B31="","",PRODUCTOS!$B31) | F32: =IF($E32="","",SUMIFS(VENTAS!$D$5:$D$504,VENTAS!$B$5:$B$504,INICIO!$C$8,VENTAS!$C$5:$C$504,$E32)) | G32: =IF($E32="","",SUMIFS(VENTAS!$F$5:$F$504,VENTAS!$B$5:$B$504,INICIO!$C$8,VENTAS!$C$5:$C$504,$E32)) | H32: =IF($E32="","",SUMIFS(VENTAS!$J$5:$J$504,VENTAS!$B$5:$B$504,INICIO!$C$8,VENTAS!$C$5:$C$504,$E32))
... E45: =IF(PRODUCTOS!$B44="","",PRODUCTOS!$B44) | F45: =IF($E45="","",SUMIFS(VENTAS!$D$5:$D$504,VENTAS!$B$5:$B$504,INICIO!$C$8,VENTAS!$C$5:$C$504,$E45)) | G45: =IF($E45="","",SUMIFS(VENTAS!$F$5:$F$504,VENTAS!$B$5:$B$504,INICIO!$C$8,VENTAS!$C$5:$C$504,$E45)) | H45: =IF($E45="","",SUMIFS(VENTAS!$J$5:$J$504,VENTAS!$B$5:$B$504,INICIO!$C$8,VENTAS!$C$5:$C$504,$E45))
E47: Ordena esta tabla por 'Utilidad' (Datos > Ordenar) para ver que producto realmente te da de comer.
E48: El que mas vende no siempre es el que mas deja. Ese es el punto de esta tabla.

Sheet VENTAS
A1: VENTAS
A2: Una fila por venta. Solo llenas: Fecha · Producto · Cantidad · Forma de pago · Atendio. El resto se calcula solo.
A4: Fecha | B4: Mes | C4: Producto | D4: Cant. | E4: PVP unit c/IVA | F4: TOTAL c/IVA | G4: IVA cobrado | H4: Ingreso neto | I4: Costo | J4: UTILIDAD | K4: Forma de pago | L4: Atendio
A5: 46280 | B5: =IF($A5="","",TEXT($A5,"YYYY-MM")) | C5: Coco s/alcohol | D5: 2 | E5: =IFERROR(IF($C5="","",INDEX(PRODUCTOS!$E$5:$E$44,MATCH($C5,PRODUCTOS!$B$5:$B$44,0))),"") | F5: =IFERROR(IF($C5="","",$D5*$E5),"") | G5: =IFERROR(IF($C5="","",$F5-$H5),"") | H5: =IFERROR(IF($C5="","",$F5/(1+INICIO!$C$5)),"") | I5: =IFERROR(IF($C5="","",$D5*INDEX(PRODUCTOS!$D$5:$D$44,MATCH($C5,PRODUCTOS!$B$5:$B$44,0))),"") | J5: =IFERROR(IF($C5="","",$H5-$I5),"") | K5: Efectivo | L5: Fabian
B6: =IF($A6="","",TEXT($A6,"YYYY-MM")) | E6: =IFERROR(IF($C6="","",INDEX(PRODUCTOS!$E$5:$E$44,MATCH($C6,PRODUCTOS!$B$5:$B$44,0))),"") | F6: =IFERROR(IF($C6="","",$D6*$E6),"") | G6: =IFERROR(IF($C6="","",$F6-$H6),"") | H6: =IFERROR(IF($C6="","",$F6/(1+INICIO!$C$5)),"") | I6: =IFERROR(IF($C6="","",$D6*INDEX(PRODUCTOS!$D$5:$D$44,MATCH($C6,PRODUCTOS!$B$5:$B$44,0))),"") | J6: =IFERROR(IF($C6="","",$H6-$I6),"")
B7: =IF($A7="","",TEXT($A7,"YYYY-MM")) | E7: =IFERROR(IF($C7="","",INDEX(PRODUCTOS!$E$5:$E$44,MATCH($C7,PRODUCTOS!$B$5:$B$44,0))),"") | F7: =IFERROR(IF($C7="","",$D7*$E7),"") | G7: =IFERROR(IF($C7="","",$F7-$H7),"") | H7: =IFERROR(IF($C7="","",$F7/(1+INICIO!$C$5)),"") | I7: =IFERROR(IF($C7="","",$D7*INDEX(PRODUCTOS!$D$5:$D$44,MATCH($C7,PRODUCTOS!$B$5:$B$44,0))),"") | J7: =IFERROR(IF($C7="","",$H7-$I7),"")
B8: =IF($A8="","",TEXT($A8,"YYYY-MM")) | E8: =IFERROR(IF($C8="","",INDEX(PRODUCTOS!$E$5:$E$44,MATCH($C8,PRODUCTOS!$B$5:$B$44,0))),"") | F8: =IFERROR(IF($C8="","",$D8*$E8),"") | G8: =IFERROR(IF($C8="","",$F8-$H8),"") | H8: =IFERROR(IF($C8="","",$F8/(1+INICIO!$C$5)),"") | I8: =IFERROR(IF($C8="","",$D8*INDEX(PRODUCTOS!$D$5:$D$44,MATCH($C8,PRODUCTOS!$B$5:$B$44,0))),"") | J8: =IFERROR(IF($C8="","",$H8-$I8),"")
B9: =IF($A9="","",TEXT($A9,"YYYY-MM")) | E9: =IFERROR(IF($C9="","",INDEX(PRODUCTOS!$E$5:$E$44,MATCH($C9,PRODUCTOS!$B$5:$B$44,0))),"") | F9: =IFERROR(IF($C9="","",$D9*$E9),"") | G9: =IFERROR(IF($C9="","",$F9-$H9),"") | H9: =IFERROR(IF($C9="","",$F9/(1+INICIO!$C$5)),"") | I9: =IFERROR(IF($C9="","",$D9*INDEX(PRODUCTOS!$D$5:$D$44,MATCH($C9,PRODUCTOS!$B$5:$B$44,0))),"") | J9: =IFERROR(IF($C9="","",$H9-$I9),"")
B10: =IF($A10="","",TEXT($A10,"YYYY-MM")) | E10: =IFERROR(IF($C10="","",INDEX(PRODUCTOS!$E$5:$E$44,MATCH($C10,PRODUCTOS!$B$5:$B$44,0))),"") | F10: =IFERROR(IF($C10="","",$D10*$E10),"") | G10: =IFERROR(IF($C10="","",$F10-$H10),"") | H10: =IFERROR(IF($C10="","",$F10/(1+INICIO!$C$5)),"") | I10: =IFERROR(IF($C10="","",$D10*INDEX(PRODUCTOS!$D$5:$D$44,MATCH($C10,PRODUCTOS!$B$5:$B$44,0))),"") | J10: =IFERROR(IF($C10="","",$H10-$I10),"")
B11: =IF($A11="","",TEXT($A11,"YYYY-MM")) | E11: =IFERROR(IF($C11="","",INDEX(PRODUCTOS!$E$5:$E$44,MATCH($C11,PRODUCTOS!$B$5:$B$44,0))),"") | F11: =IFERROR(IF($C11="","",$D11*$E11),"") | G11: =IFERROR(IF($C11="","",$F11-$H11),"") | H11: =IFERROR(IF($C11="","",$F11/(1+INICIO!$C$5)),"") | I11: =IFERROR(IF($C11="","",$D11*INDEX(PRODUCTOS!$D$5:$D$44,MATCH($C11,PRODUCTOS!$B$5:$B$44,0))),"") | J11: =IFERROR(IF($C11="","",$H11-$I11),"")
B12: =IF($A12="","",TEXT($A12,"YYYY-MM")) | E12: =IFERROR(IF($C12="","",INDEX(PRODUCTOS!$E$5:$E$44,MATCH($C12,PRODUCTOS!$B$5:$B$44,0))),"") | F12: =IFERROR(IF($C12="","",$D12*$E12),"") | G12: =IFERROR(IF($C12="","",$F12-$H12),"") | H12: =IFERROR(IF($C12="","",$F12/(1+INICIO!$C$5)),"") | I12: =IFERROR(IF($C12="","",$D12*INDEX(PRODUCTOS!$D$5:$D$44,MATCH($C12,PRODUCTOS!$B$5:$B$44,0))),"") | J12: =IFERROR(IF($C12="","",$H12-$I12),"")
B13: =IF($A13="","",TEXT($A13,"YYYY-MM")) | E13: =IFERROR(IF($C13="","",INDEX(PRODUCTOS!$E$5:$E$44,MATCH($C13,PRODUCTOS!$B$5:$B$44,0))),"") | F13: =IFERROR(IF($C13="","",$D13*$E13),"") | G13: =IFERROR(IF($C13="","",$F13-$H13),"") | H13: =IFERROR(IF($C13="","",$F13/(1+INICIO!$C$5)),"") | I13: =IFERROR(IF($C13="","",$D13*INDEX(PRODUCTOS!$D$5:$D$44,MATCH($C13,PRODUCTOS!$B$5:$B$44,0))),"") | J13: =IFERROR(IF($C13="","",$H13-$I13),"")
B14: =IF($A14="","",TEXT($A14,"YYYY-MM")) | E14: =IFERROR(IF($C14="","",INDEX(PRODUCTOS!$E$5:$E$44,MATCH($C14,PRODUCTOS!$B$5:$B$44,0))),"") | F14: =IFERROR(IF($C14="","",$D14*$E14),"") | G14: =IFERROR(IF($C14="","",$F14-$H14),"") | H14: =IFERROR(IF($C14="","",$F14/(1+INICIO!$C$5)),"") | I14: =IFERROR(IF($C14="","",$D14*INDEX(PRODUCTOS!$D$5:$D$44,MATCH($C14,PRODUCTOS!$B$5:$B$44,0))),"") | J14: =IFERROR(IF($C14="","",$H14-$I14),"")
B15: =IF($A15="","",TEXT($A15,"YYYY-MM")) | E15: =IFERROR(IF($C15="","",INDEX(PRODUCTOS!$E$5:$E$44,MATCH($C15,PRODUCTOS!$B$5:$B$44,0))),"") | F15: =IFERROR(IF($C15="","",$D15*$E15),"") | G15: =IFERROR(IF($C15="","",$F15-$H15),"") | H15: =IFERROR(IF($C15="","",$F15/(1+INICIO!$C$5)),"") | I15: =IFERROR(IF($C15="","",$D15*INDEX(PRODUCTOS!$D$5:$D$44,MATCH($C15,PRODUCTOS!$B$5:$B$44,0))),"") | J15: =IFERROR(IF($C15="","",$H15-$I15),"")
B16: =IF($A16="","",TEXT($A16,"YYYY-MM")) | E16: =IFERROR(IF($C16="","",INDEX(PRODUCTOS!$E$5:$E$44,MATCH($C16,PRODUCTOS!$B$5:$B$44,0))),"") | F16: =IFERROR(IF($C16="","",$D16*$E16),"") | G16: =IFERROR(IF($C16="","",$F16-$H16),"") | H16: =IFERROR(IF($C16="","",$F16/(1+INICIO!$C$5)),"") | I16: =IFERROR(IF($C16="","",$D16*INDEX(PRODUCTOS!$D$5:$D$44,MATCH($C16,PRODUCTOS!$B$5:$B$44,0))),"") | J16: =IFERROR(IF($C16="","",$H16-$I16),"")
B17: =IF($A17="","",TEXT($A17,"YYYY-MM")) | E17: =IFERROR(IF($C17="","",INDEX(PRODUCTOS!$E$5:$E$44,MATCH($C17,PRODUCTOS!$B$5:$B$44,0))),"") | F17: =IFERROR(IF($C17="","",$D17*$E17),"") | G17: =IFERROR(IF($C17="","",$F17-$H17),"") | H17: =IFERROR(IF($C17="","",$F17/(1+INICIO!$C$5)),"") | I17: =IFERROR(IF($C17="","",$D17*INDEX(PRODUCTOS!$D$5:$D$44,MATCH($C17,PRODUCTOS!$B$5:$B$44,0))),"") | J17: =IFERROR(IF($C17="","",$H17-$I17),"")
... B504: =IF($A504="","",TEXT($A504,"YYYY-MM")) | E504: =IFERROR(IF($C504="","",INDEX(PRODUCTOS!$E$5:$E$44,MATCH($C504,PRODUCTOS!$B$5:$B$44,0))),"") | F504: =IFERROR(IF($C504="","",$D504*$E504),"") | G504: =IFERROR(IF($C504="","",$F504-$H504),"") | H504: =IFERROR(IF($C504="","",$F504/(1+INICIO!$C$5)),"") | I504: =IFERROR(IF($C504="","",$D504*INDEX(PRODUCTOS!$D$5:$D$44,MATCH($C504,PRODUCTOS!$B$5:$B$44,0))),"") | J504: =IFERROR(IF($C504="","",$H504-$I504),"")

Sheet GASTOS
A1: GASTOS
A2: Todo lo que sale del negocio. Si no lo registras, tu utilidad es mentira.
A4: Fecha | B4: Mes | C4: Categoria | D4: Detalle / Proveedor | E4: Monto | F4: Tipo | G4: Forma de pago | H4: ¿Sale de caja?
A5: 46280 | B5: =IF($A5="","",TEXT($A5,"YYYY-MM")) | C5: Insumos | D5: Compra de jarabes - proveedor local | E5: 40 | F5: Variable | G5: Efectivo | H5: SI
B6: =IF($A6="","",TEXT($A6,"YYYY-MM"))
B7: =IF($A7="","",TEXT($A7,"YYYY-MM"))
B8: =IF($A8="","",TEXT($A8,"YYYY-MM"))
B9: =IF($A9="","",TEXT($A9,"YYYY-MM"))
B10: =IF($A10="","",TEXT($A10,"YYYY-MM"))
B11: =IF($A11="","",TEXT($A11,"YYYY-MM"))
B12: =IF($A12="","",TEXT($A12,"YYYY-MM"))
B13: =IF($A13="","",TEXT($A13,"YYYY-MM"))
B14: =IF($A14="","",TEXT($A14,"YYYY-MM"))
B15: =IF($A15="","",TEXT($A15,"YYYY-MM"))
B16: =IF($A16="","",TEXT($A16,"YYYY-MM"))
B17: =IF($A17="","",TEXT($A17,"YYYY-MM"))
... B304: =IF($A304="","",TEXT($A304,"YYYY-MM"))

Sheet CAJA
A1: CIERRE DE CAJA DIARIO
A2: Al cerrar: pon el fondo con el que abriste y cuenta el efectivo real. El descuadre te dice si algo se fue.
A4: Fecha | B4: Fondo apertura | C4: Ventas EFECTIVO | D4: Ventas TRANSFERENCIA | E4: Ventas PAYPHONE/Tarjeta | F4: Gastos en efectivo | G4: Retiros | H4: EFECTIVO TEORICO | I4: Efectivo contado | J4: DESCUADRE
A5: 46280 | B5: 20 | C5: =IF($A5="","",SUMIFS(VENTAS!$F$5:$F$504,VENTAS!$A$5:$A$504,$A5,VENTAS!$K$5:$K$504,"Efectivo")) | D5: =IF($A5="","",SUMIFS(VENTAS!$F$5:$F$504,VENTAS!$A$5:$A$504,$A5,VENTAS!$K$5:$K$504,"Transferencia")) | E5: =IF($A5="","",SUMIFS(VENTAS!$F$5:$F$504,VENTAS!$A$5:$A$504,$A5,VENTAS!$K$5:$K$504,"PayPhone")+SUMIFS(VENTAS!$F$5:$F$504,VENTAS!$A$5:$A$504,$A5,VENTAS!$K$5:$K$504,"Tarjeta")) | F5: =IF($A5="","",SUMIFS(GASTOS!$E$5:$E$304,GASTOS!$A$5:$A$304,$A5,GASTOS!$G$5:$G$304,"Efectivo",GASTOS!$H$5:$H$304,"SI")) | H5: =IF($A5="","",$B5+$C5-$F5-N($G5)) | J5: =IF($A5="","",IF($I5="","",$I5-$H5))
C6: =IF($A6="","",SUMIFS(VENTAS!$F$5:$F$504,VENTAS!$A$5:$A$504,$A6,VENTAS!$K$5:$K$504,"Efectivo")) | D6: =IF($A6="","",SUMIFS(VENTAS!$F$5:$F$504,VENTAS!$A$5:$A$504,$A6,VENTAS!$K$5:$K$504,"Transferencia")) | E6: =IF($A6="","",SUMIFS(VENTAS!$F$5:$F$504,VENTAS!$A$5:$A$504,$A6,VENTAS!$K$5:$K$504,"PayPhone")+SUMIFS(VENTAS!$F$5:$F$504,VENTAS!$A$5:$A$504,$A6,VENTAS!$K$5:$K$504,"Tarjeta")) | F6: =IF($A6="","",SUMIFS(GASTOS!$E$5:$E$304,GASTOS!$A$5:$A$304,$A6,GASTOS!$G$5:$G$304,"Efectivo",GASTOS!$H$5:$H$304,"SI")) | H6: =IF($A6="","",$B6+$C6-$F6-N($G6)) | J6: =IF($A6="","",IF($I6="","",$I6-$H6))
C7: =IF($A7="","",SUMIFS(VENTAS!$F$5:$F$504,VENTAS!$A$5:$A$504,$A7,VENTAS!$K$5:$K$504,"Efectivo")) | D7: =IF($A7="","",SUMIFS(VENTAS!$F$5:$F$504,VENTAS!$A$5:$A$504,$A7,VENTAS!$K$5:$K$504,"Transferencia")) | E7: =IF($A7="","",SUMIFS(VENTAS!$F$5:$F$504,VENTAS!$A$5:$A$504,$A7,VENTAS!$K$5:$K$504,"PayPhone")+SUMIFS(VENTAS!$F$5:$F$504,VENTAS!$A$5:$A$504,$A7,VENTAS!$K$5:$K$504,"Tarjeta")) | F7: =IF($A7="","",SUMIFS(GASTOS!$E$5:$E$304,GASTOS!$A$5:$A$304,$A7,GASTOS!$G$5:$G$304,"Efectivo",GASTOS!$H$5:$H$304,"SI")) | H7: =IF($A7="","",$B7+$C7-$F7-N($G7)) | J7: =IF($A7="","",IF($I7="","",$I7-$H7))
C8: =IF($A8="","",SUMIFS(VENTAS!$F$5:$F$504,VENTAS!$A$5:$A$504,$A8,VENTAS!$K$5:$K$504,"Efectivo")) | D8: =IF($A8="","",SUMIFS(VENTAS!$F$5:$F$504,VENTAS!$A$5:$A$504,$A8,VENTAS!$K$5:$K$504,"Transferencia")) | E8: =IF($A8="","",SUMIFS(VENTAS!$F$5:$F$504,VENTAS!$A$5:$A$504,$A8,VENTAS!$K$5:$K$504,"PayPhone")+SUMIFS(VENTAS!$F$5:$F$504,VENTAS!$A$5:$A$504,$A8,VENTAS!$K$5:$K$504,"Tarjeta")) | F8: =IF($A8="","",SUMIFS(GASTOS!$E$5:$E$304,GASTOS!$A$5:$A$304,$A8,GASTOS!$G$5:$G$304,"Efectivo",GASTOS!$H$5:$H$304,"SI")) | H8: =IF($A8="","",$B8+$C8-$F8-N($G8)) | J8: =IF($A8="","",IF($I8="","",$I8-$H8))
C9: =IF($A9="","",SUMIFS(VENTAS!$F$5:$F$504,VENTAS!$A$5:$A$504,$A9,VENTAS!$K$5:$K$504,"Efectivo")) | D9: =IF($A9="","",SUMIFS(VENTAS!$F$5:$F$504,VENTAS!$A$5:$A$504,$A9,VENTAS!$K$5:$K$504,"Transferencia")) | E9: =IF($A9="","",SUMIFS(VENTAS!$F$5:$F$504,VENTAS!$A$5:$A$504,$A9,VENTAS!$K$5:$K$504,"PayPhone")+SUMIFS(VENTAS!$F$5:$F$504,VENTAS!$A$5:$A$504,$A9,VENTAS!$K$5:$K$504,"Tarjeta")) | F9: =IF($A9="","",SUMIFS(GASTOS!$E$5:$E$304,GASTOS!$A$5:$A$304,$A9,GASTOS!$G$5:$G$304,"Efectivo",GASTOS!$H$5:$H$304,"SI")) | H9: =IF($A9="","",$B9+$C9-$F9-N($G9)) | J9: =IF($A9="","",IF($I9="","",$I9-$H9))
C10: =IF($A10="","",SUMIFS(VENTAS!$F$5:$F$504,VENTAS!$A$5:$A$504,$A10,VENTAS!$K$5:$K$504,"Efectivo")) | D10: =IF($A10="","",SUMIFS(VENTAS!$F$5:$F$504,VENTAS!$A$5:$A$504,$A10,VENTAS!$K$5:$K$504,"Transferencia")) | E10: =IF($A10="","",SUMIFS(VENTAS!$F$5:$F$504,VENTAS!$A$5:$A$504,$A10,VENTAS!$K$5:$K$504,"PayPhone")+SUMIFS(VENTAS!$F$5:$F$504,VENTAS!$A$5:$A$504,$A10,VENTAS!$K$5:$K$504,"Tarjeta")) | F10: =IF($A10="","",SUMIFS(GASTOS!$E$5:$E$304,GASTOS!$A$5:$A$304,$A10,GASTOS!$G$5:$G$304,"Efectivo",GASTOS!$H$5:$H$304,"SI")) | H10: =IF($A10="","",$B10+$C10-$F10-N($G10)) | J10: =IF($A10="","",IF($I10="","",$I10-$H10))
C11: =IF($A11="","",SUMIFS(VENTAS!$F$5:$F$504,VENTAS!$A$5:$A$504,$A11,VENTAS!$K$5:$K$504,"Efectivo")) | D11: =IF($A11="","",SUMIFS(VENTAS!$F$5:$F$504,VENTAS!$A$5:$A$504,$A11,VENTAS!$K$5:$K$504,"Transferencia")) | E11: =IF($A11="","",SUMIFS(VENTAS!$F$5:$F$504,VENTAS!$A$5:$A$504,$A11,VENTAS!$K$5:$K$504,"PayPhone")+SUMIFS(VENTAS!$F$5:$F$504,VENTAS!$A$5:$A$504,$A11,VENTAS!$K$5:$K$504,"Tarjeta")) | F11: =IF($A11="","",SUMIFS(GASTOS!$E$5:$E$304,GASTOS!$A$5:$A$304,$A11,GASTOS!$G$5:$G$304,"Efectivo",GASTOS!$H$5:$H$304,"SI")) | H11: =IF($A11="","",$B11+$C11-$F11-N($G11)) | J11: =IF($A11="","",IF($I11="","",$I11-$H11))
C12: =IF($A12="","",SUMIFS(VENTAS!$F$5:$F$504,VENTAS!$A$5:$A$504,$A12,VENTAS!$K$5:$K$504,"Efectivo")) | D12: =IF($A12="","",SUMIFS(VENTAS!$F$5:$F$504,VENTAS!$A$5:$A$504,$A12,VENTAS!$K$5:$K$504,"Transferencia")) | E12: =IF($A12="","",SUMIFS(VENTAS!$F$5:$F$504,VENTAS!$A$5:$A$504,$A12,VENTAS!$K$5:$K$504,"PayPhone")+SUMIFS(VENTAS!$F$5:$F$504,VENTAS!$A$5:$A$504,$A12,VENTAS!$K$5:$K$504,"Tarjeta")) | F12: =IF($A12="","",SUMIFS(GASTOS!$E$5:$E$304,GASTOS!$A$5:$A$304,$A12,GASTOS!$G$5:$G$304,"Efectivo",GASTOS!$H$5:$H$304,"SI")) | H12: =IF($A12="","",$B12+$C12-$F12-N($G12)) | J12: =IF($A12="","",IF($I12="","",$I12-$H12))
C13: =IF($A13="","",SUMIFS(VENTAS!$F$5:$F$504,VENTAS!$A$5:$A$504,$A13,VENTAS!$K$5:$K$504,"Efectivo")) | D13: =IF($A13="","",SUMIFS(VENTAS!$F$5:$F$504,VENTAS!$A$5:$A$504,$A13,VENTAS!$K$5:$K$504,"Transferencia")) | E13: =IF($A13="","",SUMIFS(VENTAS!$F$5:$F$504,VENTAS!$A$5:$A$504,$A13,VENTAS!$K$5:$K$504,"PayPhone")+SUMIFS(VENTAS!$F$5:$F$504,VENTAS!$A$5:$A$504,$A13,VENTAS!$K$5:$K$504,"Tarjeta")) | F13: =IF($A13="","",SUMIFS(GASTOS!$E$5:$E$304,GASTOS!$A$5:$A$304,$A13,GASTOS!$G$5:$G$304,"Efectivo",GASTOS!$H$5:$H$304,"SI")) | H13: =IF($A13="","",$B13+$C13-$F13-N($G13)) | J13: =IF($A13="","",IF($I13="","",$I13-$H13))
C14: =IF($A14="","",SUMIFS(VENTAS!$F$5:$F$504,VENTAS!$A$5:$A$504,$A14,VENTAS!$K$5:$K$504,"Efectivo")) | D14: =IF($A14="","",SUMIFS(VENTAS!$F$5:$F$504,VENTAS!$A$5:$A$504,$A14,VENTAS!$K$5:$K$504,"Transferencia")) | E14: =IF($A14="","",SUMIFS(VENTAS!$F$5:$F$504,VENTAS!$A$5:$A$504,$A14,VENTAS!$K$5:$K$504,"PayPhone")+SUMIFS(VENTAS!$F$5:$F$504,VENTAS!$A$5:$A$504,$A14,VENTAS!$K$5:$K$504,"Tarjeta")) | F14: =IF($A14="","",SUMIFS(GASTOS!$E$5:$E$304,GASTOS!$A$5:$A$304,$A14,GASTOS!$G$5:$G$304,"Efectivo",GASTOS!$H$5:$H$304,"SI")) | H14: =IF($A14="","",$B14+$C14-$F14-N($G14)) | J14: =IF($A14="","",IF($I14="","",$I14-$H14))
C15: =IF($A15="","",SUMIFS(VENTAS!$F$5:$F$504,VENTAS!$A$5:$A$504,$A15,VENTAS!$K$5:$K$504,"Efectivo")) | D15: =IF($A15="","",SUMIFS(VENTAS!$F$5:$F$504,VENTAS!$A$5:$A$504,$A15,VENTAS!$K$5:$K$504,"Transferencia")) | E15: =IF($A15="","",SUMIFS(VENTAS!$F$5:$F$504,VENTAS!$A$5:$A$504,$A15,VENTAS!$K$5:$K$504,"PayPhone")+SUMIFS(VENTAS!$F$5:$F$504,VENTAS!$A$5:$A$504,$A15,VENTAS!$K$5:$K$504,"Tarjeta")) | F15: =IF($A15="","",SUMIFS(GASTOS!$E$5:$E$304,GASTOS!$A$5:$A$304,$A15,GASTOS!$G$5:$G$304,"Efectivo",GASTOS!$H$5:$H$304,"SI")) | H15: =IF($A15="","",$B15+$C15-$F15-N($G15)) | J15: =IF($A15="","",IF($I15="","",$I15-$H15))
C16: =IF($A16="","",SUMIFS(VENTAS!$F$5:$F$504,VENTAS!$A$5:$A$504,$A16,VENTAS!$K$5:$K$504,"Efectivo")) | D16: =IF($A16="","",SUMIFS(VENTAS!$F$5:$F$504,VENTAS!$A$5:$A$504,$A16,VENTAS!$K$5:$K$504,"Transferencia")) | E16: =IF($A16="","",SUMIFS(VENTAS!$F$5:$F$504,VENTAS!$A$5:$A$504,$A16,VENTAS!$K$5:$K$504,"PayPhone")+SUMIFS(VENTAS!$F$5:$F$504,VENTAS!$A$5:$A$504,$A16,VENTAS!$K$5:$K$504,"Tarjeta")) | F16: =IF($A16="","",SUMIFS(GASTOS!$E$5:$E$304,GASTOS!$A$5:$A$304,$A16,GASTOS!$G$5:$G$304,"Efectivo",GASTOS!$H$5:$H$304,"SI")) | H16: =IF($A16="","",$B16+$C16-$F16-N($G16)) | J16: =IF($A16="","",IF($I16="","",$I16-$H16))
C17: =IF($A17="","",SUMIFS(VENTAS!$F$5:$F$504,VENTAS!$A$5:$A$504,$A17,VENTAS!$K$5:$K$504,"Efectivo")) | D17: =IF($A17="","",SUMIFS(VENTAS!$F$5:$F$504,VENTAS!$A$5:$A$504,$A17,VENTAS!$K$5:$K$504,"Transferencia")) | E17: =IF($A17="","",SUMIFS(VENTAS!$F$5:$F$504,VENTAS!$A$5:$A$504,$A17,VENTAS!$K$5:$K$504,"PayPhone")+SUMIFS(VENTAS!$F$5:$F$504,VENTAS!$A$5:$A$504,$A17,VENTAS!$K$5:$K$504,"Tarjeta")) | F17: =IF($A17="","",SUMIFS(GASTOS!$E$5:$E$304,GASTOS!$A$5:$A$304,$A17,GASTOS!$G$5:$G$304,"Efectivo",GASTOS!$H$5:$H$304,"SI")) | H17: =IF($A17="","",$B17+$C17-$F17-N($G17)) | J17: =IF($A17="","",IF($I17="","",$I17-$H17))
... C204: =IF($A204="","",SUMIFS(VENTAS!$F$5:$F$504,VENTAS!$A$5:$A$504,$A204,VENTAS!$K$5:$K$504,"Efectivo")) | D204: =IF($A204="","",SUMIFS(VENTAS!$F$5:$F$504,VENTAS!$A$5:$A$504,$A204,VENTAS!$K$5:$K$504,"Transferencia")) | E204: =IF($A204="","",SUMIFS(VENTAS!$F$5:$F$504,VENTAS!$A$5:$A$504,$A204,VENTAS!$K$5:$K$504,"PayPhone")+SUMIFS(VENTAS!$F$5:$F$504,VENTAS!$A$5:$A$504,$A204,VENTAS!$K$5:$K$504,"Tarjeta")) | F204: =IF($A204="","",SUMIFS(GASTOS!$E$5:$E$304,GASTOS!$A$5:$A$304,$A204,GASTOS!$G$5:$G$304,"Efectivo",GASTOS!$H$5:$H$304,"SI")) | H204: =IF($A204="","",$B204+$C204-$F204-N($G204)) | J204: =IF($A204="","",IF($I204="","",$I204-$H204))
B206: Descuadre negativo = falta plata. Positivo = sobra (mal cobrado o venta no registrada). Ambos son problema.

Sheet PRODUCTOS
A1: PRODUCTOS Y PRECIOS
A2: Precios de carta CON IVA incluido. El sistema descuenta el IVA para mostrarte tu utilidad REAL.
A4: ID | B4: Producto | C4: Categoria | D4: COSTO | E4: PVP c/IVA | F4: IVA % | G4: Ingreso neto (sin IVA) | H4: UTILIDAD | I4: MARGEN | J4: Margen objetivo | K4: PVP sugerido c/IVA | L4: ESTADO
A5: 1 | B5: Coco s/alcohol | C5: Granizado maquina | D5: =IF($B5="","",SUMIFS(RECETAS!$G$5:$G$254,RECETAS!$B$5:$B$254,$B5)+IFERROR(INDEX(COMBOS!$K$5:$K$24,MATCH($B5,COMBOS!$B$5:$B$24,0)),0)) | E5: 1.5 | F5: =IF($B5="","",INICIO!$C$5) | G5: =IFERROR(IF($B5="","",$E5/(1+$F5)),"") | H5: =IFERROR(IF($B5="","",$G5-$D5),"") | I5: =IFERROR(IF($B5="","",$H5/$G5),"") | J5: =IF($B5="","",INICIO!$C$9) | K5: =IFERROR(IF($B5="","",$D5/(1-$J5)*(1+$F5)),"") | L5: =IF($B5="","",IF($I5<0,"PIERDE PLATA",IF($I5<0.5,"MARGEN BAJO",IF($I5<0.65,"ACEPTABLE","EXCELENTE"))))
A6: 2 | B6: Frutos Rojos s/alcohol | C6: Granizado maquina | D6: =IF($B6="","",SUMIFS(RECETAS!$G$5:$G$254,RECETAS!$B$5:$B$254,$B6)+IFERROR(INDEX(COMBOS!$K$5:$K$24,MATCH($B6,COMBOS!$B$5:$B$24,0)),0)) | E6: 1.5 | F6: =IF($B6="","",INICIO!$C$5) | G6: =IFERROR(IF($B6="","",$E6/(1+$F6)),"") | H6: =IFERROR(IF($B6="","",$G6-$D6),"") | I6: =IFERROR(IF($B6="","",$H6/$G6),"") | J6: =IF($B6="","",INICIO!$C$9) | K6: =IFERROR(IF($B6="","",$D6/(1-$J6)*(1+$F6)),"") | L6: =IF($B6="","",IF($I6<0,"PIERDE PLATA",IF($I6<0.5,"MARGEN BAJO",IF($I6<0.65,"ACEPTABLE","EXCELENTE"))))
A7: 3 | B7: Maracuya s/alcohol | C7: Granizado maquina | D7: =IF($B7="","",SUMIFS(RECETAS!$G$5:$G$254,RECETAS!$B$5:$B$254,$B7)+IFERROR(INDEX(COMBOS!$K$5:$K$24,MATCH($B7,COMBOS!$B$5:$B$24,0)),0)) | E7: 1.5 | F7: =IF($B7="","",INICIO!$C$5) | G7: =IFERROR(IF($B7="","",$E7/(1+$F7)),"") | H7: =IFERROR(IF($B7="","",$G7-$D7),"") | I7: =IFERROR(IF($B7="","",$H7/$G7),"") | J7: =IF($B7="","",INICIO!$C$9) | K7: =IFERROR(IF($B7="","",$D7/(1-$J7)*(1+$F7)),"") | L7: =IF($B7="","",IF($I7<0,"PIERDE PLATA",IF($I7<0.5,"MARGEN BAJO",IF($I7<0.65,"ACEPTABLE","EXCELENTE"))))
A8: 4 | B8: Naranja s/alcohol | C8: Granizado maquina | D8: =IF($B8="","",SUMIFS(RECETAS!$G$5:$G$254,RECETAS!$B$5:$B$254,$B8)+IFERROR(INDEX(COMBOS!$K$5:$K$24,MATCH($B8,COMBOS!$B$5:$B$24,0)),0)) | E8: 1.5 | F8: =IF($B8="","",INICIO!$C$5) | G8: =IFERROR(IF($B8="","",$E8/(1+$F8)),"") | H8: =IFERROR(IF($B8="","",$G8-$D8),"") | I8: =IFERROR(IF($B8="","",$H8/$G8),"") | J8: =IF($B8="","",INICIO!$C$9) | K8: =IFERROR(IF($B8="","",$D8/(1-$J8)*(1+$F8)),"") | L8: =IF($B8="","",IF($I8<0,"PIERDE PLATA",IF($I8<0.5,"MARGEN BAJO",IF($I8<0.65,"ACEPTABLE","EXCELENTE"))))
A9: 5 | B9: Coco c/alcohol | C9: Granizado maquina | D9: =IF($B9="","",SUMIFS(RECETAS!$G$5:$G$254,RECETAS!$B$5:$B$254,$B9)+IFERROR(INDEX(COMBOS!$K$5:$K$24,MATCH($B9,COMBOS!$B$5:$B$24,0)),0)) | E9: 2 | F9: =IF($B9="","",INICIO!$C$5) | G9: =IFERROR(IF($B9="","",$E9/(1+$F9)),"") | H9: =IFERROR(IF($B9="","",$G9-$D9),"") | I9: =IFERROR(IF($B9="","",$H9/$G9),"") | J9: =IF($B9="","",INICIO!$C$9) | K9: =IFERROR(IF($B9="","",$D9/(1-$J9)*(1+$F9)),"") | L9: =IF($B9="","",IF($I9<0,"PIERDE PLATA",IF($I9<0.5,"MARGEN BAJO",IF($I9<0.65,"ACEPTABLE","EXCELENTE"))))
A10: 6 | B10: Frutos Rojos c/alcohol | C10: Granizado maquina | D10: =IF($B10="","",SUMIFS(RECETAS!$G$5:$G$254,RECETAS!$B$5:$B$254,$B10)+IFERROR(INDEX(COMBOS!$K$5:$K$24,MATCH($B10,COMBOS!$B$5:$B$24,0)),0)) | E10: 2 | F10: =IF($B10="","",INICIO!$C$5) | G10: =IFERROR(IF($B10="","",$E10/(1+$F10)),"") | H10: =IFERROR(IF($B10="","",$G10-$D10),"") | I10: =IFERROR(IF($B10="","",$H10/$G10),"") | J10: =IF($B10="","",INICIO!$C$9) | K10: =IFERROR(IF($B10="","",$D10/(1-$J10)*(1+$F10)),"") | L10: =IF($B10="","",IF($I10<0,"PIERDE PLATA",IF($I10<0.5,"MARGEN BAJO",IF($I10<0.65,"ACEPTABLE","EXCELENTE"))))
A11: 7 | B11: Maracuya c/alcohol | C11: Granizado maquina | D11: =IF($B11="","",SUMIFS(RECETAS!$G$5:$G$254,RECETAS!$B$5:$B$254,$B11)+IFERROR(INDEX(COMBOS!$K$5:$K$24,MATCH($B11,COMBOS!$B$5:$B$24,0)),0)) | E11: 2 | F11: =IF($B11="","",INICIO!$C$5) | G11: =IFERROR(IF($B11="","",$E11/(1+$F11)),"") | H11: =IFERROR(IF($B11="","",$G11-$D11),"") | I11: =IFERROR(IF($B11="","",$H11/$G11),"") | J11: =IF($B11="","",INICIO!$C$9) | K11: =IFERROR(IF($B11="","",$D11/(1-$J11)*(1+$F11)),"") | L11: =IF($B11="","",IF($I11<0,"PIERDE PLATA",IF($I11<0.5,"MARGEN BAJO",IF($I11<0.65,"ACEPTABLE","EXCELENTE"))))
A12: 8 | B12: Naranja c/alcohol | C12: Granizado maquina | D12: =IF($B12="","",SUMIFS(RECETAS!$G$5:$G$254,RECETAS!$B$5:$B$254,$B12)+IFERROR(INDEX(COMBOS!$K$5:$K$24,MATCH($B12,COMBOS!$B$5:$B$24,0)),0)) | E12: 2 | F12: =IF($B12="","",INICIO!$C$5) | G12: =IFERROR(IF($B12="","",$E12/(1+$F12)),"") | H12: =IFERROR(IF($B12="","",$G12-$D12),"") | I12: =IFERROR(IF($B12="","",$H12/$G12),"") | J12: =IF($B12="","",INICIO!$C$9) | K12: =IFERROR(IF($B12="","",$D12/(1-$J12)*(1+$F12)),"") | L12: =IF($B12="","",IF($I12<0,"PIERDE PLATA",IF($I12<0.5,"MARGEN BAJO",IF($I12<0.65,"ACEPTABLE","EXCELENTE"))))
A13: 9 | B13: Oreo s/alcohol | C13: Granizado especial | D13: =IF($B13="","",SUMIFS(RECETAS!$G$5:$G$254,RECETAS!$B$5:$B$254,$B13)+IFERROR(INDEX(COMBOS!$K$5:$K$24,MATCH($B13,COMBOS!$B$5:$B$24,0)),0)) | E13: 3 | F13: =IF($B13="","",INICIO!$C$5) | G13: =IFERROR(IF($B13="","",$E13/(1+$F13)),"") | H13: =IFERROR(IF($B13="","",$G13-$D13),"") | I13: =IFERROR(IF($B13="","",$H13/$G13),"") | J13: =IF($B13="","",INICIO!$C$9) | K13: =IFERROR(IF($B13="","",$D13/(1-$J13)*(1+$F13)),"") | L13: =IF($B13="","",IF($I13<0,"PIERDE PLATA",IF($I13<0.5,"MARGEN BAJO",IF($I13<0.65,"ACEPTABLE","EXCELENTE"))))
A14: 10 | B14: Nutella s/alcohol | C14: Granizado especial | D14: =IF($B14="","",SUMIFS(RECETAS!$G$5:$G$254,RECETAS!$B$5:$B$254,$B14)+IFERROR(INDEX(COMBOS!$K$5:$K$24,MATCH($B14,COMBOS!$B$5:$B$24,0)),0)) | E14: 3 | F14: =IF($B14="","",INICIO!$C$5) | G14: =IFERROR(IF($B14="","",$E14/(1+$F14)),"") | H14: =IFERROR(IF($B14="","",$G14-$D14),"") | I14: =IFERROR(IF($B14="","",$H14/$G14),"") | J14: =IF($B14="","",INICIO!$C$9) | K14: =IFERROR(IF($B14="","",$D14/(1-$J14)*(1+$F14)),"") | L14: =IF($B14="","",IF($I14<0,"PIERDE PLATA",IF($I14<0.5,"MARGEN BAJO",IF($I14<0.65,"ACEPTABLE","EXCELENTE"))))
A15: 11 | B15: Cafe s/alcohol | C15: Granizado especial | D15: =IF($B15="","",SUMIFS(RECETAS!$G$5:$G$254,RECETAS!$B$5:$B$254,$B15)+IFERROR(INDEX(COMBOS!$K$5:$K$24,MATCH($B15,COMBOS!$B$5:$B$24,0)),0)) | E15: 3 | F15: =IF($B15="","",INICIO!$C$5) | G15: =IFERROR(IF($B15="","",$E15/(1+$F15)),"") | H15: =IFERROR(IF($B15="","",$G15-$D15),"") | I15: =IFERROR(IF($B15="","",$H15/$G15),"") | J15: =IF($B15="","",INICIO!$C$9) | K15: =IFERROR(IF($B15="","",$D15/(1-$J15)*(1+$F15)),"") | L15: =IF($B15="","",IF($I15<0,"PIERDE PLATA",IF($I15<0.5,"MARGEN BAJO",IF($I15<0.65,"ACEPTABLE","EXCELENTE"))))
A16: 12 | B16: Oreo c/alcohol | C16: Granizado especial | D16: =IF($B16="","",SUMIFS(RECETAS!$G$5:$G$254,RECETAS!$B$5:$B$254,$B16)+IFERROR(INDEX(COMBOS!$K$5:$K$24,MATCH($B16,COMBOS!$B$5:$B$24,0)),0)) | E16: 3.5 | F16: =IF($B16="","",INICIO!$C$5) | G16: =IFERROR(IF($B16="","",$E16/(1+$F16)),"") | H16: =IFERROR(IF($B16="","",$G16-$D16),"") | I16: =IFERROR(IF($B16="","",$H16/$G16),"") | J16: =IF($B16="","",INICIO!$C$9) | K16: =IFERROR(IF($B16="","",$D16/(1-$J16)*(1+$F16)),"") | L16: =IF($B16="","",IF($I16<0,"PIERDE PLATA",IF($I16<0.5,"MARGEN BAJO",IF($I16<0.65,"ACEPTABLE","EXCELENTE"))))
... A24: 20 | B24: Combo Solo | C24: Combo | D24: =IF($B24="","",SUMIFS(RECETAS!$G$5:$G$254,RECETAS!$B$5:$B$254,$B24)+IFERROR(INDEX(COMBOS!$K$5:$K$24,MATCH($B24,COMBOS!$B$5:$B$24,0)),0)) | E24: 2.5 | F24: =IF($B24="","",INICIO!$C$5) | G24: =IFERROR(IF($B24="","",$E24/(1+$F24)),"") | H24: =IFERROR(IF($B24="","",$G24-$D24),"") | I24: =IFERROR(IF($B24="","",$H24/$G24),"") | J24: =IF($B24="","",INICIO!$C$9) | K24: =IFERROR(IF($B24="","",$D24/(1-$J24)*(1+$F24)),"") | L24: =IF($B24="","",IF($I24<0,"PIERDE PLATA",IF($I24<0.5,"MARGEN BAJO",IF($I24<0.65,"ACEPTABLE","EXCELENTE"))))
D25: =IF($B25="","",SUMIFS(RECETAS!$G$5:$G$254,RECETAS!$B$5:$B$254,$B25)+IFERROR(INDEX(COMBOS!$K$5:$K$24,MATCH($B25,COMBOS!$B$5:$B$24,0)),0)) | F25: =IF($B25="","",INICIO!$C$5) | G25: =IFERROR(IF($B25="","",$E25/(1+$F25)),"") | H25: =IFERROR(IF($B25="","",$G25-$D25),"") | I25: =IFERROR(IF($B25="","",$H25/$G25),"") | J25: =IF($B25="","",INICIO!$C$9) | K25: =IFERROR(IF($B25="","",$D25/(1-$J25)*(1+$F25)),"") | L25: =IF($B25="","",IF($I25<0,"PIERDE PLATA",IF($I25<0.5,"MARGEN BAJO",IF($I25<0.65,"ACEPTABLE","EXCELENTE"))))
D26: =IF($B26="","",SUMIFS(RECETAS!$G$5:$G$254,RECETAS!$B$5:$B$254,$B26)+IFERROR(INDEX(COMBOS!$K$5:$K$24,MATCH($B26,COMBOS!$B$5:$B$24,0)),0)) | F26: =IF($B26="","",INICIO!$C$5) | G26: =IFERROR(IF($B26="","",$E26/(1+$F26)),"") | H26: =IFERROR(IF($B26="","",$G26-$D26),"") | I26: =IFERROR(IF($B26="","",$H26/$G26),"") | J26: =IF($B26="","",INICIO!$C$9) | K26: =IFERROR(IF($B26="","",$D26/(1-$J26)*(1+$F26)),"") | L26: =IF($B26="","",IF($I26<0,"PIERDE PLATA",IF($I26<0.5,"MARGEN BAJO",IF($I26<0.65,"ACEPTABLE","EXCELENTE"))))
D27: =IF($B27="","",SUMIFS(RECETAS!$G$5:$G$254,RECETAS!$B$5:$B$254,$B27)+IFERROR(INDEX(COMBOS!$K$5:$K$24,MATCH($B27,COMBOS!$B$5:$B$24,0)),0)) | F27: =IF($B27="","",INICIO!$C$5) | G27: =IFERROR(IF($B27="","",$E27/(1+$F27)),"") | H27: =IFERROR(IF($B27="","",$G27-$D27),"") | I27: =IFERROR(IF($B27="","",$H27/$G27),"") | J27: =IF($B27="","",INICIO!$C$9) | K27: =IFERROR(IF($B27="","",$D27/(1-$J27)*(1+$F27)),"") | L27: =IF($B27="","",IF($I27<0,"PIERDE PLATA",IF($I27<0.5,"MARGEN BAJO",IF($I27<0.65,"ACEPTABLE","EXCELENTE"))))
D28: =IF($B28="","",SUMIFS(RECETAS!$G$5:$G$254,RECETAS!$B$5:$B$254,$B28)+IFERROR(INDEX(COMBOS!$K$5:$K$24,MATCH($B28,COMBOS!$B$5:$B$24,0)),0)) | F28: =IF($B28="","",INICIO!$C$5) | G28: =IFERROR(IF($B28="","",$E28/(1+$F28)),"") | H28: =IFERROR(IF($B28="","",$G28-$D28),"") | I28: =IFERROR(IF($B28="","",$H28/$G28),"") | J28: =IF($B28="","",INICIO!$C$9) | K28: =IFERROR(IF($B28="","",$D28/(1-$J28)*(1+$F28)),"") | L28: =IF($B28="","",IF($I28<0,"PIERDE PLATA",IF($I28<0.5,"MARGEN BAJO",IF($I28<0.65,"ACEPTABLE","EXCELENTE"))))
D29: =IF($B29="","",SUMIFS(RECETAS!$G$5:$G$254,RECETAS!$B$5:$B$254,$B29)+IFERROR(INDEX(COMBOS!$K$5:$K$24,MATCH($B29,COMBOS!$B$5:$B$24,0)),0)) | F29: =IF($B29="","",INICIO!$C$5) | G29: =IFERROR(IF($B29="","",$E29/(1+$F29)),"") | H29: =IFERROR(IF($B29="","",$G29-$D29),"") | I29: =IFERROR(IF($B29="","",$H29/$G29),"") | J29: =IF($B29="","",INICIO!$C$9) | K29: =IFERROR(IF($B29="","",$D29/(1-$J29)*(1+$F29)),"") | L29: =IF($B29="","",IF($I29<0,"PIERDE PLATA",IF($I29<0.5,"MARGEN BAJO",IF($I29<0.65,"ACEPTABLE","EXCELENTE"))))
D30: =IF($B30="","",SUMIFS(RECETAS!$G$5:$G$254,RECETAS!$B$5:$B$254,$B30)+IFERROR(INDEX(COMBOS!$K$5:$K$24,MATCH($B30,COMBOS!$B$5:$B$24,0)),0)) | F30: =IF($B30="","",INICIO!$C$5) | G30: =IFERROR(IF($B30="","",$E30/(1+$F30)),"") | H30: =IFERROR(IF($B30="","",$G30-$D30),"") | I30: =IFERROR(IF($B30="","",$H30/$G30),"") | J30: =IF($B30="","",INICIO!$C$9) | K30: =IFERROR(IF($B30="","",$D30/(1-$J30)*(1+$F30)),"") | L30: =IF($B30="","",IF($I30<0,"PIERDE PLATA",IF($I30<0.5,"MARGEN BAJO",IF($I30<0.65,"ACEPTABLE","EXCELENTE"))))
D31: =IF($B31="","",SUMIFS(RECETAS!$G$5:$G$254,RECETAS!$B$5:$B$254,$B31)+IFERROR(INDEX(COMBOS!$K$5:$K$24,MATCH($B31,COMBOS!$B$5:$B$24,0)),0)) | F31: =IF($B31="","",INICIO!$C$5) | G31: =IFERROR(IF($B31="","",$E31/(1+$F31)),"") | H31: =IFERROR(IF($B31="","",$G31-$D31),"") | I31: =IFERROR(IF($B31="","",$H31/$G31),"") | J31: =IF($B31="","",INICIO!$C$9) | K31: =IFERROR(IF($B31="","",$D31/(1-$J31)*(1+$F31)),"") | L31: =IF($B31="","",IF($I31<0,"PIERDE PLATA",IF($I31<0.5,"MARGEN BAJO",IF($I31<0.65,"ACEPTABLE","EXCELENTE"))))
D32: =IF($B32="","",SUMIFS(RECETAS!$G$5:$G$254,RECETAS!$B$5:$B$254,$B32)+IFERROR(INDEX(COMBOS!$K$5:$K$24,MATCH($B32,COMBOS!$B$5:$B$24,0)),0)) | F32: =IF($B32="","",INICIO!$C$5) | G32: =IFERROR(IF($B32="","",$E32/(1+$F32)),"") | H32: =IFERROR(IF($B32="","",$G32-$D32),"") | I32: =IFERROR(IF($B32="","",$H32/$G32),"") | J32: =IF($B32="","",INICIO!$C$9) | K32: =IFERROR(IF($B32="","",$D32/(1-$J32)*(1+$F32)),"") | L32: =IF($B32="","",IF($I32<0,"PIERDE PLATA",IF($I32<0.5,"MARGEN BAJO",IF($I32<0.65,"ACEPTABLE","EXCELENTE"))))
D33: =IF($B33="","",SUMIFS(RECETAS!$G$5:$G$254,RECETAS!$B$5:$B$254,$B33)+IFERROR(INDEX(COMBOS!$K$5:$K$24,MATCH($B33,COMBOS!$B$5:$B$24,0)),0)) | F33: =IF($B33="","",INICIO!$C$5) | G33: =IFERROR(IF($B33="","",$E33/(1+$F33)),"") | H33: =IFERROR(IF($B33="","",$G33-$D33),"") | I33: =IFERROR(IF($B33="","",$H33/$G33),"") | J33: =IF($B33="","",INICIO!$C$9) | K33: =IFERROR(IF($B33="","",$D33/(1-$J33)*(1+$F33)),"") | L33: =IF($B33="","",IF($I33<0,"PIERDE PLATA",IF($I33<0.5,"MARGEN BAJO",IF($I33<0.65,"ACEPTABLE","EXCELENTE"))))
D34: =IF($B34="","",SUMIFS(RECETAS!$G$5:$G$254,RECETAS!$B$5:$B$254,$B34)+IFERROR(INDEX(COMBOS!$K$5:$K$24,MATCH($B34,COMBOS!$B$5:$B$24,0)),0)) | F34: =IF($B34="","",INICIO!$C$5) | G34: =IFERROR(IF($B34="","",$E34/(1+$F34)),"") | H34: =IFERROR(IF($B34="","",$G34-$D34),"") | I34: =IFERROR(IF($B34="","",$H34/$G34),"") | J34: =IF($B34="","",INICIO!$C$9) | K34: =IFERROR(IF($B34="","",$D34/(1-$J34)*(1+$F34)),"") | L34: =IF($B34="","",IF($I34<0,"PIERDE PLATA",IF($I34<0.5,"MARGEN BAJO",IF($I34<0.65,"ACEPTABLE","EXCELENTE"))))
D35: =IF($B35="","",SUMIFS(RECETAS!$G$5:$G$254,RECETAS!$B$5:$B$254,$B35)+IFERROR(INDEX(COMBOS!$K$5:$K$24,MATCH($B35,COMBOS!$B$5:$B$24,0)),0)) | F35: =IF($B35="","",INICIO!$C$5) | G35: =IFERROR(IF($B35="","",$E35/(1+$F35)),"") | H35: =IFERROR(IF($B35="","",$G35-$D35),"") | I35: =IFERROR(IF($B35="","",$H35/$G35),"") | J35: =IF($B35="","",INICIO!$C$9) | K35: =IFERROR(IF($B35="","",$D35/(1-$J35)*(1+$F35)),"") | L35: =IF($B35="","",IF($I35<0,"PIERDE PLATA",IF($I35<0.5,"MARGEN BAJO",IF($I35<0.65,"ACEPTABLE","EXCELENTE"))))
D36: =IF($B36="","",SUMIFS(RECETAS!$G$5:$G$254,RECETAS!$B$5:$B$254,$B36)+IFERROR(INDEX(COMBOS!$K$5:$K$24,MATCH($B36,COMBOS!$B$5:$B$24,0)),0)) | F36: =IF($B36="","",INICIO!$C$5) | G36: =IFERROR(IF($B36="","",$E36/(1+$F36)),"") | H36: =IFERROR(IF($B36="","",$G36-$D36),"") | I36: =IFERROR(IF($B36="","",$H36/$G36),"") | J36: =IF($B36="","",INICIO!$C$9) | K36: =IFERROR(IF($B36="","",$D36/(1-$J36)*(1+$F36)),"") | L36: =IF($B36="","",IF($I36<0,"PIERDE PLATA",IF($I36<0.5,"MARGEN BAJO",IF($I36<0.65,"ACEPTABLE","EXCELENTE"))))
... D44: =IF($B44="","",SUMIFS(RECETAS!$G$5:$G$254,RECETAS!$B$5:$B$254,$B44)+IFERROR(INDEX(COMBOS!$K$5:$K$24,MATCH($B44,COMBOS!$B$5:$B$24,0)),0)) | F44: =IF($B44="","",INICIO!$C$5) | G44: =IFERROR(IF($B44="","",$E44/(1+$F44)),"") | H44: =IFERROR(IF($B44="","",$G44-$D44),"") | I44: =IFERROR(IF($B44="","",$H44/$G44),"") | J44: =IF($B44="","",INICIO!$C$9) | K44: =IFERROR(IF($B44="","",$D44/(1-$J44)*(1+$F44)),"") | L44: =IF($B44="","",IF($I44<0,"PIERDE PLATA",IF($I44<0.5,"MARGEN BAJO",IF($I44<0.65,"ACEPTABLE","EXCELENTE"))))
B46: OJO: con IVA 15%, un granizado de $1.50 te deja $1.30 de ingreso real. El PVP sugerido ya viene con IVA para que lo pongas tal cual en la carta.

Sheet COMBOS
A1: COMBOS
A2: Arma el combo, mira cuanto margen sacrificas ANTES de lanzarlo. Los combos aparecen tambien en PRODUCTOS para poder venderlos.
A4: ID | B4: Nombre del combo | C4: Item 1 | D4: Cant 1 | E4: Item 2 | F4: Cant 2 | G4: Item 3 | H4: Cant 3 | I4: Precio suelto (c/IVA) | J4: PVP combo (c/IVA) | K4: COSTO COMBO | L4: Descuento que das | M4: Margen combo
A5: 1 | B5: Combo Pareja | C5: Coco c/alcohol | D5: 2 | E5: Papas en cono natural | F5: 1 | I5: =IF($B5="","",IFERROR(INDEX(PRODUCTOS!$E$5:$E$44,MATCH($C5,PRODUCTOS!$B$5:$B$44,0))*N($D5),0)+IFERROR(INDEX(PRODUCTOS!$E$5:$E$44,MATCH($E5,PRODUCTOS!$B$5:$B$44,0))*N($F5),0)+IFERROR(INDEX(PRODUCTOS!$E$5:$E$44,MATCH($G5,PRODUCTOS!$B$5:$B$44,0))*N($H5),0)) | J5: 5 | K5: =IF($B5="","",IFERROR(SUMIFS(RECETAS!$G$5:$G$254,RECETAS!$B$5:$B$254,$C5)*N($D5),0)+IFERROR(SUMIFS(RECETAS!$G$5:$G$254,RECETAS!$B$5:$B$254,$E5)*N($F5),0)+IFERROR(SUMIFS(RECETAS!$G$5:$G$254,RECETAS!$B$5:$B$254,$G5)*N($H5),0)) | L5: =IFERROR(IF($B5="","",($I5-$J5)/$I5),"") | M5: =IFERROR(IF($B5="","",($J5/(1+INICIO!$C$5)-$K5)/($J5/(1+INICIO!$C$5))),"")
A6: 2 | B6: Combo Amigos (4 granizados) | C6: Coco s/alcohol | D6: 4 | I6: =IF($B6="","",IFERROR(INDEX(PRODUCTOS!$E$5:$E$44,MATCH($C6,PRODUCTOS!$B$5:$B$44,0))*N($D6),0)+IFERROR(INDEX(PRODUCTOS!$E$5:$E$44,MATCH($E6,PRODUCTOS!$B$5:$B$44,0))*N($F6),0)+IFERROR(INDEX(PRODUCTOS!$E$5:$E$44,MATCH($G6,PRODUCTOS!$B$5:$B$44,0))*N($H6),0)) | J6: 5 | K6: =IF($B6="","",IFERROR(SUMIFS(RECETAS!$G$5:$G$254,RECETAS!$B$5:$B$254,$C6)*N($D6),0)+IFERROR(SUMIFS(RECETAS!$G$5:$G$254,RECETAS!$B$5:$B$254,$E6)*N($F6),0)+IFERROR(SUMIFS(RECETAS!$G$5:$G$254,RECETAS!$B$5:$B$254,$G6)*N($H6),0)) | L6: =IFERROR(IF($B6="","",($I6-$J6)/$I6),"") | M6: =IFERROR(IF($B6="","",($J6/(1+INICIO!$C$5)-$K6)/($J6/(1+INICIO!$C$5))),"")
A7: 3 | B7: Combo Premium | C7: Oreo s/alcohol | D7: 2 | E7: Papas en cono + salsa | F7: 1 | I7: =IF($B7="","",IFERROR(INDEX(PRODUCTOS!$E$5:$E$44,MATCH($C7,PRODUCTOS!$B$5:$B$44,0))*N($D7),0)+IFERROR(INDEX(PRODUCTOS!$E$5:$E$44,MATCH($E7,PRODUCTOS!$B$5:$B$44,0))*N($F7),0)+IFERROR(INDEX(PRODUCTOS!$E$5:$E$44,MATCH($G7,PRODUCTOS!$B$5:$B$44,0))*N($H7),0)) | J7: 7.5 | K7: =IF($B7="","",IFERROR(SUMIFS(RECETAS!$G$5:$G$254,RECETAS!$B$5:$B$254,$C7)*N($D7),0)+IFERROR(SUMIFS(RECETAS!$G$5:$G$254,RECETAS!$B$5:$B$254,$E7)*N($F7),0)+IFERROR(SUMIFS(RECETAS!$G$5:$G$254,RECETAS!$B$5:$B$254,$G7)*N($H7),0)) | L7: =IFERROR(IF($B7="","",($I7-$J7)/$I7),"") | M7: =IFERROR(IF($B7="","",($J7/(1+INICIO!$C$5)-$K7)/($J7/(1+INICIO!$C$5))),"")
A8: 4 | B8: Combo Solo | C8: Maracuya s/alcohol | D8: 1 | E8: Papas en cono natural | F8: 1 | I8: =IF($B8="","",IFERROR(INDEX(PRODUCTOS!$E$5:$E$44,MATCH($C8,PRODUCTOS!$B$5:$B$44,0))*N($D8),0)+IFERROR(INDEX(PRODUCTOS!$E$5:$E$44,MATCH($E8,PRODUCTOS!$B$5:$B$44,0))*N($F8),0)+IFERROR(INDEX(PRODUCTOS!$E$5:$E$44,MATCH($G8,PRODUCTOS!$B$5:$B$44,0))*N($H8),0)) | J8: 2.5 | K8: =IF($B8="","",IFERROR(SUMIFS(RECETAS!$G$5:$G$254,RECETAS!$B$5:$B$254,$C8)*N($D8),0)+IFERROR(SUMIFS(RECETAS!$G$5:$G$254,RECETAS!$B$5:$B$254,$E8)*N($F8),0)+IFERROR(SUMIFS(RECETAS!$G$5:$G$254,RECETAS!$B$5:$B$254,$G8)*N($H8),0)) | L8: =IFERROR(IF($B8="","",($I8-$J8)/$I8),"") | M8: =IFERROR(IF($B8="","",($J8/(1+INICIO!$C$5)-$K8)/($J8/(1+INICIO!$C$5))),"")
I9: =IF($B9="","",IFERROR(INDEX(PRODUCTOS!$E$5:$E$44,MATCH($C9,PRODUCTOS!$B$5:$B$44,0))*N($D9),0)+IFERROR(INDEX(PRODUCTOS!$E$5:$E$44,MATCH($E9,PRODUCTOS!$B$5:$B$44,0))*N($F9),0)+IFERROR(INDEX(PRODUCTOS!$E$5:$E$44,MATCH($G9,PRODUCTOS!$B$5:$B$44,0))*N($H9),0)) | K9: =IF($B9="","",IFERROR(SUMIFS(RECETAS!$G$5:$G$254,RECETAS!$B$5:$B$254,$C9)*N($D9),0)+IFERROR(SUMIFS(RECETAS!$G$5:$G$254,RECETAS!$B$5:$B$254,$E9)*N($F9),0)+IFERROR(SUMIFS(RECETAS!$G$5:$G$254,RECETAS!$B$5:$B$254,$G9)*N($H9),0)) | L9: =IFERROR(IF($B9="","",($I9-$J9)/$I9),"") | M9: =IFERROR(IF($B9="","",($J9/(1+INICIO!$C$5)-$K9)/($J9/(1+INICIO!$C$5))),"")
I10: =IF($B10="","",IFERROR(INDEX(PRODUCTOS!$E$5:$E$44,MATCH($C10,PRODUCTOS!$B$5:$B$44,0))*N($D10),0)+IFERROR(INDEX(PRODUCTOS!$E$5:$E$44,MATCH($E10,PRODUCTOS!$B$5:$B$44,0))*N($F10),0)+IFERROR(INDEX(PRODUCTOS!$E$5:$E$44,MATCH($G10,PRODUCTOS!$B$5:$B$44,0))*N($H10),0)) | K10: =IF($B10="","",IFERROR(SUMIFS(RECETAS!$G$5:$G$254,RECETAS!$B$5:$B$254,$C10)*N($D10),0)+IFERROR(SUMIFS(RECETAS!$G$5:$G$254,RECETAS!$B$5:$B$254,$E10)*N($F10),0)+IFERROR(SUMIFS(RECETAS!$G$5:$G$254,RECETAS!$B$5:$B$254,$G10)*N($H10),0)) | L10: =IFERROR(IF($B10="","",($I10-$J10)/$I10),"") | M10: =IFERROR(IF($B10="","",($J10/(1+INICIO!$C$5)-$K10)/($J10/(1+INICIO!$C$5))),"")
I11: =IF($B11="","",IFERROR(INDEX(PRODUCTOS!$E$5:$E$44,MATCH($C11,PRODUCTOS!$B$5:$B$44,0))*N($D11),0)+IFERROR(INDEX(PRODUCTOS!$E$5:$E$44,MATCH($E11,PRODUCTOS!$B$5:$B$44,0))*N($F11),0)+IFERROR(INDEX(PRODUCTOS!$E$5:$E$44,MATCH($G11,PRODUCTOS!$B$5:$B$44,0))*N($H11),0)) | K11: =IF($B11="","",IFERROR(SUMIFS(RECETAS!$G$5:$G$254,RECETAS!$B$5:$B$254,$C11)*N($D11),0)+IFERROR(SUMIFS(RECETAS!$G$5:$G$254,RECETAS!$B$5:$B$254,$E11)*N($F11),0)+IFERROR(SUMIFS(RECETAS!$G$5:$G$254,RECETAS!$B$5:$B$254,$G11)*N($H11),0)) | L11: =IFERROR(IF($B11="","",($I11-$J11)/$I11),"") | M11: =IFERROR(IF($B11="","",($J11/(1+INICIO!$C$5)-$K11)/($J11/(1+INICIO!$C$5))),"")
I12: =IF($B12="","",IFERROR(INDEX(PRODUCTOS!$E$5:$E$44,MATCH($C12,PRODUCTOS!$B$5:$B$44,0))*N($D12),0)+IFERROR(INDEX(PRODUCTOS!$E$5:$E$44,MATCH($E12,PRODUCTOS!$B$5:$B$44,0))*N($F12),0)+IFERROR(INDEX(PRODUCTOS!$E$5:$E$44,MATCH($G12,PRODUCTOS!$B$5:$B$44,0))*N($H12),0)) | K12: =IF($B12="","",IFERROR(SUMIFS(RECETAS!$G$5:$G$254,RECETAS!$B$5:$B$254,$C12)*N($D12),0)+IFERROR(SUMIFS(RECETAS!$G$5:$G$254,RECETAS!$B$5:$B$254,$E12)*N($F12),0)+IFERROR(SUMIFS(RECETAS!$G$5:$G$254,RECETAS!$B$5:$B$254,$G12)*N($H12),0)) | L12: =IFERROR(IF($B12="","",($I12-$J12)/$I12),"") | M12: =IFERROR(IF($B12="","",($J12/(1+INICIO!$C$5)-$K12)/($J12/(1+INICIO!$C$5))),"")
I13: =IF($B13="","",IFERROR(INDEX(PRODUCTOS!$E$5:$E$44,MATCH($C13,PRODUCTOS!$B$5:$B$44,0))*N($D13),0)+IFERROR(INDEX(PRODUCTOS!$E$5:$E$44,MATCH($E13,PRODUCTOS!$B$5:$B$44,0))*N($F13),0)+IFERROR(INDEX(PRODUCTOS!$E$5:$E$44,MATCH($G13,PRODUCTOS!$B$5:$B$44,0))*N($H13),0)) | K13: =IF($B13="","",IFERROR(SUMIFS(RECETAS!$G$5:$G$254,RECETAS!$B$5:$B$254,$C13)*N($D13),0)+IFERROR(SUMIFS(RECETAS!$G$5:$G$254,RECETAS!$B$5:$B$254,$E13)*N($F13),0)+IFERROR(SUMIFS(RECETAS!$G$5:$G$254,RECETAS!$B$5:$B$254,$G13)*N($H13),0)) | L13: =IFERROR(IF($B13="","",($I13-$J13)/$I13),"") | M13: =IFERROR(IF($B13="","",($J13/(1+INICIO!$C$5)-$K13)/($J13/(1+INICIO!$C$5))),"")
I14: =IF($B14="","",IFERROR(INDEX(PRODUCTOS!$E$5:$E$44,MATCH($C14,PRODUCTOS!$B$5:$B$44,0))*N($D14),0)+IFERROR(INDEX(PRODUCTOS!$E$5:$E$44,MATCH($E14,PRODUCTOS!$B$5:$B$44,0))*N($F14),0)+IFERROR(INDEX(PRODUCTOS!$E$5:$E$44,MATCH($G14,PRODUCTOS!$B$5:$B$44,0))*N($H14),0)) | K14: =IF($B14="","",IFERROR(SUMIFS(RECETAS!$G$5:$G$254,RECETAS!$B$5:$B$254,$C14)*N($D14),0)+IFERROR(SUMIFS(RECETAS!$G$5:$G$254,RECETAS!$B$5:$B$254,$E14)*N($F14),0)+IFERROR(SUMIFS(RECETAS!$G$5:$G$254,RECETAS!$B$5:$B$254,$G14)*N($H14),0)) | L14: =IFERROR(IF($B14="","",($I14-$J14)/$I14),"") | M14: =IFERROR(IF($B14="","",($J14/(1+INICIO!$C$5)-$K14)/($J14/(1+INICIO!$C$5))),"")
I15: =IF($B15="","",IFERROR(INDEX(PRODUCTOS!$E$5:$E$44,MATCH($C15,PRODUCTOS!$B$5:$B$44,0))*N($D15),0)+IFERROR(INDEX(PRODUCTOS!$E$5:$E$44,MATCH($E15,PRODUCTOS!$B$5:$B$44,0))*N($F15),0)+IFERROR(INDEX(PRODUCTOS!$E$5:$E$44,MATCH($G15,PRODUCTOS!$B$5:$B$44,0))*N($H15),0)) | K15: =IF($B15="","",IFERROR(SUMIFS(RECETAS!$G$5:$G$254,RECETAS!$B$5:$B$254,$C15)*N($D15),0)+IFERROR(SUMIFS(RECETAS!$G$5:$G$254,RECETAS!$B$5:$B$254,$E15)*N($F15),0)+IFERROR(SUMIFS(RECETAS!$G$5:$G$254,RECETAS!$B$5:$B$254,$G15)*N($H15),0)) | L15: =IFERROR(IF($B15="","",($I15-$J15)/$I15),"") | M15: =IFERROR(IF($B15="","",($J15/(1+INICIO!$C$5)-$K15)/($J15/(1+INICIO!$C$5))),"")
I16: =IF($B16="","",IFERROR(INDEX(PRODUCTOS!$E$5:$E$44,MATCH($C16,PRODUCTOS!$B$5:$B$44,0))*N($D16),0)+IFERROR(INDEX(PRODUCTOS!$E$5:$E$44,MATCH($E16,PRODUCTOS!$B$5:$B$44,0))*N($F16),0)+IFERROR(INDEX(PRODUCTOS!$E$5:$E$44,MATCH($G16,PRODUCTOS!$B$5:$B$44,0))*N($H16),0)) | K16: =IF($B16="","",IFERROR(SUMIFS(RECETAS!$G$5:$G$254,RECETAS!$B$5:$B$254,$C16)*N($D16),0)+IFERROR(SUMIFS(RECETAS!$G$5:$G$254,RECETAS!$B$5:$B$254,$E16)*N($F16),0)+IFERROR(SUMIFS(RECETAS!$G$5:$G$254,RECETAS!$B$5:$B$254,$G16)*N($H16),0)) | L16: =IFERROR(IF($B16="","",($I16-$J16)/$I16),"") | M16: =IFERROR(IF($B16="","",($J16/(1+INICIO!$C$5)-$K16)/($J16/(1+INICIO!$C$5))),"")
I17: =IF($B17="","",IFERROR(INDEX(PRODUCTOS!$E$5:$E$44,MATCH($C17,PRODUCTOS!$B$5:$B$44,0))*N($D17),0)+IFERROR(INDEX(PRODUCTOS!$E$5:$E$44,MATCH($E17,PRODUCTOS!$B$5:$B$44,0))*N($F17),0)+IFERROR(INDEX(PRODUCTOS!$E$5:$E$44,MATCH($G17,PRODUCTOS!$B$5:$B$44,0))*N($H17),0)) | K17: =IF($B17="","",IFERROR(SUMIFS(RECETAS!$G$5:$G$254,RECETAS!$B$5:$B$254,$C17)*N($D17),0)+IFERROR(SUMIFS(RECETAS!$G$5:$G$254,RECETAS!$B$5:$B$254,$E17)*N($F17),0)+IFERROR(SUMIFS(RECETAS!$G$5:$G$254,RECETAS!$B$5:$B$254,$G17)*N($H17),0)) | L17: =IFERROR(IF($B17="","",($I17-$J17)/$I17),"") | M17: =IFERROR(IF($B17="","",($J17/(1+INICIO!$C$5)-$K17)/($J17/(1+INICIO!$C$5))),"")
I18: =IF($B18="","",IFERROR(INDEX(PRODUCTOS!$E$5:$E$44,MATCH($C18,PRODUCTOS!$B$5:$B$44,0))*N($D18),0)+IFERROR(INDEX(PRODUCTOS!$E$5:$E$44,MATCH($E18,PRODUCTOS!$B$5:$B$44,0))*N($F18),0)+IFERROR(INDEX(PRODUCTOS!$E$5:$E$44,MATCH($G18,PRODUCTOS!$B$5:$B$44,0))*N($H18),0)) | K18: =IF($B18="","",IFERROR(SUMIFS(RECETAS!$G$5:$G$254,RECETAS!$B$5:$B$254,$C18)*N($D18),0)+IFERROR(SUMIFS(RECETAS!$G$5:$G$254,RECETAS!$B$5:$B$254,$E18)*N($F18),0)+IFERROR(SUMIFS(RECETAS!$G$5:$G$254,RECETAS!$B$5:$B$254,$G18)*N($H18),0)) | L18: =IFERROR(IF($B18="","",($I18-$J18)/$I18),"") | M18: =IFERROR(IF($B18="","",($J18/(1+INICIO!$C$5)-$K18)/($J18/(1+INICIO!$C$5))),"")
I19: =IF($B19="","",IFERROR(INDEX(PRODUCTOS!$E$5:$E$44,MATCH($C19,PRODUCTOS!$B$5:$B$44,0))*N($D19),0)+IFERROR(INDEX(PRODUCTOS!$E$5:$E$44,MATCH($E19,PRODUCTOS!$B$5:$B$44,0))*N($F19),0)+IFERROR(INDEX(PRODUCTOS!$E$5:$E$44,MATCH($G19,PRODUCTOS!$B$5:$B$44,0))*N($H19),0)) | K19: =IF($B19="","",IFERROR(SUMIFS(RECETAS!$G$5:$G$254,RECETAS!$B$5:$B$254,$C19)*N($D19),0)+IFERROR(SUMIFS(RECETAS!$G$5:$G$254,RECETAS!$B$5:$B$254,$E19)*N($F19),0)+IFERROR(SUMIFS(RECETAS!$G$5:$G$254,RECETAS!$B$5:$B$254,$G19)*N($H19),0)) | L19: =IFERROR(IF($B19="","",($I19-$J19)/$I19),"") | M19: =IFERROR(IF($B19="","",($J19/(1+INICIO!$C$5)-$K19)/($J19/(1+INICIO!$C$5))),"")
I20: =IF($B20="","",IFERROR(INDEX(PRODUCTOS!$E$5:$E$44,MATCH($C20,PRODUCTOS!$B$5:$B$44,0))*N($D20),0)+IFERROR(INDEX(PRODUCTOS!$E$5:$E$44,MATCH($E20,PRODUCTOS!$B$5:$B$44,0))*N($F20),0)+IFERROR(INDEX(PRODUCTOS!$E$5:$E$44,MATCH($G20,PRODUCTOS!$B$5:$B$44,0))*N($H20),0)) | K20: =IF($B20="","",IFERROR(SUMIFS(RECETAS!$G$5:$G$254,RECETAS!$B$5:$B$254,$C20)*N($D20),0)+IFERROR(SUMIFS(RECETAS!$G$5:$G$254,RECETAS!$B$5:$B$254,$E20)*N($F20),0)+IFERROR(SUMIFS(RECETAS!$G$5:$G$254,RECETAS!$B$5:$B$254,$G20)*N($H20),0)) | L20: =IFERROR(IF($B20="","",($I20-$J20)/$I20),"") | M20: =IFERROR(IF($B20="","",($J20/(1+INICIO!$C$5)-$K20)/($J20/(1+INICIO!$C$5))),"")
... I24: =IF($B24="","",IFERROR(INDEX(PRODUCTOS!$E$5:$E$44,MATCH($C24,PRODUCTOS!$B$5:$B$44,0))*N($D24),0)+IFERROR(INDEX(PRODUCTOS!$E$5:$E$44,MATCH($E24,PRODUCTOS!$B$5:$B$44,0))*N($F24),0)+IFERROR(INDEX(PRODUCTOS!$E$5:$E$44,MATCH($G24,PRODUCTOS!$B$5:$B$44,0))*N($H24),0)) | K24: =IF($B24="","",IFERROR(SUMIFS(RECETAS!$G$5:$G$254,RECETAS!$B$5:$B$254,$C24)*N($D24),0)+IFERROR(SUMIFS(RECETAS!$G$5:$G$254,RECETAS!$B$5:$B$254,$E24)*N($F24),0)+IFERROR(SUMIFS(RECETAS!$G$5:$G$254,RECETAS!$B$5:$B$254,$G24)*N($H24),0)) | L24: =IFERROR(IF($B24="","",($I24-$J24)/$I24),"") | M24: =IFERROR(IF($B24="","",($J24/(1+INICIO!$C$5)-$K24)/($J24/(1+INICIO!$C$5))),"")
B27: Regla: si el margen del combo baja de 55%, no lo lances. Estas regalando plata para vender lo mismo.

Sheet RECETAS
A1: RECETAS
A2: Una fila por cada ingrediente de cada producto. El costo se jala solo desde INSUMOS.
A4: # | B4: Producto | C4: Insumo | D4: Cantidad | E4: Unidad | F4: Costo unitario | G4: COSTO LINEA | H4: Notas de preparacion | I4: Uds. vendidas del producto (mes DASHBOARD) | J4: Consumo del insumo en el mes
A5: 1 | B5: Coco s/alcohol | C5: Jarabe Coco | D5: 63 | E5: =IFERROR(IF($C5="","",INDEX(INSUMOS!$G$5:$G$84,MATCH($C5,INSUMOS!$B$5:$B$84,0))),"") | F5: =IFERROR(IF($C5="","",INDEX(INSUMOS!$I$5:$I$84,MATCH($C5,INSUMOS!$B$5:$B$84,0))),"") | G5: =IFERROR(IF($C5="","",$D5*$F5),"") | H5: 63ml jarabe + 190ml agua | I5: =IF($B5="","",SUMIFS(VENTAS!$D$5:$D$504,VENTAS!$B$5:$B$504,INICIO!$C$8,VENTAS!$C$5:$C$504,$B5)) | J5: =IF($C5="","",$D5*$I5)
A6: 2 | B6: Coco s/alcohol | C6: Agua purificada | D6: 190 | E6: =IFERROR(IF($C6="","",INDEX(INSUMOS!$G$5:$G$84,MATCH($C6,INSUMOS!$B$5:$B$84,0))),"") | F6: =IFERROR(IF($C6="","",INDEX(INSUMOS!$I$5:$I$84,MATCH($C6,INSUMOS!$B$5:$B$84,0))),"") | G6: =IFERROR(IF($C6="","",$D6*$F6),"") | I6: =IF($B6="","",SUMIFS(VENTAS!$D$5:$D$504,VENTAS!$B$5:$B$504,INICIO!$C$8,VENTAS!$C$5:$C$504,$B6)) | J6: =IF($C6="","",$D6*$I6)
A7: 3 | B7: Coco s/alcohol | C7: Energia maquina granizadora | D7: 1 | E7: =IFERROR(IF($C7="","",INDEX(INSUMOS!$G$5:$G$84,MATCH($C7,INSUMOS!$B$5:$B$84,0))),"") | F7: =IFERROR(IF($C7="","",INDEX(INSUMOS!$I$5:$I$84,MATCH($C7,INSUMOS!$B$5:$B$84,0))),"") | G7: =IFERROR(IF($C7="","",$D7*$F7),"") | I7: =IF($B7="","",SUMIFS(VENTAS!$D$5:$D$504,VENTAS!$B$5:$B$504,INICIO!$C$8,VENTAS!$C$5:$C$504,$B7)) | J7: =IF($C7="","",$D7*$I7)
A8: 4 | B8: Coco s/alcohol | C8: Vaso 12 oz | D8: 1 | E8: =IFERROR(IF($C8="","",INDEX(INSUMOS!$G$5:$G$84,MATCH($C8,INSUMOS!$B$5:$B$84,0))),"") | F8: =IFERROR(IF($C8="","",INDEX(INSUMOS!$I$5:$I$84,MATCH($C8,INSUMOS!$B$5:$B$84,0))),"") | G8: =IFERROR(IF($C8="","",$D8*$F8),"") | I8: =IF($B8="","",SUMIFS(VENTAS!$D$5:$D$504,VENTAS!$B$5:$B$504,INICIO!$C$8,VENTAS!$C$5:$C$504,$B8)) | J8: =IF($C8="","",$D8*$I8)
A9: 5 | B9: Coco s/alcohol | C9: Tapa domo 12 oz | D9: 1 | E9: =IFERROR(IF($C9="","",INDEX(INSUMOS!$G$5:$G$84,MATCH($C9,INSUMOS!$B$5:$B$84,0))),"") | F9: =IFERROR(IF($C9="","",INDEX(INSUMOS!$I$5:$I$84,MATCH($C9,INSUMOS!$B$5:$B$84,0))),"") | G9: =IFERROR(IF($C9="","",$D9*$F9),"") | I9: =IF($B9="","",SUMIFS(VENTAS!$D$5:$D$504,VENTAS!$B$5:$B$504,INICIO!$C$8,VENTAS!$C$5:$C$504,$B9)) | J9: =IF($C9="","",$D9*$I9)
A10: 6 | B10: Coco s/alcohol | C10: Pitillo | D10: 1 | E10: =IFERROR(IF($C10="","",INDEX(INSUMOS!$G$5:$G$84,MATCH($C10,INSUMOS!$B$5:$B$84,0))),"") | F10: =IFERROR(IF($C10="","",INDEX(INSUMOS!$I$5:$I$84,MATCH($C10,INSUMOS!$B$5:$B$84,0))),"") | G10: =IFERROR(IF($C10="","",$D10*$F10),"") | I10: =IF($B10="","",SUMIFS(VENTAS!$D$5:$D$504,VENTAS!$B$5:$B$504,INICIO!$C$8,VENTAS!$C$5:$C$504,$B10)) | J10: =IF($C10="","",$D10*$I10)
A11: 7 | B11: Coco s/alcohol | C11: Servilleta | D11: 1 | E11: =IFERROR(IF($C11="","",INDEX(INSUMOS!$G$5:$G$84,MATCH($C11,INSUMOS!$B$5:$B$84,0))),"") | F11: =IFERROR(IF($C11="","",INDEX(INSUMOS!$I$5:$I$84,MATCH($C11,INSUMOS!$B$5:$B$84,0))),"") | G11: =IFERROR(IF($C11="","",$D11*$F11),"") | I11: =IF($B11="","",SUMIFS(VENTAS!$D$5:$D$504,VENTAS!$B$5:$B$504,INICIO!$C$8,VENTAS!$C$5:$C$504,$B11)) | J11: =IF($C11="","",$D11*$I11)
A12: 8 | B12: Frutos Rojos s/alcohol | C12: Jarabe Frutos Rojos | D12: 63 | E12: =IFERROR(IF($C12="","",INDEX(INSUMOS!$G$5:$G$84,MATCH($C12,INSUMOS!$B$5:$B$84,0))),"") | F12: =IFERROR(IF($C12="","",INDEX(INSUMOS!$I$5:$I$84,MATCH($C12,INSUMOS!$B$5:$B$84,0))),"") | G12: =IFERROR(IF($C12="","",$D12*$F12),"") | I12: =IF($B12="","",SUMIFS(VENTAS!$D$5:$D$504,VENTAS!$B$5:$B$504,INICIO!$C$8,VENTAS!$C$5:$C$504,$B12)) | J12: =IF($C12="","",$D12*$I12)
A13: 9 | B13: Frutos Rojos s/alcohol | C13: Agua purificada | D13: 190 | E13: =IFERROR(IF($C13="","",INDEX(INSUMOS!$G$5:$G$84,MATCH($C13,INSUMOS!$B$5:$B$84,0))),"") | F13: =IFERROR(IF($C13="","",INDEX(INSUMOS!$I$5:$I$84,MATCH($C13,INSUMOS!$B$5:$B$84,0))),"") | G13: =IFERROR(IF($C13="","",$D13*$F13),"") | I13: =IF($B13="","",SUMIFS(VENTAS!$D$5:$D$504,VENTAS!$B$5:$B$504,INICIO!$C$8,VENTAS!$C$5:$C$504,$B13)) | J13: =IF($C13="","",$D13*$I13)
A14: 10 | B14: Frutos Rojos s/alcohol | C14: Energia maquina granizadora | D14: 1 | E14: =IFERROR(IF($C14="","",INDEX(INSUMOS!$G$5:$G$84,MATCH($C14,INSUMOS!$B$5:$B$84,0))),"") | F14: =IFERROR(IF($C14="","",INDEX(INSUMOS!$I$5:$I$84,MATCH($C14,INSUMOS!$B$5:$B$84,0))),"") | G14: =IFERROR(IF($C14="","",$D14*$F14),"") | I14: =IF($B14="","",SUMIFS(VENTAS!$D$5:$D$504,VENTAS!$B$5:$B$504,INICIO!$C$8,VENTAS!$C$5:$C$504,$B14)) | J14: =IF($C14="","",$D14*$I14)
A15: 11 | B15: Frutos Rojos s/alcohol | C15: Vaso 12 oz | D15: 1 | E15: =IFERROR(IF($C15="","",INDEX(INSUMOS!$G$5:$G$84,MATCH($C15,INSUMOS!$B$5:$B$84,0))),"") | F15: =IFERROR(IF($C15="","",INDEX(INSUMOS!$I$5:$I$84,MATCH($C15,INSUMOS!$B$5:$B$84,0))),"") | G15: =IFERROR(IF($C15="","",$D15*$F15),"") | I15: =IF($B15="","",SUMIFS(VENTAS!$D$5:$D$504,VENTAS!$B$5:$B$504,INICIO!$C$8,VENTAS!$C$5:$C$504,$B15)) | J15: =IF($C15="","",$D15*$I15)
A16: 12 | B16: Frutos Rojos s/alcohol | C16: Tapa domo 12 oz | D16: 1 | E16: =IFERROR(IF($C16="","",INDEX(INSUMOS!$G$5:$G$84,MATCH($C16,INSUMOS!$B$5:$B$84,0))),"") | F16: =IFERROR(IF($C16="","",INDEX(INSUMOS!$I$5:$I$84,MATCH($C16,INSUMOS!$B$5:$B$84,0))),"") | G16: =IFERROR(IF($C16="","",$D16*$F16),"") | I16: =IF($B16="","",SUMIFS(VENTAS!$D$5:$D$504,VENTAS!$B$5:$B$504,INICIO!$C$8,VENTAS!$C$5:$C$504,$B16)) | J16: =IF($C16="","",$D16*$I16)
A17: 13 | B17: Frutos Rojos s/alcohol | C17: Pitillo | D17: 1 | E17: =IFERROR(IF($C17="","",INDEX(INSUMOS!$G$5:$G$84,MATCH($C17,INSUMOS!$B$5:$B$84,0))),"") | F17: =IFERROR(IF($C17="","",INDEX(INSUMOS!$I$5:$I$84,MATCH($C17,INSUMOS!$B$5:$B$84,0))),"") | G17: =IFERROR(IF($C17="","",$D17*$F17),"") | I17: =IF($B17="","",SUMIFS(VENTAS!$D$5:$D$504,VENTAS!$B$5:$B$504,INICIO!$C$8,VENTAS!$C$5:$C$504,$B17)) | J17: =IF($C17="","",$D17*$I17)
... A32: 28 | B32: Naranja s/alcohol | C32: Servilleta | D32: 1 | E32: =IFERROR(IF($C32="","",INDEX(INSUMOS!$G$5:$G$84,MATCH($C32,INSUMOS!$B$5:$B$84,0))),"") | F32: =IFERROR(IF($C32="","",INDEX(INSUMOS!$I$5:$I$84,MATCH($C32,INSUMOS!$B$5:$B$84,0))),"") | G32: =IFERROR(IF($C32="","",$D32*$F32),"") | I32: =IF($B32="","",SUMIFS(VENTAS!$D$5:$D$504,VENTAS!$B$5:$B$504,INICIO!$C$8,VENTAS!$C$5:$C$504,$B32)) | J32: =IF($C32="","",$D32*$I32)
A33: 29 | B33: Oreo s/alcohol | C33: Galleta Oreo | D33: 4 | E33: =IFERROR(IF($C33="","",INDEX(INSUMOS!$G$5:$G$84,MATCH($C33,INSUMOS!$B$5:$B$84,0))),"") | F33: =IFERROR(IF($C33="","",INDEX(INSUMOS!$I$5:$I$84,MATCH($C33,INSUMOS!$B$5:$B$84,0))),"") | G33: =IFERROR(IF($C33="","",$D33*$F33),"") | H33: 3 licuadas + 1 para decorar | I33: =IF($B33="","",SUMIFS(VENTAS!$D$5:$D$504,VENTAS!$B$5:$B$504,INICIO!$C$8,VENTAS!$C$5:$C$504,$B33)) | J33: =IF($C33="","",$D33*$I33)
A34: 30 | B34: Oreo s/alcohol | C34: Leche entera | D34: 100 | E34: =IFERROR(IF($C34="","",INDEX(INSUMOS!$G$5:$G$84,MATCH($C34,INSUMOS!$B$5:$B$84,0))),"") | F34: =IFERROR(IF($C34="","",INDEX(INSUMOS!$I$5:$I$84,MATCH($C34,INSUMOS!$B$5:$B$84,0))),"") | G34: =IFERROR(IF($C34="","",$D34*$F34),"") | I34: =IF($B34="","",SUMIFS(VENTAS!$D$5:$D$504,VENTAS!$B$5:$B$504,INICIO!$C$8,VENTAS!$C$5:$C$504,$B34)) | J34: =IF($C34="","",$D34*$I34)
A35: 31 | B35: Oreo s/alcohol | C35: Hielo en cubos | D35: 150 | E35: =IFERROR(IF($C35="","",INDEX(INSUMOS!$G$5:$G$84,MATCH($C35,INSUMOS!$B$5:$B$84,0))),"") | F35: =IFERROR(IF($C35="","",INDEX(INSUMOS!$I$5:$I$84,MATCH($C35,INSUMOS!$B$5:$B$84,0))),"") | G35: =IFERROR(IF($C35="","",$D35*$F35),"") | H35: ~10 cubos | I35: =IF($B35="","",SUMIFS(VENTAS!$D$5:$D$504,VENTAS!$B$5:$B$504,INICIO!$C$8,VENTAS!$C$5:$C$504,$B35)) | J35: =IF($C35="","",$D35*$I35)
A36: 32 | B36: Oreo s/alcohol | C36: Crema de leche | D36: 20 | E36: =IFERROR(IF($C36="","",INDEX(INSUMOS!$G$5:$G$84,MATCH($C36,INSUMOS!$B$5:$B$84,0))),"") | F36: =IFERROR(IF($C36="","",INDEX(INSUMOS!$I$5:$I$84,MATCH($C36,INSUMOS!$B$5:$B$84,0))),"") | G36: =IFERROR(IF($C36="","",$D36*$F36),"") | H36: opcional | I36: =IF($B36="","",SUMIFS(VENTAS!$D$5:$D$504,VENTAS!$B$5:$B$504,INICIO!$C$8,VENTAS!$C$5:$C$504,$B36)) | J36: =IF($C36="","",$D36*$I36)
A37: 33 | B37: Oreo s/alcohol | C37: Vaso 12 oz | D37: 1 | E37: =IFERROR(IF($C37="","",INDEX(INSUMOS!$G$5:$G$84,MATCH($C37,INSUMOS!$B$5:$B$84,0))),"") | F37: =IFERROR(IF($C37="","",INDEX(INSUMOS!$I$5:$I$84,MATCH($C37,INSUMOS!$B$5:$B$84,0))),"") | G37: =IFERROR(IF($C37="","",$D37*$F37),"") | I37: =IF($B37="","",SUMIFS(VENTAS!$D$5:$D$504,VENTAS!$B$5:$B$504,INICIO!$C$8,VENTAS!$C$5:$C$504,$B37)) | J37: =IF($C37="","",$D37*$I37)
A38: 34 | B38: Oreo s/alcohol | C38: Tapa domo 12 oz | D38: 1 | E38: =IFERROR(IF($C38="","",INDEX(INSUMOS!$G$5:$G$84,MATCH($C38,INSUMOS!$B$5:$B$84,0))),"") | F38: =IFERROR(IF($C38="","",INDEX(INSUMOS!$I$5:$I$84,MATCH($C38,INSUMOS!$B$5:$B$84,0))),"") | G38: =IFERROR(IF($C38="","",$D38*$F38),"") | I38: =IF($B38="","",SUMIFS(VENTAS!$D$5:$D$504,VENTAS!$B$5:$B$504,INICIO!$C$8,VENTAS!$C$5:$C$504,$B38)) | J38: =IF($C38="","",$D38*$I38)
A39: 35 | B39: Oreo s/alcohol | C39: Pitillo | D39: 1 | E39: =IFERROR(IF($C39="","",INDEX(INSUMOS!$G$5:$G$84,MATCH($C39,INSUMOS!$B$5:$B$84,0))),"") | F39: =IFERROR(IF($C39="","",INDEX(INSUMOS!$I$5:$I$84,MATCH($C39,INSUMOS!$B$5:$B$84,0))),"") | G39: =IFERROR(IF($C39="","",$D39*$F39),"") | I39: =IF($B39="","",SUMIFS(VENTAS!$D$5:$D$504,VENTAS!$B$5:$B$504,INICIO!$C$8,VENTAS!$C$5:$C$504,$B39)) | J39: =IF($C39="","",$D39*$I39)
A40: 36 | B40: Oreo s/alcohol | C40: Servilleta | D40: 1 | E40: =IFERROR(IF($C40="","",INDEX(INSUMOS!$G$5:$G$84,MATCH($C40,INSUMOS!$B$5:$B$84,0))),"") | F40: =IFERROR(IF($C40="","",INDEX(INSUMOS!$I$5:$I$84,MATCH($C40,INSUMOS!$B$5:$B$84,0))),"") | G40: =IFERROR(IF($C40="","",$D40*$F40),"") | I40: =IF($B40="","",SUMIFS(VENTAS!$D$5:$D$504,VENTAS!$B$5:$B$504,INICIO!$C$8,VENTAS!$C$5:$C$504,$B40)) | J40: =IF($C40="","",$D40*$I40)
A41: 37 | B41: Nutella s/alcohol | C41: Nutella | D41: 30 | E41: =IFERROR(IF($C41="","",INDEX(INSUMOS!$G$5:$G$84,MATCH($C41,INSUMOS!$B$5:$B$84,0))),"") | F41: =IFERROR(IF($C41="","",INDEX(INSUMOS!$I$5:$I$84,MATCH($C41,INSUMOS!$B$5:$B$84,0))),"") | G41: =IFERROR(IF($C41="","",$D41*$F41),"") | H41: 2 cucharadas soperas | I41: =IF($B41="","",SUMIFS(VENTAS!$D$5:$D$504,VENTAS!$B$5:$B$504,INICIO!$C$8,VENTAS!$C$5:$C$504,$B41)) | J41: =IF($C41="","",$D41*$I41)
A42: 38 | B42: Nutella s/alcohol | C42: Leche entera | D42: 120 | E42: =IFERROR(IF($C42="","",INDEX(INSUMOS!$G$5:$G$84,MATCH($C42,INSUMOS!$B$5:$B$84,0))),"") | F42: =IFERROR(IF($C42="","",INDEX(INSUMOS!$I$5:$I$84,MATCH($C42,INSUMOS!$B$5:$B$84,0))),"") | G42: =IFERROR(IF($C42="","",$D42*$F42),"") | I42: =IF($B42="","",SUMIFS(VENTAS!$D$5:$D$504,VENTAS!$B$5:$B$504,INICIO!$C$8,VENTAS!$C$5:$C$504,$B42)) | J42: =IF($C42="","",$D42*$I42)
A43: 39 | B43: Nutella s/alcohol | C43: Hielo en cubos | D43: 150 | E43: =IFERROR(IF($C43="","",INDEX(INSUMOS!$G$5:$G$84,MATCH($C43,INSUMOS!$B$5:$B$84,0))),"") | F43: =IFERROR(IF($C43="","",INDEX(INSUMOS!$I$5:$I$84,MATCH($C43,INSUMOS!$B$5:$B$84,0))),"") | G43: =IFERROR(IF($C43="","",$D43*$F43),"") | I43: =IF($B43="","",SUMIFS(VENTAS!$D$5:$D$504,VENTAS!$B$5:$B$504,INICIO!$C$8,VENTAS!$C$5:$C$504,$B43)) | J43: =IF($C43="","",$D43*$I43)
A44: 40 | B44: Nutella s/alcohol | C44: Vaso 12 oz | D44: 1 | E44: =IFERROR(IF($C44="","",INDEX(INSUMOS!$G$5:$G$84,MATCH($C44,INSUMOS!$B$5:$B$84,0))),"") | F44: =IFERROR(IF($C44="","",INDEX(INSUMOS!$I$5:$I$84,MATCH($C44,INSUMOS!$B$5:$B$84,0))),"") | G44: =IFERROR(IF($C44="","",$D44*$F44),"") | I44: =IF($B44="","",SUMIFS(VENTAS!$D$5:$D$504,VENTAS!$B$5:$B$504,INICIO!$C$8,VENTAS!$C$5:$C$504,$B44)) | J44: =IF($C44="","",$D44*$I44)
A45: 41 | B45: Nutella s/alcohol | C45: Tapa domo 12 oz | D45: 1 | E45: =IFERROR(IF($C45="","",INDEX(INSUMOS!$G$5:$G$84,MATCH($C45,INSUMOS!$B$5:$B$84,0))),"") | F45: =IFERROR(IF($C45="","",INDEX(INSUMOS!$I$5:$I$84,MATCH($C45,INSUMOS!$B$5:$B$84,0))),"") | G45: =IFERROR(IF($C45="","",$D45*$F45),"") | I45: =IF($B45="","",SUMIFS(VENTAS!$D$5:$D$504,VENTAS!$B$5:$B$504,INICIO!$C$8,VENTAS!$C$5:$C$504,$B45)) | J45: =IF($C45="","",$D45*$I45)
A46: 42 | B46: Nutella s/alcohol | C46: Pitillo | D46: 1 | E46: =IFERROR(IF($C46="","",INDEX(INSUMOS!$G$5:$G$84,MATCH($C46,INSUMOS!$B$5:$B$84,0))),"") | F46: =IFERROR(IF($C46="","",INDEX(INSUMOS!$I$5:$I$84,MATCH($C46,INSUMOS!$B$5:$B$84,0))),"") | G46: =IFERROR(IF($C46="","",$D46*$F46),"") | I46: =IF($B46="","",SUMIFS(VENTAS!$D$5:$D$504,VENTAS!$B$5:$B$504,INICIO!$C$8,VENTAS!$C$5:$C$504,$B46)) | J46: =IF($C46="","",$D46*$I46)
A47: 43 | B47: Nutella s/alcohol | C47: Servilleta | D47: 1 | E47: =IFERROR(IF($C47="","",INDEX(INSUMOS!$G$5:$G$84,MATCH($C47,INSUMOS!$B$5:$B$84,0))),"") | F47: =IFERROR(IF($C47="","",INDEX(INSUMOS!$I$5:$I$84,MATCH($C47,INSUMOS!$B$5:$B$84,0))),"") | G47: =IFERROR(IF($C47="","",$D47*$F47),"") | I47: =IF($B47="","",SUMIFS(VENTAS!$D$5:$D$504,VENTAS!$B$5:$B$504,INICIO!$C$8,VENTAS!$C$5:$C$504,$B47)) | J47: =IF($C47="","",$D47*$I47)
A48: 44 | B48: Cafe s/alcohol | C48: Cafe soluble | D48: 4 | E48: =IFERROR(IF($C48="","",INDEX(INSUMOS!$G$5:$G$84,MATCH($C48,INSUMOS!$B$5:$B$84,0))),"") | F48: =IFERROR(IF($C48="","",INDEX(INSUMOS!$I$5:$I$84,MATCH($C48,INSUMOS!$B$5:$B$84,0))),"") | G48: =IFERROR(IF($C48="","",$D48*$F48),"") | H48: 2 cucharaditas, disolver primero | I48: =IF($B48="","",SUMIFS(VENTAS!$D$5:$D$504,VENTAS!$B$5:$B$504,INICIO!$C$8,VENTAS!$C$5:$C$504,$B48)) | J48: =IF($C48="","",$D48*$I48)
A49: 45 | B49: Cafe s/alcohol | C49: Leche condensada | D49: 20 | E49: =IFERROR(IF($C49="","",INDEX(INSUMOS!$G$5:$G$84,MATCH($C49,INSUMOS!$B$5:$B$84,0))),"") | F49: =IFERROR(IF($C49="","",INDEX(INSUMOS!$I$5:$I$84,MATCH($C49,INSUMOS!$B$5:$B$84,0))),"") | G49: =IFERROR(IF($C49="","",$D49*$F49),"") | I49: =IF($B49="","",SUMIFS(VENTAS!$D$5:$D$504,VENTAS!$B$5:$B$504,INICIO!$C$8,VENTAS!$C$5:$C$504,$B49)) | J49: =IF($C49="","",$D49*$I49)
A50: 46 | B50: Cafe s/alcohol | C50: Leche entera | D50: 80 | E50: =IFERROR(IF($C50="","",INDEX(INSUMOS!$G$5:$G$84,MATCH($C50,INSUMOS!$B$5:$B$84,0))),"") | F50: =IFERROR(IF($C50="","",INDEX(INSUMOS!$I$5:$I$84,MATCH($C50,INSUMOS!$B$5:$B$84,0))),"") | G50: =IFERROR(IF($C50="","",$D50*$F50),"") | I50: =IF($B50="","",SUMIFS(VENTAS!$D$5:$D$504,VENTAS!$B$5:$B$504,INICIO!$C$8,VENTAS!$C$5:$C$504,$B50)) | J50: =IF($C50="","",$D50*$I50)
A51: 47 | B51: Cafe s/alcohol | C51: Hielo en cubos | D51: 160 | E51: =IFERROR(IF($C51="","",INDEX(INSUMOS!$G$5:$G$84,MATCH($C51,INSUMOS!$B$5:$B$84,0))),"") | F51: =IFERROR(IF($C51="","",INDEX(INSUMOS!$I$5:$I$84,MATCH($C51,INSUMOS!$B$5:$B$84,0))),"") | G51: =IFERROR(IF($C51="","",$D51*$F51),"") | I51: =IF($B51="","",SUMIFS(VENTAS!$D$5:$D$504,VENTAS!$B$5:$B$504,INICIO!$C$8,VENTAS!$C$5:$C$504,$B51)) | J51: =IF($C51="","",$D51*$I51)
A52: 48 | B52: Cafe s/alcohol | C52: Vaso 12 oz | D52: 1 | E52: =IFERROR(IF($C52="","",INDEX(INSUMOS!$G$5:$G$84,MATCH($C52,INSUMOS!$B$5:$B$84,0))),"") | F52: =IFERROR(IF($C52="","",INDEX(INSUMOS!$I$5:$I$84,MATCH($C52,INSUMOS!$B$5:$B$84,0))),"") | G52: =IFERROR(IF($C52="","",$D52*$F52),"") | I52: =IF($B52="","",SUMIFS(VENTAS!$D$5:$D$504,VENTAS!$B$5:$B$504,INICIO!$C$8,VENTAS!$C$5:$C$504,$B52)) | J52: =IF($C52="","",$D52*$I52)
A53: 49 | B53: Cafe s/alcohol | C53: Tapa domo 12 oz | D53: 1 | E53: =IFERROR(IF($C53="","",INDEX(INSUMOS!$G$5:$G$84,MATCH($C53,INSUMOS!$B$5:$B$84,0))),"") | F53: =IFERROR(IF($C53="","",INDEX(INSUMOS!$I$5:$I$84,MATCH($C53,INSUMOS!$B$5:$B$84,0))),"") | G53: =IFERROR(IF($C53="","",$D53*$F53),"") | I53: =IF($B53="","",SUMIFS(VENTAS!$D$5:$D$504,VENTAS!$B$5:$B$504,INICIO!$C$8,VENTAS!$C$5:$C$504,$B53)) | J53: =IF($C53="","",$D53*$I53)
A54: 50 | B54: Cafe s/alcohol | C54: Pitillo | D54: 1 | E54: =IFERROR(IF($C54="","",INDEX(INSUMOS!$G$5:$G$84,MATCH($C54,INSUMOS!$B$5:$B$84,0))),"") | F54: =IFERROR(IF($C54="","",INDEX(INSUMOS!$I$5:$I$84,MATCH($C54,INSUMOS!$B$5:$B$84,0))),"") | G54: =IFERROR(IF($C54="","",$D54*$F54),"") | I54: =IF($B54="","",SUMIFS(VENTAS!$D$5:$D$504,VENTAS!$B$5:$B$504,INICIO!$C$8,VENTAS!$C$5:$C$504,$B54)) | J54: =IF($C54="","",$D54*$I54)
A55: 51 | B55: Cafe s/alcohol | C55: Servilleta | D55: 1 | E55: =IFERROR(IF($C55="","",INDEX(INSUMOS!$G$5:$G$84,MATCH($C55,INSUMOS!$B$5:$B$84,0))),"") | F55: =IFERROR(IF($C55="","",INDEX(INSUMOS!$I$5:$I$84,MATCH($C55,INSUMOS!$B$5:$B$84,0))),"") | G55: =IFERROR(IF($C55="","",$D55*$F55),"") | I55: =IF($B55="","",SUMIFS(VENTAS!$D$5:$D$504,VENTAS!$B$5:$B$504,INICIO!$C$8,VENTAS!$C$5:$C$504,$B55)) | J55: =IF($C55="","",$D55*$I55)
A56: 52 | B56: Papas en cono natural | C56: Papa | D56: 200 | E56: =IFERROR(IF($C56="","",INDEX(INSUMOS!$G$5:$G$84,MATCH($C56,INSUMOS!$B$5:$B$84,0))),"") | F56: =IFERROR(IF($C56="","",INDEX(INSUMOS!$I$5:$I$84,MATCH($C56,INSUMOS!$B$5:$B$84,0))),"") | G56: =IFERROR(IF($C56="","",$D56*$F56),"") | I56: =IF($B56="","",SUMIFS(VENTAS!$D$5:$D$504,VENTAS!$B$5:$B$504,INICIO!$C$8,VENTAS!$C$5:$C$504,$B56)) | J56: =IF($C56="","",$D56*$I56)
A57: 53 | B57: Papas en cono natural | C57: Aceite de freir | D57: 35 | E57: =IFERROR(IF($C57="","",INDEX(INSUMOS!$G$5:$G$84,MATCH($C57,INSUMOS!$B$5:$B$84,0))),"") | F57: =IFERROR(IF($C57="","",INDEX(INSUMOS!$I$5:$I$84,MATCH($C57,INSUMOS!$B$5:$B$84,0))),"") | G57: =IFERROR(IF($C57="","",$D57*$F57),"") | H57: absorcion estimada | I57: =IF($B57="","",SUMIFS(VENTAS!$D$5:$D$504,VENTAS!$B$5:$B$504,INICIO!$C$8,VENTAS!$C$5:$C$504,$B57)) | J57: =IF($C57="","",$D57*$I57)
A58: 54 | B58: Papas en cono natural | C58: Sal y condimentos | D58: 2 | E58: =IFERROR(IF($C58="","",INDEX(INSUMOS!$G$5:$G$84,MATCH($C58,INSUMOS!$B$5:$B$84,0))),"") | F58: =IFERROR(IF($C58="","",INDEX(INSUMOS!$I$5:$I$84,MATCH($C58,INSUMOS!$B$5:$B$84,0))),"") | G58: =IFERROR(IF($C58="","",$D58*$F58),"") | I58: =IF($B58="","",SUMIFS(VENTAS!$D$5:$D$504,VENTAS!$B$5:$B$504,INICIO!$C$8,VENTAS!$C$5:$C$504,$B58)) | J58: =IF($C58="","",$D58*$I58)
A59: 55 | B59: Papas en cono natural | C59: Cono de papel | D59: 1 | E59: =IFERROR(IF($C59="","",INDEX(INSUMOS!$G$5:$G$84,MATCH($C59,INSUMOS!$B$5:$B$84,0))),"") | F59: =IFERROR(IF($C59="","",INDEX(INSUMOS!$I$5:$I$84,MATCH($C59,INSUMOS!$B$5:$B$84,0))),"") | G59: =IFERROR(IF($C59="","",$D59*$F59),"") | I59: =IF($B59="","",SUMIFS(VENTAS!$D$5:$D$504,VENTAS!$B$5:$B$504,INICIO!$C$8,VENTAS!$C$5:$C$504,$B59)) | J59: =IF($C59="","",$D59*$I59)
A60: 56 | B60: Papas en cono natural | C60: Servilleta | D60: 2 | E60: =IFERROR(IF($C60="","",INDEX(INSUMOS!$G$5:$G$84,MATCH($C60,INSUMOS!$B$5:$B$84,0))),"") | F60: =IFERROR(IF($C60="","",INDEX(INSUMOS!$I$5:$I$84,MATCH($C60,INSUMOS!$B$5:$B$84,0))),"") | G60: =IFERROR(IF($C60="","",$D60*$F60),"") | I60: =IF($B60="","",SUMIFS(VENTAS!$D$5:$D$504,VENTAS!$B$5:$B$504,INICIO!$C$8,VENTAS!$C$5:$C$504,$B60)) | J60: =IF($C60="","",$D60*$I60)
A61: 57 | B61: Papas en cono + salsa | C61: Papa | D61: 200 | E61: =IFERROR(IF($C61="","",INDEX(INSUMOS!$G$5:$G$84,MATCH($C61,INSUMOS!$B$5:$B$84,0))),"") | F61: =IFERROR(IF($C61="","",INDEX(INSUMOS!$I$5:$I$84,MATCH($C61,INSUMOS!$B$5:$B$84,0))),"") | G61: =IFERROR(IF($C61="","",$D61*$F61),"") | I61: =IF($B61="","",SUMIFS(VENTAS!$D$5:$D$504,VENTAS!$B$5:$B$504,INICIO!$C$8,VENTAS!$C$5:$C$504,$B61)) | J61: =IF($C61="","",$D61*$I61)
A62: 58 | B62: Papas en cono + salsa | C62: Aceite de freir | D62: 35 | E62: =IFERROR(IF($C62="","",INDEX(INSUMOS!$G$5:$G$84,MATCH($C62,INSUMOS!$B$5:$B$84,0))),"") | F62: =IFERROR(IF($C62="","",INDEX(INSUMOS!$I$5:$I$84,MATCH($C62,INSUMOS!$B$5:$B$84,0))),"") | G62: =IFERROR(IF($C62="","",$D62*$F62),"") | I62: =IF($B62="","",SUMIFS(VENTAS!$D$5:$D$504,VENTAS!$B$5:$B$504,INICIO!$C$8,VENTAS!$C$5:$C$504,$B62)) | J62: =IF($C62="","",$D62*$I62)
A63: 59 | B63: Papas en cono + salsa | C63: Sal y condimentos | D63: 2 | E63: =IFERROR(IF($C63="","",INDEX(INSUMOS!$G$5:$G$84,MATCH($C63,INSUMOS!$B$5:$B$84,0))),"") | F63: =IFERROR(IF($C63="","",INDEX(INSUMOS!$I$5:$I$84,MATCH($C63,INSUMOS!$B$5:$B$84,0))),"") | G63: =IFERROR(IF($C63="","",$D63*$F63),"") | I63: =IF($B63="","",SUMIFS(VENTAS!$D$5:$D$504,VENTAS!$B$5:$B$504,INICIO!$C$8,VENTAS!$C$5:$C$504,$B63)) | J63: =IF($C63="","",$D63*$I63)
A64: 60 | B64: Papas en cono + salsa | C64: Cono de papel | D64: 1 | E64: =IFERROR(IF($C64="","",INDEX(INSUMOS!$G$5:$G$84,MATCH($C64,INSUMOS!$B$5:$B$84,0))),"") | F64: =IFERROR(IF($C64="","",INDEX(INSUMOS!$I$5:$I$84,MATCH($C64,INSUMOS!$B$5:$B$84,0))),"") | G64: =IFERROR(IF($C64="","",$D64*$F64),"") | I64: =IF($B64="","",SUMIFS(VENTAS!$D$5:$D$504,VENTAS!$B$5:$B$504,INICIO!$C$8,VENTAS!$C$5:$C$504,$B64)) | J64: =IF($C64="","",$D64*$I64)
A65: 61 | B65: Papas en cono + salsa | C65: Servilleta | D65: 2 | E65: =IFERROR(IF($C65="","",INDEX(INSUMOS!$G$5:$G$84,MATCH($C65,INSUMOS!$B$5:$B$84,0))),"") | F65: =IFERROR(IF($C65="","",INDEX(INSUMOS!$I$5:$I$84,MATCH($C65,INSUMOS!$B$5:$B$84,0))),"") | G65: =IFERROR(IF($C65="","",$D65*$F65),"") | I65: =IF($B65="","",SUMIFS(VENTAS!$D$5:$D$504,VENTAS!$B$5:$B$504,INICIO!$C$8,VENTAS!$C$5:$C$504,$B65)) | J65: =IF($C65="","",$D65*$I65)
A66: 62 | B66: Papas en cono + salsa | C66: Salsa porcion (sachet) | D66: 1 | E66: =IFERROR(IF($C66="","",INDEX(INSUMOS!$G$5:$G$84,MATCH($C66,INSUMOS!$B$5:$B$84,0))),"") | F66: =IFERROR(IF($C66="","",INDEX(INSUMOS!$I$5:$I$84,MATCH($C66,INSUMOS!$B$5:$B$84,0))),"") | G66: =IFERROR(IF($C66="","",$D66*$F66),"") | I66: =IF($B66="","",SUMIFS(VENTAS!$D$5:$D$504,VENTAS!$B$5:$B$504,INICIO!$C$8,VENTAS!$C$5:$C$504,$B66)) | J66: =IF($C66="","",$D66*$I66)
A67: 63 | B67: Coco c/alcohol | C67: Jarabe Coco | D67: 63 | E67: =IFERROR(IF($C67="","",INDEX(INSUMOS!$G$5:$G$84,MATCH($C67,INSUMOS!$B$5:$B$84,0))),"") | F67: =IFERROR(IF($C67="","",INDEX(INSUMOS!$I$5:$I$84,MATCH($C67,INSUMOS!$B$5:$B$84,0))),"") | G67: =IFERROR(IF($C67="","",$D67*$F67),"") | H67: 63ml jarabe + 190ml agua | I67: =IF($B67="","",SUMIFS(VENTAS!$D$5:$D$504,VENTAS!$B$5:$B$504,INICIO!$C$8,VENTAS!$C$5:$C$504,$B67)) | J67: =IF($C67="","",$D67*$I67)
A68: 64 | B68: Coco c/alcohol | C68: Agua purificada | D68: 190 | E68: =IFERROR(IF($C68="","",INDEX(INSUMOS!$G$5:$G$84,MATCH($C68,INSUMOS!$B$5:$B$84,0))),"") | F68: =IFERROR(IF($C68="","",INDEX(INSUMOS!$I$5:$I$84,MATCH($C68,INSUMOS!$B$5:$B$84,0))),"") | G68: =IFERROR(IF($C68="","",$D68*$F68),"") | I68: =IF($B68="","",SUMIFS(VENTAS!$D$5:$D$504,VENTAS!$B$5:$B$504,INICIO!$C$8,VENTAS!$C$5:$C$504,$B68)) | J68: =IF($C68="","",$D68*$I68)
A69: 65 | B69: Coco c/alcohol | C69: Energia maquina granizadora | D69: 1 | E69: =IFERROR(IF($C69="","",INDEX(INSUMOS!$G$5:$G$84,MATCH($C69,INSUMOS!$B$5:$B$84,0))),"") | F69: =IFERROR(IF($C69="","",INDEX(INSUMOS!$I$5:$I$84,MATCH($C69,INSUMOS!$B$5:$B$84,0))),"") | G69: =IFERROR(IF($C69="","",$D69*$F69),"") | I69: =IF($B69="","",SUMIFS(VENTAS!$D$5:$D$504,VENTAS!$B$5:$B$504,INICIO!$C$8,VENTAS!$C$5:$C$504,$B69)) | J69: =IF($C69="","",$D69*$I69)
A70: 66 | B70: Coco c/alcohol | C70: Vaso 12 oz | D70: 1 | E70: =IFERROR(IF($C70="","",INDEX(INSUMOS!$G$5:$G$84,MATCH($C70,INSUMOS!$B$5:$B$84,0))),"") | F70: =IFERROR(IF($C70="","",INDEX(INSUMOS!$I$5:$I$84,MATCH($C70,INSUMOS!$B$5:$B$84,0))),"") | G70: =IFERROR(IF($C70="","",$D70*$F70),"") | I70: =IF($B70="","",SUMIFS(VENTAS!$D$5:$D$504,VENTAS!$B$5:$B$504,INICIO!$C$8,VENTAS!$C$5:$C$504,$B70)) | J70: =IF($C70="","",$D70*$I70)
A71: 67 | B71: Coco c/alcohol | C71: Tapa domo 12 oz | D71: 1 | E71: =IFERROR(IF($C71="","",INDEX(INSUMOS!$G$5:$G$84,MATCH($C71,INSUMOS!$B$5:$B$84,0))),"") | F71: =IFERROR(IF($C71="","",INDEX(INSUMOS!$I$5:$I$84,MATCH($C71,INSUMOS!$B$5:$B$84,0))),"") | G71: =IFERROR(IF($C71="","",$D71*$F71),"") | I71: =IF($B71="","",SUMIFS(VENTAS!$D$5:$D$504,VENTAS!$B$5:$B$504,INICIO!$C$8,VENTAS!$C$5:$C$504,$B71)) | J71: =IF($C71="","",$D71*$I71)
A72: 68 | B72: Coco c/alcohol | C72: Pitillo | D72: 1 | E72: =IFERROR(IF($C72="","",INDEX(INSUMOS!$G$5:$G$84,MATCH($C72,INSUMOS!$B$5:$B$84,0))),"") | F72: =IFERROR(IF($C72="","",INDEX(INSUMOS!$I$5:$I$84,MATCH($C72,INSUMOS!$B$5:$B$84,0))),"") | G72: =IFERROR(IF($C72="","",$D72*$F72),"") | I72: =IF($B72="","",SUMIFS(VENTAS!$D$5:$D$504,VENTAS!$B$5:$B$504,INICIO!$C$8,VENTAS!$C$5:$C$504,$B72)) | J72: =IF($C72="","",$D72*$I72)
A73: 69 | B73: Coco c/alcohol | C73: Servilleta | D73: 1 | E73: =IFERROR(IF($C73="","",INDEX(INSUMOS!$G$5:$G$84,MATCH($C73,INSUMOS!$B$5:$B$84,0))),"") | F73: =IFERROR(IF($C73="","",INDEX(INSUMOS!$I$5:$I$84,MATCH($C73,INSUMOS!$B$5:$B$84,0))),"") | G73: =IFERROR(IF($C73="","",$D73*$F73),"") | I73: =IF($B73="","",SUMIFS(VENTAS!$D$5:$D$504,VENTAS!$B$5:$B$504,INICIO!$C$8,VENTAS!$C$5:$C$504,$B73)) | J73: =IF($C73="","",$D73*$I73)
A74: 70 | B74: Coco c/alcohol | C74: Vodka / Aguardiente | D74: 30 | E74: =IFERROR(IF($C74="","",INDEX(INSUMOS!$G$5:$G$84,MATCH($C74,INSUMOS!$B$5:$B$84,0))),"") | F74: =IFERROR(IF($C74="","",INDEX(INSUMOS!$I$5:$I$84,MATCH($C74,INSUMOS!$B$5:$B$84,0))),"") | G74: =IFERROR(IF($C74="","",$D74*$F74),"") | H74: Porcion estandar 30ml | I74: =IF($B74="","",SUMIFS(VENTAS!$D$5:$D$504,VENTAS!$B$5:$B$504,INICIO!$C$8,VENTAS!$C$5:$C$504,$B74)) | J74: =IF($C74="","",$D74*$I74)
A75: 71 | B75: Frutos Rojos c/alcohol | C75: Jarabe Frutos Rojos | D75: 63 | E75: =IFERROR(IF($C75="","",INDEX(INSUMOS!$G$5:$G$84,MATCH($C75,INSUMOS!$B$5:$B$84,0))),"") | F75: =IFERROR(IF($C75="","",INDEX(INSUMOS!$I$5:$I$84,MATCH($C75,INSUMOS!$B$5:$B$84,0))),"") | G75: =IFERROR(IF($C75="","",$D75*$F75),"") | I75: =IF($B75="","",SUMIFS(VENTAS!$D$5:$D$504,VENTAS!$B$5:$B$504,INICIO!$C$8,VENTAS!$C$5:$C$504,$B75)) | J75: =IF($C75="","",$D75*$I75)
A76: 72 | B76: Frutos Rojos c/alcohol | C76: Agua purificada | D76: 190 | E76: =IFERROR(IF($C76="","",INDEX(INSUMOS!$G$5:$G$84,MATCH($C76,INSUMOS!$B$5:$B$84,0))),"") | F76: =IFERROR(IF($C76="","",INDEX(INSUMOS!$I$5:$I$84,MATCH($C76,INSUMOS!$B$5:$B$84,0))),"") | G76: =IFERROR(IF($C76="","",$D76*$F76),"") | I76: =IF($B76="","",SUMIFS(VENTAS!$D$5:$D$504,VENTAS!$B$5:$B$504,INICIO!$C$8,VENTAS!$C$5:$C$504,$B76)) | J76: =IF($C76="","",$D76*$I76)
A77: 73 | B77: Frutos Rojos c/alcohol | C77: Energia maquina granizadora | D77: 1 | E77: =IFERROR(IF($C77="","",INDEX(INSUMOS!$G$5:$G$84,MATCH($C77,INSUMOS!$B$5:$B$84,0))),"") | F77: =IFERROR(IF($C77="","",INDEX(INSUMOS!$I$5:$I$84,MATCH($C77,INSUMOS!$B$5:$B$84,0))),"") | G77: =IFERROR(IF($C77="","",$D77*$F77),"") | I77: =IF($B77="","",SUMIFS(VENTAS!$D$5:$D$504,VENTAS!$B$5:$B$504,INICIO!$C$8,VENTAS!$C$5:$C$504,$B77)) | J77: =IF($C77="","",$D77*$I77)
A78: 74 | B78: Frutos Rojos c/alcohol | C78: Vaso 12 oz | D78: 1 | E78: =IFERROR(IF($C78="","",INDEX(INSUMOS!$G$5:$G$84,MATCH($C78,INSUMOS!$B$5:$B$84,0))),"") | F78: =IFERROR(IF($C78="","",INDEX(INSUMOS!$I$5:$I$84,MATCH($C78,INSUMOS!$B$5:$B$84,0))),"") | G78: =IFERROR(IF($C78="","",$D78*$F78),"") | I78: =IF($B78="","",SUMIFS(VENTAS!$D$5:$D$504,VENTAS!$B$5:$B$504,INICIO!$C$8,VENTAS!$C$5:$C$504,$B78)) | J78: =IF($C78="","",$D78*$I78)
A79: 75 | B79: Frutos Rojos c/alcohol | C79: Tapa domo 12 oz | D79: 1 | E79: =IFERROR(IF($C79="","",INDEX(INSUMOS!$G$5:$G$84,MATCH($C79,INSUMOS!$B$5:$B$84,0))),"") | F79: =IFERROR(IF($C79="","",INDEX(INSUMOS!$I$5:$I$84,MATCH($C79,INSUMOS!$B$5:$B$84,0))),"") | G79: =IFERROR(IF($C79="","",$D79*$F79),"") | I79: =IF($B79="","",SUMIFS(VENTAS!$D$5:$D$504,VENTAS!$B$5:$B$504,INICIO!$C$8,VENTAS!$C$5:$C$504,$B79)) | J79: =IF($C79="","",$D79*$I79)
A80: 76 | B80: Frutos Rojos c/alcohol | C80: Pitillo | D80: 1 | E80: =IFERROR(IF($C80="","",INDEX(INSUMOS!$G$5:$G$84,MATCH($C80,INSUMOS!$B$5:$B$84,0))),"") | F80: =IFERROR(IF($C80="","",INDEX(INSUMOS!$I$5:$I$84,MATCH($C80,INSUMOS!$B$5:$B$84,0))),"") | G80: =IFERROR(IF($C80="","",$D80*$F80),"") | I80: =IF($B80="","",SUMIFS(VENTAS!$D$5:$D$504,VENTAS!$B$5:$B$504,INICIO!$C$8,VENTAS!$C$5:$C$504,$B80)) | J80: =IF($C80="","",$D80*$I80)
A81: 77 | B81: Frutos Rojos c/alcohol | C81: Servilleta | D81: 1 | E81: =IFERROR(IF($C81="","",INDEX(INSUMOS!$G$5:$G$84,MATCH($C81,INSUMOS!$B$5:$B$84,0))),"") | F81: =IFERROR(IF($C81="","",INDEX(INSUMOS!$I$5:$I$84,MATCH($C81,INSUMOS!$B$5:$B$84,0))),"") | G81: =IFERROR(IF($C81="","",$D81*$F81),"") | I81: =IF($B81="","",SUMIFS(VENTAS!$D$5:$D$504,VENTAS!$B$5:$B$504,INICIO!$C$8,VENTAS!$C$5:$C$504,$B81)) | J81: =IF($C81="","",$D81*$I81)
A82: 78 | B82: Frutos Rojos c/alcohol | C82: Vodka / Aguardiente | D82: 30 | E82: =IFERROR(IF($C82="","",INDEX(INSUMOS!$G$5:$G$84,MATCH($C82,INSUMOS!$B$5:$B$84,0))),"") | F82: =IFERROR(IF($C82="","",INDEX(INSUMOS!$I$5:$I$84,MATCH($C82,INSUMOS!$B$5:$B$84,0))),"") | G82: =IFERROR(IF($C82="","",$D82*$F82),"") | H82: Porcion estandar 30ml | I82: =IF($B82="","",SUMIFS(VENTAS!$D$5:$D$504,VENTAS!$B$5:$B$504,INICIO!$C$8,VENTAS!$C$5:$C$504,$B82)) | J82: =IF($C82="","",$D82*$I82)
A83: 79 | B83: Maracuya c/alcohol | C83: Jarabe Maracuya | D83: 63 | E83: =IFERROR(IF($C83="","",INDEX(INSUMOS!$G$5:$G$84,MATCH($C83,INSUMOS!$B$5:$B$84,0))),"") | F83: =IFERROR(IF($C83="","",INDEX(INSUMOS!$I$5:$I$84,MATCH($C83,INSUMOS!$B$5:$B$84,0))),"") | G83: =IFERROR(IF($C83="","",$D83*$F83),"") | I83: =IF($B83="","",SUMIFS(VENTAS!$D$5:$D$504,VENTAS!$B$5:$B$504,INICIO!$C$8,VENTAS!$C$5:$C$504,$B83)) | J83: =IF($C83="","",$D83*$I83)
A84: 80 | B84: Maracuya c/alcohol | C84: Agua purificada | D84: 190 | E84: =IFERROR(IF($C84="","",INDEX(INSUMOS!$G$5:$G$84,MATCH($C84,INSUMOS!$B$5:$B$84,0))),"") | F84: =IFERROR(IF($C84="","",INDEX(INSUMOS!$I$5:$I$84,MATCH($C84,INSUMOS!$B$5:$B$84,0))),"") | G84: =IFERROR(IF($C84="","",$D84*$F84),"") | I84: =IF($B84="","",SUMIFS(VENTAS!$D$5:$D$504,VENTAS!$B$5:$B$504,INICIO!$C$8,VENTAS!$C$5:$C$504,$B84)) | J84: =IF($C84="","",$D84*$I84)
A85: 81 | B85: Maracuya c/alcohol | C85: Energia maquina granizadora | D85: 1 | E85: =IFERROR(IF($C85="","",INDEX(INSUMOS!$G$5:$G$84,MATCH($C85,INSUMOS!$B$5:$B$84,0))),"") | F85: =IFERROR(IF($C85="","",INDEX(INSUMOS!$I$5:$I$84,MATCH($C85,INSUMOS!$B$5:$B$84,0))),"") | G85: =IFERROR(IF($C85="","",$D85*$F85),"") | I85: =IF($B85="","",SUMIFS(VENTAS!$D$5:$D$504,VENTAS!$B$5:$B$504,INICIO!$C$8,VENTAS!$C$5:$C$504,$B85)) | J85: =IF($C85="","",$D85*$I85)
A86: 82 | B86: Maracuya c/alcohol | C86: Vaso 12 oz | D86: 1 | E86: =IFERROR(IF($C86="","",INDEX(INSUMOS!$G$5:$G$84,MATCH($C86,INSUMOS!$B$5:$B$84,0))),"") | F86: =IFERROR(IF($C86="","",INDEX(INSUMOS!$I$5:$I$84,MATCH($C86,INSUMOS!$B$5:$B$84,0))),"") | G86: =IFERROR(IF($C86="","",$D86*$F86),"") | I86: =IF($B86="","",SUMIFS(VENTAS!$D$5:$D$504,VENTAS!$B$5:$B$504,INICIO!$C$8,VENTAS!$C$5:$C$504,$B86)) | J86: =IF($C86="","",$D86*$I86)
A87: 83 | B87: Maracuya c/alcohol | C87: Tapa domo 12 oz | D87: 1 | E87: =IFERROR(IF($C87="","",INDEX(INSUMOS!$G$5:$G$84,MATCH($C87,INSUMOS!$B$5:$B$84,0))),"") | F87: =IFERROR(IF($C87="","",INDEX(INSUMOS!$I$5:$I$84,MATCH($C87,INSUMOS!$B$5:$B$84,0))),"") | G87: =IFERROR(IF($C87="","",$D87*$F87),"") | I87: =IF($B87="","",SUMIFS(VENTAS!$D$5:$D$504,VENTAS!$B$5:$B$504,INICIO!$C$8,VENTAS!$C$5:$C$504,$B87)) | J87: =IF($C87="","",$D87*$I87)
A88: 84 | B88: Maracuya c/alcohol | C88: Pitillo | D88: 1 | E88: =IFERROR(IF($C88="","",INDEX(INSUMOS!$G$5:$G$84,MATCH($C88,INSUMOS!$B$5:$B$84,0))),"") | F88: =IFERROR(IF($C88="","",INDEX(INSUMOS!$I$5:$I$84,MATCH($C88,INSUMOS!$B$5:$B$84,0))),"") | G88: =IFERROR(IF($C88="","",$D88*$F88),"") | I88: =IF($B88="","",SUMIFS(VENTAS!$D$5:$D$504,VENTAS!$B$5:$B$504,INICIO!$C$8,VENTAS!$C$5:$C$504,$B88)) | J88: =IF($C88="","",$D88*$I88)
A89: 85 | B89: Maracuya c/alcohol | C89: Servilleta | D89: 1 | E89: =IFERROR(IF($C89="","",INDEX(INSUMOS!$G$5:$G$84,MATCH($C89,INSUMOS!$B$5:$B$84,0))),"") | F89: =IFERROR(IF($C89="","",INDEX(INSUMOS!$I$5:$I$84,MATCH($C89,INSUMOS!$B$5:$B$84,0))),"") | G89: =IFERROR(IF($C89="","",$D89*$F89),"") | I89: =IF($B89="","",SUMIFS(VENTAS!$D$5:$D$504,VENTAS!$B$5:$B$504,INICIO!$C$8,VENTAS!$C$5:$C$504,$B89)) | J89: =IF($C89="","",$D89*$I89)
A90: 86 | B90: Maracuya c/alcohol | C90: Vodka / Aguardiente | D90: 30 | E90: =IFERROR(IF($C90="","",INDEX(INSUMOS!$G$5:$G$84,MATCH($C90,INSUMOS!$B$5:$B$84,0))),"") | F90: =IFERROR(IF($C90="","",INDEX(INSUMOS!$I$5:$I$84,MATCH($C90,INSUMOS!$B$5:$B$84,0))),"") | G90: =IFERROR(IF($C90="","",$D90*$F90),"") | H90: Porcion estandar 30ml | I90: =IF($B90="","",SUMIFS(VENTAS!$D$5:$D$504,VENTAS!$B$5:$B$504,INICIO!$C$8,VENTAS!$C$5:$C$504,$B90)) | J90: =IF($C90="","",$D90*$I90)
A91: 87 | B91: Naranja c/alcohol | C91: Jarabe Naranja | D91: 63 | E91: =IFERROR(IF($C91="","",INDEX(INSUMOS!$G$5:$G$84,MATCH($C91,INSUMOS!$B$5:$B$84,0))),"") | F91: =IFERROR(IF($C91="","",INDEX(INSUMOS!$I$5:$I$84,MATCH($C91,INSUMOS!$B$5:$B$84,0))),"") | G91: =IFERROR(IF($C91="","",$D91*$F91),"") | I91: =IF($B91="","",SUMIFS(VENTAS!$D$5:$D$504,VENTAS!$B$5:$B$504,INICIO!$C$8,VENTAS!$C$5:$C$504,$B91)) | J91: =IF($C91="","",$D91*$I91)
A92: 88 | B92: Naranja c/alcohol | C92: Agua purificada | D92: 190 | E92: =IFERROR(IF($C92="","",INDEX(INSUMOS!$G$5:$G$84,MATCH($C92,INSUMOS!$B$5:$B$84,0))),"") | F92: =IFERROR(IF($C92="","",INDEX(INSUMOS!$I$5:$I$84,MATCH($C92,INSUMOS!$B$5:$B$84,0))),"") | G92: =IFERROR(IF($C92="","",$D92*$F92),"") | I92: =IF($B92="","",SUMIFS(VENTAS!$D$5:$D$504,VENTAS!$B$5:$B$504,INICIO!$C$8,VENTAS!$C$5:$C$504,$B92)) | J92: =IF($C92="","",$D92*$I92)
A93: 89 | B93: Naranja c/alcohol | C93: Energia maquina granizadora | D93: 1 | E93: =IFERROR(IF($C93="","",INDEX(INSUMOS!$G$5:$G$84,MATCH($C93,INSUMOS!$B$5:$B$84,0))),"") | F93: =IFERROR(IF($C93="","",INDEX(INSUMOS!$I$5:$I$84,MATCH($C93,INSUMOS!$B$5:$B$84,0))),"") | G93: =IFERROR(IF($C93="","",$D93*$F93),"") | I93: =IF($B93="","",SUMIFS(VENTAS!$D$5:$D$504,VENTAS!$B$5:$B$504,INICIO!$C$8,VENTAS!$C$5:$C$504,$B93)) | J93: =IF($C93="","",$D93*$I93)
A94: 90 | B94: Naranja c/alcohol | C94: Vaso 12 oz | D94: 1 | E94: =IFERROR(IF($C94="","",INDEX(INSUMOS!$G$5:$G$84,MATCH($C94,INSUMOS!$B$5:$B$84,0))),"") | F94: =IFERROR(IF($C94="","",INDEX(INSUMOS!$I$5:$I$84,MATCH($C94,INSUMOS!$B$5:$B$84,0))),"") | G94: =IFERROR(IF($C94="","",$D94*$F94),"") | I94: =IF($B94="","",SUMIFS(VENTAS!$D$5:$D$504,VENTAS!$B$5:$B$504,INICIO!$C$8,VENTAS!$C$5:$C$504,$B94)) | J94: =IF($C94="","",$D94*$I94)
A95: 91 | B95: Naranja c/alcohol | C95: Tapa domo 12 oz | D95: 1 | E95: =IFERROR(IF($C95="","",INDEX(INSUMOS!$G$5:$G$84,MATCH($C95,INSUMOS!$B$5:$B$84,0))),"") | F95: =IFERROR(IF($C95="","",INDEX(INSUMOS!$I$5:$I$84,MATCH($C95,INSUMOS!$B$5:$B$84,0))),"") | G95: =IFERROR(IF($C95="","",$D95*$F95),"") | I95: =IF($B95="","",SUMIFS(VENTAS!$D$5:$D$504,VENTAS!$B$5:$B$504,INICIO!$C$8,VENTAS!$C$5:$C$504,$B95)) | J95: =IF($C95="","",$D95*$I95)
A96: 92 | B96: Naranja c/alcohol | C96: Pitillo | D96: 1 | E96: =IFERROR(IF($C96="","",INDEX(INSUMOS!$G$5:$G$84,MATCH($C96,INSUMOS!$B$5:$B$84,0))),"") | F96: =IFERROR(IF($C96="","",INDEX(INSUMOS!$I$5:$I$84,MATCH($C96,INSUMOS!$B$5:$B$84,0))),"") | G96: =IFERROR(IF($C96="","",$D96*$F96),"") | I96: =IF($B96="","",SUMIFS(VENTAS!$D$5:$D$504,VENTAS!$B$5:$B$504,INICIO!$C$8,VENTAS!$C$5:$C$504,$B96)) | J96: =IF($C96="","",$D96*$I96)
A97: 93 | B97: Naranja c/alcohol | C97: Servilleta | D97: 1 | E97: =IFERROR(IF($C97="","",INDEX(INSUMOS!$G$5:$G$84,MATCH($C97,INSUMOS!$B$5:$B$84,0))),"") | F97: =IFERROR(IF($C97="","",INDEX(INSUMOS!$I$5:$I$84,MATCH($C97,INSUMOS!$B$5:$B$84,0))),"") | G97: =IFERROR(IF($C97="","",$D97*$F97),"") | I97: =IF($B97="","",SUMIFS(VENTAS!$D$5:$D$504,VENTAS!$B$5:$B$504,INICIO!$C$8,VENTAS!$C$5:$C$504,$B97)) | J97: =IF($C97="","",$D97*$I97)
A98: 94 | B98: Naranja c/alcohol | C98: Vodka / Aguardiente | D98: 30 | E98: =IFERROR(IF($C98="","",INDEX(INSUMOS!$G$5:$G$84,MATCH($C98,INSUMOS!$B$5:$B$84,0))),"") | F98: =IFERROR(IF($C98="","",INDEX(INSUMOS!$I$5:$I$84,MATCH($C98,INSUMOS!$B$5:$B$84,0))),"") | G98: =IFERROR(IF($C98="","",$D98*$F98),"") | H98: Porcion estandar 30ml | I98: =IF($B98="","",SUMIFS(VENTAS!$D$5:$D$504,VENTAS!$B$5:$B$504,INICIO!$C$8,VENTAS!$C$5:$C$504,$B98)) | J98: =IF($C98="","",$D98*$I98)
A99: 95 | B99: Oreo c/alcohol | C99: Galleta Oreo | D99: 4 | E99: =IFERROR(IF($C99="","",INDEX(INSUMOS!$G$5:$G$84,MATCH($C99,INSUMOS!$B$5:$B$84,0))),"") | F99: =IFERROR(IF($C99="","",INDEX(INSUMOS!$I$5:$I$84,MATCH($C99,INSUMOS!$B$5:$B$84,0))),"") | G99: =IFERROR(IF($C99="","",$D99*$F99),"") | H99: 3 licuadas + 1 para decorar | I99: =IF($B99="","",SUMIFS(VENTAS!$D$5:$D$504,VENTAS!$B$5:$B$504,INICIO!$C$8,VENTAS!$C$5:$C$504,$B99)) | J99: =IF($C99="","",$D99*$I99)
A100: 96 | B100: Oreo c/alcohol | C100: Leche entera | D100: 100 | E100: =IFERROR(IF($C100="","",INDEX(INSUMOS!$G$5:$G$84,MATCH($C100,INSUMOS!$B$5:$B$84,0))),"") | F100: =IFERROR(IF($C100="","",INDEX(INSUMOS!$I$5:$I$84,MATCH($C100,INSUMOS!$B$5:$B$84,0))),"") | G100: =IFERROR(IF($C100="","",$D100*$F100),"") | I100: =IF($B100="","",SUMIFS(VENTAS!$D$5:$D$504,VENTAS!$B$5:$B$504,INICIO!$C$8,VENTAS!$C$5:$C$504,$B100)) | J100: =IF($C100="","",$D100*$I100)
A101: 97 | B101: Oreo c/alcohol | C101: Hielo en cubos | D101: 150 | E101: =IFERROR(IF($C101="","",INDEX(INSUMOS!$G$5:$G$84,MATCH($C101,INSUMOS!$B$5:$B$84,0))),"") | F101: =IFERROR(IF($C101="","",INDEX(INSUMOS!$I$5:$I$84,MATCH($C101,INSUMOS!$B$5:$B$84,0))),"") | G101: =IFERROR(IF($C101="","",$D101*$F101),"") | H101: ~10 cubos | I101: =IF($B101="","",SUMIFS(VENTAS!$D$5:$D$504,VENTAS!$B$5:$B$504,INICIO!$C$8,VENTAS!$C$5:$C$504,$B101)) | J101: =IF($C101="","",$D101*$I101)
A102: 98 | B102: Oreo c/alcohol | C102: Crema de leche | D102: 20 | E102: =IFERROR(IF($C102="","",INDEX(INSUMOS!$G$5:$G$84,MATCH($C102,INSUMOS!$B$5:$B$84,0))),"") | F102: =IFERROR(IF($C102="","",INDEX(INSUMOS!$I$5:$I$84,MATCH($C102,INSUMOS!$B$5:$B$84,0))),"") | G102: =IFERROR(IF($C102="","",$D102*$F102),"") | H102: opcional | I102: =IF($B102="","",SUMIFS(VENTAS!$D$5:$D$504,VENTAS!$B$5:$B$504,INICIO!$C$8,VENTAS!$C$5:$C$504,$B102)) | J102: =IF($C102="","",$D102*$I102)
A103: 99 | B103: Oreo c/alcohol | C103: Vaso 12 oz | D103: 1 | E103: =IFERROR(IF($C103="","",INDEX(INSUMOS!$G$5:$G$84,MATCH($C103,INSUMOS!$B$5:$B$84,0))),"") | F103: =IFERROR(IF($C103="","",INDEX(INSUMOS!$I$5:$I$84,MATCH($C103,INSUMOS!$B$5:$B$84,0))),"") | G103: =IFERROR(IF($C103="","",$D103*$F103),"") | I103: =IF($B103="","",SUMIFS(VENTAS!$D$5:$D$504,VENTAS!$B$5:$B$504,INICIO!$C$8,VENTAS!$C$5:$C$504,$B103)) | J103: =IF($C103="","",$D103*$I103)
A104: 100 | B104: Oreo c/alcohol | C104: Tapa domo 12 oz | D104: 1 | E104: =IFERROR(IF($C104="","",INDEX(INSUMOS!$G$5:$G$84,MATCH($C104,INSUMOS!$B$5:$B$84,0))),"") | F104: =IFERROR(IF($C104="","",INDEX(INSUMOS!$I$5:$I$84,MATCH($C104,INSUMOS!$B$5:$B$84,0))),"") | G104: =IFERROR(IF($C104="","",$D104*$F104),"") | I104: =IF($B104="","",SUMIFS(VENTAS!$D$5:$D$504,VENTAS!$B$5:$B$504,INICIO!$C$8,VENTAS!$C$5:$C$504,$B104)) | J104: =IF($C104="","",$D104*$I104)
A105: 101 | B105: Oreo c/alcohol | C105: Pitillo | D105: 1 | E105: =IFERROR(IF($C105="","",INDEX(INSUMOS!$G$5:$G$84,MATCH($C105,INSUMOS!$B$5:$B$84,0))),"") | F105: =IFERROR(IF($C105="","",INDEX(INSUMOS!$I$5:$I$84,MATCH($C105,INSUMOS!$B$5:$B$84,0))),"") | G105: =IFERROR(IF($C105="","",$D105*$F105),"") | I105: =IF($B105="","",SUMIFS(VENTAS!$D$5:$D$504,VENTAS!$B$5:$B$504,INICIO!$C$8,VENTAS!$C$5:$C$504,$B105)) | J105: =IF($C105="","",$D105*$I105)
A106: 102 | B106: Oreo c/alcohol | C106: Servilleta | D106: 1 | E106: =IFERROR(IF($C106="","",INDEX(INSUMOS!$G$5:$G$84,MATCH($C106,INSUMOS!$B$5:$B$84,0))),"") | F106: =IFERROR(IF($C106="","",INDEX(INSUMOS!$I$5:$I$84,MATCH($C106,INSUMOS!$B$5:$B$84,0))),"") | G106: =IFERROR(IF($C106="","",$D106*$F106),"") | I106: =IF($B106="","",SUMIFS(VENTAS!$D$5:$D$504,VENTAS!$B$5:$B$504,INICIO!$C$8,VENTAS!$C$5:$C$504,$B106)) | J106: =IF($C106="","",$D106*$I106)
A107: 103 | B107: Oreo c/alcohol | C107: Vodka / Aguardiente | D107: 30 | E107: =IFERROR(IF($C107="","",INDEX(INSUMOS!$G$5:$G$84,MATCH($C107,INSUMOS!$B$5:$B$84,0))),"") | F107: =IFERROR(IF($C107="","",INDEX(INSUMOS!$I$5:$I$84,MATCH($C107,INSUMOS!$B$5:$B$84,0))),"") | G107: =IFERROR(IF($C107="","",$D107*$F107),"") | H107: Porcion estandar 30ml | I107: =IF($B107="","",SUMIFS(VENTAS!$D$5:$D$504,VENTAS!$B$5:$B$504,INICIO!$C$8,VENTAS!$C$5:$C$504,$B107)) | J107: =IF($C107="","",$D107*$I107)
A108: 104 | B108: Nutella c/alcohol | C108: Nutella | D108: 30 | E108: =IFERROR(IF($C108="","",INDEX(INSUMOS!$G$5:$G$84,MATCH($C108,INSUMOS!$B$5:$B$84,0))),"") | F108: =IFERROR(IF($C108="","",INDEX(INSUMOS!$I$5:$I$84,MATCH($C108,INSUMOS!$B$5:$B$84,0))),"") | G108: =IFERROR(IF($C108="","",$D108*$F108),"") | H108: 2 cucharadas soperas | I108: =IF($B108="","",SUMIFS(VENTAS!$D$5:$D$504,VENTAS!$B$5:$B$504,INICIO!$C$8,VENTAS!$C$5:$C$504,$B108)) | J108: =IF($C108="","",$D108*$I108)
A109: 105 | B109: Nutella c/alcohol | C109: Leche entera | D109: 120 | E109: =IFERROR(IF($C109="","",INDEX(INSUMOS!$G$5:$G$84,MATCH($C109,INSUMOS!$B$5:$B$84,0))),"") | F109: =IFERROR(IF($C109="","",INDEX(INSUMOS!$I$5:$I$84,MATCH($C109,INSUMOS!$B$5:$B$84,0))),"") | G109: =IFERROR(IF($C109="","",$D109*$F109),"") | I109: =IF($B109="","",SUMIFS(VENTAS!$D$5:$D$504,VENTAS!$B$5:$B$504,INICIO!$C$8,VENTAS!$C$5:$C$504,$B109)) | J109: =IF($C109="","",$D109*$I109)
A110: 106 | B110: Nutella c/alcohol | C110: Hielo en cubos | D110: 150 | E110: =IFERROR(IF($C110="","",INDEX(INSUMOS!$G$5:$G$84,MATCH($C110,INSUMOS!$B$5:$B$84,0))),"") | F110: =IFERROR(IF($C110="","",INDEX(INSUMOS!$I$5:$I$84,MATCH($C110,INSUMOS!$B$5:$B$84,0))),"") | G110: =IFERROR(IF($C110="","",$D110*$F110),"") | I110: =IF($B110="","",SUMIFS(VENTAS!$D$5:$D$504,VENTAS!$B$5:$B$504,INICIO!$C$8,VENTAS!$C$5:$C$504,$B110)) | J110: =IF($C110="","",$D110*$I110)
A111: 107 | B111: Nutella c/alcohol | C111: Vaso 12 oz | D111: 1 | E111: =IFERROR(IF($C111="","",INDEX(INSUMOS!$G$5:$G$84,MATCH($C111,INSUMOS!$B$5:$B$84,0))),"") | F111: =IFERROR(IF($C111="","",INDEX(INSUMOS!$I$5:$I$84,MATCH($C111,INSUMOS!$B$5:$B$84,0))),"") | G111: =IFERROR(IF($C111="","",$D111*$F111),"") | I111: =IF($B111="","",SUMIFS(VENTAS!$D$5:$D$504,VENTAS!$B$5:$B$504,INICIO!$C$8,VENTAS!$C$5:$C$504,$B111)) | J111: =IF($C111="","",$D111*$I111)
A112: 108 | B112: Nutella c/alcohol | C112: Tapa domo 12 oz | D112: 1 | E112: =IFERROR(IF($C112="","",INDEX(INSUMOS!$G$5:$G$84,MATCH($C112,INSUMOS!$B$5:$B$84,0))),"") | F112: =IFERROR(IF($C112="","",INDEX(INSUMOS!$I$5:$I$84,MATCH($C112,INSUMOS!$B$5:$B$84,0))),"") | G112: =IFERROR(IF($C112="","",$D112*$F112),"") | I112: =IF($B112="","",SUMIFS(VENTAS!$D$5:$D$504,VENTAS!$B$5:$B$504,INICIO!$C$8,VENTAS!$C$5:$C$504,$B112)) | J112: =IF($C112="","",$D112*$I112)
A113: 109 | B113: Nutella c/alcohol | C113: Pitillo | D113: 1 | E113: =IFERROR(IF($C113="","",INDEX(INSUMOS!$G$5:$G$84,MATCH($C113,INSUMOS!$B$5:$B$84,0))),"") | F113: =IFERROR(IF($C113="","",INDEX(INSUMOS!$I$5:$I$84,MATCH($C113,INSUMOS!$B$5:$B$84,0))),"") | G113: =IFERROR(IF($C113="","",$D113*$F113),"") | I113: =IF($B113="","",SUMIFS(VENTAS!$D$5:$D$504,VENTAS!$B$5:$B$504,INICIO!$C$8,VENTAS!$C$5:$C$504,$B113)) | J113: =IF($C113="","",$D113*$I113)
A114: 110 | B114: Nutella c/alcohol | C114: Servilleta | D114: 1 | E114: =IFERROR(IF($C114="","",INDEX(INSUMOS!$G$5:$G$84,MATCH($C114,INSUMOS!$B$5:$B$84,0))),"") | F114: =IFERROR(IF($C114="","",INDEX(INSUMOS!$I$5:$I$84,MATCH($C114,INSUMOS!$B$5:$B$84,0))),"") | G114: =IFERROR(IF($C114="","",$D114*$F114),"") | I114: =IF($B114="","",SUMIFS(VENTAS!$D$5:$D$504,VENTAS!$B$5:$B$504,INICIO!$C$8,VENTAS!$C$5:$C$504,$B114)) | J114: =IF($C114="","",$D114*$I114)
A115: 111 | B115: Nutella c/alcohol | C115: Vodka / Aguardiente | D115: 30 | E115: =IFERROR(IF($C115="","",INDEX(INSUMOS!$G$5:$G$84,MATCH($C115,INSUMOS!$B$5:$B$84,0))),"") | F115: =IFERROR(IF($C115="","",INDEX(INSUMOS!$I$5:$I$84,MATCH($C115,INSUMOS!$B$5:$B$84,0))),"") | G115: =IFERROR(IF($C115="","",$D115*$F115),"") | H115: Porcion estandar 30ml | I115: =IF($B115="","",SUMIFS(VENTAS!$D$5:$D$504,VENTAS!$B$5:$B$504,INICIO!$C$8,VENTAS!$C$5:$C$504,$B115)) | J115: =IF($C115="","",$D115*$I115)
...

Sheet INSUMOS
A1: INSUMOS
A2: Todo lo que compras. Cambia un precio aqui y se recalculan TODOS los costos, margenes y precios sugeridos.
A4: ID | B4: Insumo | C4: Categoria | D4: Unidad de compra | E4: Precio de compra | F4: Contenido (en unidad base) | G4: Unidad base | H4: IVA compra % | I4: COSTO POR UNIDAD BASE | J4: Proveedor | K4: Notas
A5: 1 | B5: Jarabe Coco | C5: Jarabe | D5: Galon | E5: 10 | F5: 3785 | G5: ml | H5: 0.15 | I5: =IFERROR(IF($B5="","",IF(INICIO!$C$6="SI",$E5/(1+$H5),$E5)/$F5),"") | J5: Proveedor local | K5: Dilucion 1:3 · rinde ~60 vasos
A6: 2 | B6: Jarabe Frutos Rojos | C6: Jarabe | D6: Galon | E6: 10 | F6: 3785 | G6: ml | H6: 0.15 | I6: =IFERROR(IF($B6="","",IF(INICIO!$C$6="SI",$E6/(1+$H6),$E6)/$F6),"") | J6: Proveedor local | K6: Dilucion 1:3
A7: 3 | B7: Jarabe Maracuya | C7: Jarabe | D7: Galon | E7: 10 | F7: 3785 | G7: ml | H7: 0.15 | I7: =IFERROR(IF($B7="","",IF(INICIO!$C$6="SI",$E7/(1+$H7),$E7)/$F7),"") | J7: Proveedor local | K7: Dilucion 1:3
A8: 4 | B8: Jarabe Naranja | C8: Jarabe | D8: Galon | E8: 10 | F8: 3785 | G8: ml | H8: 0.15 | I8: =IFERROR(IF($B8="","",IF(INICIO!$C$6="SI",$E8/(1+$H8),$E8)/$F8),"") | J8: Proveedor local | K8: Dilucion 1:3
A9: 5 | B9: Agua purificada | C9: Base | D9: Botellon 20L | E9: 2 | F9: 20000 | G9: ml | H9: 0 | I9: =IFERROR(IF($B9="","",IF(INICIO!$C$6="SI",$E9/(1+$H9),$E9)/$F9),"") | K9: Para dilucion de jarabes
A10: 6 | B10: Energia maquina granizadora | C10: Base | D10: Por vaso | E10: 0.02 | F10: 1 | G10: vaso | H10: 0 | I10: =IFERROR(IF($B10="","",IF(INICIO!$C$6="SI",$E10/(1+$H10),$E10)/$F10),"") | K10: ESTIMADO. Ajustar con planilla de luz real
A11: 7 | B11: Hielo en cubos | C11: Base | D11: Bolsa 5 lb | E11: 0.75 | F11: 2268 | G11: g | H11: 0 | I11: =IFERROR(IF($B11="","",IF(INICIO!$C$6="SI",$E11/(1+$H11),$E11)/$F11),"") | K11: PENDIENTE confirmar proveedor en Machala
A12: 8 | B12: Leche entera | C12: Lacteos | D12: Litro | E12: 1.1 | F12: 1000 | G12: ml | H12: 0 | I12: =IFERROR(IF($B12="","",IF(INICIO!$C$6="SI",$E12/(1+$H12),$E12)/$F12),"")
A13: 9 | B13: Leche condensada | C13: Lacteos | D13: Lata 395g | E13: 1.6 | F13: 395 | G13: ml | H13: 0.15 | I13: =IFERROR(IF($B13="","",IF(INICIO!$C$6="SI",$E13/(1+$H13),$E13)/$F13),"")
A14: 10 | B14: Crema de leche | C14: Lacteos | D14: Tetra 250ml | E14: 1.4 | F14: 250 | G14: ml | H14: 0.15 | I14: =IFERROR(IF($B14="","",IF(INICIO!$C$6="SI",$E14/(1+$H14),$E14)/$F14),"") | K14: Opcional en Oreo
A15: 11 | B15: Galleta Oreo | C15: Insumo especial | D15: Paquete 36 u | E15: 3.2 | F15: 36 | G15: unidad | H15: 0.15 | I15: =IFERROR(IF($B15="","",IF(INICIO!$C$6="SI",$E15/(1+$H15),$E15)/$F15),"")
A16: 12 | B16: Nutella | C16: Insumo especial | D16: Frasco 350g | E16: 5.6 | F16: 350 | G16: g | H16: 0.15 | I16: =IFERROR(IF($B16="","",IF(INICIO!$C$6="SI",$E16/(1+$H16),$E16)/$F16),"") | K16: PENDIENTE precio al por mayor
A17: 13 | B17: Cafe soluble | C17: Insumo especial | D17: Frasco 170g | E17: 4.5 | F17: 170 | G17: g | H17: 0.15 | I17: =IFERROR(IF($B17="","",IF(INICIO!$C$6="SI",$E17/(1+$H17),$E17)/$F17),"")
A18: 14 | B18: Azucar | C18: Insumo especial | D18: Funda 2 kg | E18: 2.2 | F18: 2000 | G18: g | H18: 0 | I18: =IFERROR(IF($B18="","",IF(INICIO!$C$6="SI",$E18/(1+$H18),$E18)/$F18),"")
A19: 15 | B19: Vodka / Aguardiente | C19: Alcohol | D19: Botella 750ml | E19: 8 | F19: 750 | G19: ml | H19: 0.15 | I19: =IFERROR(IF($B19="","",IF(INICIO!$C$6="SI",$E19/(1+$H19),$E19)/$F19),"") | K19: Porcion estandar 30ml
A20: 16 | B20: Papa | C20: Comida | D20: Quintal / 10 lb | E20: 5 | F20: 4536 | G20: g | H20: 0 | I20: =IFERROR(IF($B20="","",IF(INICIO!$C$6="SI",$E20/(1+$H20),$E20)/$F20),"") | K20: ~200g por cono
A21: 17 | B21: Aceite de freir | C21: Comida | D21: Botella 1 L | E21: 2.2 | F21: 1000 | G21: ml | H21: 0.15 | I21: =IFERROR(IF($B21="","",IF(INICIO!$C$6="SI",$E21/(1+$H21),$E21)/$F21),"") | K21: Absorcion estimada por cono
A22: 18 | B22: Sal y condimentos | C22: Comida | D22: Funda 500g | E22: 0.8 | F22: 500 | G22: g | H22: 0 | I22: =IFERROR(IF($B22="","",IF(INICIO!$C$6="SI",$E22/(1+$H22),$E22)/$F22),"")
A23: 19 | B23: Salsa porcion (sachet) | C23: Comida | D23: Caja 100 u | E23: 6 | F23: 100 | G23: unidad | H23: 0.15 | I23: =IFERROR(IF($B23="","",IF(INICIO!$C$6="SI",$E23/(1+$H23),$E23)/$F23),"")
A24: 20 | B24: Vaso 12 oz | C24: Descartable | D24: Paquete 50 u | E24: 3.5 | F24: 50 | G24: unidad | H24: 0.15 | I24: =IFERROR(IF($B24="","",IF(INICIO!$C$6="SI",$E24/(1+$H24),$E24)/$F24),"")
A25: 21 | B25: Tapa domo 12 oz | C25: Descartable | D25: Paquete 50 u | E25: 1.5 | F25: 50 | G25: unidad | H25: 0.15 | I25: =IFERROR(IF($B25="","",IF(INICIO!$C$6="SI",$E25/(1+$H25),$E25)/$F25),"")
A26: 22 | B26: Pitillo | C26: Descartable | D26: Paquete 100 u | E26: 1 | F26: 100 | G26: unidad | H26: 0.15 | I26: =IFERROR(IF($B26="","",IF(INICIO!$C$6="SI",$E26/(1+$H26),$E26)/$F26),"")
A27: 23 | B27: Servilleta | C27: Descartable | D27: Paquete 500 u | E27: 1.5 | F27: 500 | G27: unidad | H27: 0.15 | I27: =IFERROR(IF($B27="","",IF(INICIO!$C$6="SI",$E27/(1+$H27),$E27)/$F27),"")
A28: 24 | B28: Cono de papel | C28: Descartable | D28: Paquete 100 u | E28: 4 | F28: 100 | G28: unidad | H28: 0.15 | I28: =IFERROR(IF($B28="","",IF(INICIO!$C$6="SI",$E28/(1+$H28),$E28)/$F28),"")
A29: 25 | B29: Funda de despacho | C29: Descartable | D29: Paquete 100 u | E29: 2 | F29: 100 | G29: unidad | H29: 0.15 | I29: =IFERROR(IF($B29="","",IF(INICIO!$C$6="SI",$E29/(1+$H29),$E29)/$F29),"")
I30: =IFERROR(IF($B30="","",IF(INICIO!$C$6="SI",$E30/(1+$H30),$E30)/$F30),"")
I31: =IFERROR(IF($B31="","",IF(INICIO!$C$6="SI",$E31/(1+$H31),$E31)/$F31),"")
I32: =IFERROR(IF($B32="","",IF(INICIO!$C$6="SI",$E32/(1+$H32),$E32)/$F32),"")
I33: =IFERROR(IF($B33="","",IF(INICIO!$C$6="SI",$E33/(1+$H33),$E33)/$F33),"")
I34: =IFERROR(IF($B34="","",IF(INICIO!$C$6="SI",$E34/(1+$H34),$E34)/$F34),"")
I35: =IFERROR(IF($B35="","",IF(INICIO!$C$6="SI",$E35/(1+$H35),$E35)/$F35),"")
I36: =IFERROR(IF($B36="","",IF(INICIO!$C$6="SI",$E36/(1+$H36),$E36)/$F36),"")
I37: =IFERROR(IF($B37="","",IF(INICIO!$C$6="SI",$E37/(1+$H37),$E37)/$F37),"")
I38: =IFERROR(IF($B38="","",IF(INICIO!$C$6="SI",$E38/(1+$H38),$E38)/$F38),"")
I39: =IFERROR(IF($B39="","",IF(INICIO!$C$6="SI",$E39/(1+$H39),$E39)/$F39),"")
I40: =IFERROR(IF($B40="","",IF(INICIO!$C$6="SI",$E40/(1+$H40),$E40)/$F40),"")
I41: =IFERROR(IF($B41="","",IF(INICIO!$C$6="SI",$E41/(1+$H41),$E41)/$F41),"")
... I84: =IFERROR(IF($B84="","",IF(INICIO!$C$6="SI",$E84/(1+$H84),$E84)/$F84),"")
B86: NOTA: 'Contenido' = cuantas unidades base trae lo que compras. Ej: un galon de jarabe = 3785 ml.
B87: Precios cargados desde finanzas/analisis-costos.md (2026-05-29). Los marcados PENDIENTE hay que confirmarlos en Machala.

Sheet FICHAS_TECNICAS
A1: FICHAS TECNICAS DE PRODUCCION
A2: Receta estandarizada, paso a paso y tiempos. Imprime esta hoja y pegala en la pared del local. El costo se actualiza solo.
B4: Granizado de maquina (Coco / Frutos Rojos / Maracuya / Naranja)
B5: Tiempo objetivo | C5: Menos de 1 minuto
B6: Rendimiento | C6: 1 vaso 12 oz (350 ml)
B7: Equipo | C7: Maquina granizadora de 4 sabores
B8: Costo real por unidad | C8: =IFERROR(INDEX(PRODUCTOS!$D$5:$D$44,MATCH("Coco s/alcohol",PRODUCTOS!$B$5:$B$44,0)),"") | D8: (se actualiza solo desde INSUMOS)
B10: Paso | C10: Que hacer | D10: Tiempo
B11: 1 | C11: Tomar vaso 12 oz limpio y colocarlo bajo la palanca del sabor pedido. | D11: 5 seg
B12: 2 | C12: Accionar la palanca lentamente hasta llenar 3/4 del vaso (~300 ml). | D12: 15 seg
B13: 3 | C13: CONTROL: el granizado debe salir compacto, no liquido. Si sale aguado, esperar 2 min a que enfrie la maquina. | D13: -
B14: 4 | C14: SOLO version c/alcohol: agregar 30 ml de vodka o aguardiente por encima. | D14: 10 seg
B15: 5 | C15: Mezclar suavemente con el pitillo 2-3 veces. NO mezclar de mas: se pierde la textura. | D15: 5 seg
B16: 6 | C16: Colocar tapa, insertar pitillo, entregar con servilleta. | D16: 10 seg
B18: CONTROL DE CALIDAD antes de entregar
C19: [ ] Textura compacta, no liquida
C20: [ ] Vaso lleno a 3/4
C21: [ ] Tapa bien cerrada
C22: [ ] Sin derrames por fuera
B24: SI ALGO SALE MAL
C25: - Granizado liquido -> maquina no fria o mezcla muy diluida
C26: - Muy dulce -> ajustar dilucion a 1:4
C27: - Insipido -> ajustar dilucion a 1:2.5
B28: NOTA | C28: Recarga: 500 ml de jarabe + 1500 ml de agua (1:3). Rinde ~8 vasos por carga.
B31: Granizado especial OREO
B32: Tiempo objetivo | C32: Menos de 2 minutos
B33: Rendimiento | C33: 1 vaso 12 oz
B34: Equipo | C34: Licuadora
B35: Costo real por unidad | C35: =IFERROR(INDEX(PRODUCTOS!$D$5:$D$44,MATCH("Oreo s/alcohol",PRODUCTOS!$B$5:$B$44,0)),"") | D35: (se actualiza solo desde INSUMOS)
B37: Paso | C37: Que hacer | D37: Tiempo
B38: 1 | C38: Meter 150 g de hielo (~10 cubos) en la licuadora. | D38: 10 seg
B39: 2 | C39: Agregar 100 ml de leche entera. | D39: 5 seg
B40: 3 | C40: Agregar 3 galletas Oreo enteras. RESERVAR 1 galleta para decorar. | D40: 10 seg
B41: 4 | C41: Licuar 20-25 segundos hasta textura cremosa y espesa. | D41: 25 seg
B42: 5 | C42: CONTROL: debe quedar espeso como helado suave. Si queda liquido, agregar hielo y volver a licuar. | D42: -
B43: 6 | C43: Verter en el vaso 12 oz. | D43: 10 seg
B44: 7 | C44: SOLO c/alcohol: agregar 30 ml y mezclar con pitillo 2-3 veces. | D44: 10 seg
B45: 8 | C45: Triturar la galleta reservada y espolvorear encima. | D45: 15 seg
B46: 9 | C46: Tapa + pitillo. Entregar. | D46: 10 seg
B48: CONTROL DE CALIDAD antes de entregar
C49: [ ] Textura espesa tipo smoothie helado
C50: [ ] Sabor intenso a Oreo (si esta suave: 1 galleta mas)
C51: [ ] Decoracion visible arriba
C52: [ ] Muy frio al tacto
B54: SI ALGO SALE MAL
C55: - Queda aguado -> falto hielo o sobro leche
C56: - Sabor plano -> agregar 1 galleta
B57: NOTA | C57: Limpiar la licuadora OBLIGATORIAMENTE entre cada especial.
B60: Granizado especial NUTELLA
B61: Tiempo objetivo | C61: Menos de 2 minutos
B62: Rendimiento | C62: 1 vaso 12 oz
B63: Equipo | C63: Licuadora
B64: Costo real por unidad | C64: =IFERROR(INDEX(PRODUCTOS!$D$5:$D$44,MATCH("Nutella s/alcohol",PRODUCTOS!$B$5:$B$44,0)),"") | D64: (se actualiza solo desde INSUMOS)
B66: Paso | C66: Que hacer | D66: Tiempo
B67: 1 | C67: Meter 150 g de hielo en la licuadora. | D67: 10 seg
B68: 2 | C68: Agregar 120 ml de leche entera. | D68: 5 seg
B69: 3 | C69: Agregar 2 cucharadas soperas de Nutella (~30 g), a temperatura ambiente. | D69: 15 seg
B70: 4 | C70: Licuar 25-30 segundos hasta que quede cremoso y SIN grumos. | D70: 30 seg
B71: 5 | C71: CONTROL: revisar que no queden pelotitas de Nutella sin mezclar. | D71: -
B72: 6 | C72: Verter en el vaso 12 oz. | D72: 10 seg
B73: 7 | C73: SOLO c/alcohol: 30 ml y mezclar suavemente. | D73: 10 seg
B74: 8 | C74: Decorar con un hilo de Nutella encima (para foto). | D74: 10 seg
B75: 9 | C75: Tapa + pitillo. Entregar. | D75: 10 seg
B77: CONTROL DE CALIDAD antes de entregar
C78: [ ] Sin grumos
C79: [ ] Textura espesa
C80: [ ] Hilo de Nutella visible
C81: [ ] Muy frio
B83: SI ALGO SALE MAL
C84: - Grumos -> la Nutella estaba fria, sacarla de la nevera antes
C85: - Sabor amargo -> agregar 1 cucharadita de azucar
B86: NOTA | C86: Limpiar la licuadora OBLIGATORIAMENTE entre cada especial.
B89: Granizado especial CAFE
B90: Tiempo objetivo | C90: Menos de 2 minutos
B91: Rendimiento | C91: 1 vaso 12 oz
B92: Equipo | C92: Licuadora
B93: Costo real por unidad | C93: =IFERROR(INDEX(PRODUCTOS!$D$5:$D$44,MATCH("Cafe s/alcohol",PRODUCTOS!$B$5:$B$44,0)),"") | D93: (se actualiza solo desde INSUMOS)
B95: Paso | C95: Que hacer | D95: Tiempo
B96: 1 | C96: Disolver 2 cucharaditas de cafe soluble en 20 ml de agua caliente. NUNCA en polvo directo. | D96: 20 seg
B97: 2 | C97: Meter 160 g de hielo (~11 cubos) en la licuadora. | D97: 10 seg
B98: 3 | C98: Agregar 80 ml de leche entera + 20 ml de leche condensada + el cafe disuelto. | D98: 15 seg
B99: 4 | C99: Licuar 20 segundos. | D99: 20 seg
B100: 5 | C100: CONTROL: textura espesa y fria. Si esta liquido, agregar hielo. | D100: -
B101: 6 | C101: Verter en el vaso 12 oz. | D101: 10 seg
B102: 7 | C102: SOLO c/alcohol: 30 ml de licor de cafe (ideal) o vodka. Mezclar suave. | D102: 10 seg
B103: 8 | C103: Tapa + pitillo. Entregar. | D103: 10 seg
B105: CONTROL DE CALIDAD antes de entregar
C106: [ ] Sin grumos de cafe
C107: [ ] Dulzor equilibrado (lo da la leche condensada)
C108: [ ] Textura espesa
C109: [ ] Muy frio
B111: SI ALGO SALE MAL
C112: - Grumoso -> el cafe no se disolvio primero
C113: - Poco dulce -> media cucharada mas de condensada
B114: NOTA | C114: Limpiar la licuadora OBLIGATORIAMENTE entre cada especial.
B117: PAPAS FRITAS EN CONO
B118: Tiempo objetivo | C118: 3-4 minutos (con aceite ya caliente)
B119: Rendimiento | C119: 1 cono (~200 g de papa)
B120: Equipo | C120: Freidora / sarten hondo
B121: Costo real por unidad | C121: =IFERROR(INDEX(PRODUCTOS!$D$5:$D$44,MATCH("Papas en cono natural",PRODUCTOS!$B$5:$B$44,0)),"") | D121: (se actualiza solo desde INSUMOS)
...

Sheet INVENTARIO
A1: INVENTARIO
A2: Consumo estimado calculado automaticamente desde las VENTAS del mes del DASHBOARD.
A4: Insumo | B4: Unidad base | C4: Stock inicial del mes | D4: Compras del mes | E4: Consumo estimado por ventas | F4: STOCK ACTUAL | G4: Punto de reorden | H4: ALERTA
A5: Jarabe Coco | B5: =IFERROR(IF($A5="","",INDEX(INSUMOS!$G$5:$G$84,MATCH($A5,INSUMOS!$B$5:$B$84,0))),"") | E5: =IF($A5="","",SUMIFS(RECETAS!$J$5:$J$254,RECETAS!$C$5:$C$254,$A5)) | F5: =IF($A5="","",N($C5)+N($D5)-N($E5)) | G5: 0 | H5: =IF($A5="","",IF(AND(N($C5)=0,N($D5)=0),"SIN DATOS",IF($F5<=$G5,"COMPRAR YA","OK")))
A6: Jarabe Frutos Rojos | B6: =IFERROR(IF($A6="","",INDEX(INSUMOS!$G$5:$G$84,MATCH($A6,INSUMOS!$B$5:$B$84,0))),"") | E6: =IF($A6="","",SUMIFS(RECETAS!$J$5:$J$254,RECETAS!$C$5:$C$254,$A6)) | F6: =IF($A6="","",N($C6)+N($D6)-N($E6)) | G6: 0 | H6: =IF($A6="","",IF(AND(N($C6)=0,N($D6)=0),"SIN DATOS",IF($F6<=$G6,"COMPRAR YA","OK")))
A7: Jarabe Maracuya | B7: =IFERROR(IF($A7="","",INDEX(INSUMOS!$G$5:$G$84,MATCH($A7,INSUMOS!$B$5:$B$84,0))),"") | E7: =IF($A7="","",SUMIFS(RECETAS!$J$5:$J$254,RECETAS!$C$5:$C$254,$A7)) | F7: =IF($A7="","",N($C7)+N($D7)-N($E7)) | G7: 0 | H7: =IF($A7="","",IF(AND(N($C7)=0,N($D7)=0),"SIN DATOS",IF($F7<=$G7,"COMPRAR YA","OK")))
A8: Jarabe Naranja | B8: =IFERROR(IF($A8="","",INDEX(INSUMOS!$G$5:$G$84,MATCH($A8,INSUMOS!$B$5:$B$84,0))),"") | E8: =IF($A8="","",SUMIFS(RECETAS!$J$5:$J$254,RECETAS!$C$5:$C$254,$A8)) | F8: =IF($A8="","",N($C8)+N($D8)-N($E8)) | G8: 0 | H8: =IF($A8="","",IF(AND(N($C8)=0,N($D8)=0),"SIN DATOS",IF($F8<=$G8,"COMPRAR YA","OK")))
A9: Agua purificada | B9: =IFERROR(IF($A9="","",INDEX(INSUMOS!$G$5:$G$84,MATCH($A9,INSUMOS!$B$5:$B$84,0))),"") | E9: =IF($A9="","",SUMIFS(RECETAS!$J$5:$J$254,RECETAS!$C$5:$C$254,$A9)) | F9: =IF($A9="","",N($C9)+N($D9)-N($E9)) | G9: 0 | H9: =IF($A9="","",IF(AND(N($C9)=0,N($D9)=0),"SIN DATOS",IF($F9<=$G9,"COMPRAR YA","OK")))
A10: Energia maquina granizadora | B10: =IFERROR(IF($A10="","",INDEX(INSUMOS!$G$5:$G$84,MATCH($A10,INSUMOS!$B$5:$B$84,0))),"") | E10: =IF($A10="","",SUMIFS(RECETAS!$J$5:$J$254,RECETAS!$C$5:$C$254,$A10)) | F10: =IF($A10="","",N($C10)+N($D10)-N($E10)) | G10: 0 | H10: =IF($A10="","",IF(AND(N($C10)=0,N($D10)=0),"SIN DATOS",IF($F10<=$G10,"COMPRAR YA","OK")))
A11: Hielo en cubos | B11: =IFERROR(IF($A11="","",INDEX(INSUMOS!$G$5:$G$84,MATCH($A11,INSUMOS!$B$5:$B$84,0))),"") | E11: =IF($A11="","",SUMIFS(RECETAS!$J$5:$J$254,RECETAS!$C$5:$C$254,$A11)) | F11: =IF($A11="","",N($C11)+N($D11)-N($E11)) | G11: 0 | H11: =IF($A11="","",IF(AND(N($C11)=0,N($D11)=0),"SIN DATOS",IF($F11<=$G11,"COMPRAR YA","OK")))
A12: Leche entera | B12: =IFERROR(IF($A12="","",INDEX(INSUMOS!$G$5:$G$84,MATCH($A12,INSUMOS!$B$5:$B$84,0))),"") | E12: =IF($A12="","",SUMIFS(RECETAS!$J$5:$J$254,RECETAS!$C$5:$C$254,$A12)) | F12: =IF($A12="","",N($C12)+N($D12)-N($E12)) | G12: 0 | H12: =IF($A12="","",IF(AND(N($C12)=0,N($D12)=0),"SIN DATOS",IF($F12<=$G12,"COMPRAR YA","OK")))
A13: Leche condensada | B13: =IFERROR(IF($A13="","",INDEX(INSUMOS!$G$5:$G$84,MATCH($A13,INSUMOS!$B$5:$B$84,0))),"") | E13: =IF($A13="","",SUMIFS(RECETAS!$J$5:$J$254,RECETAS!$C$5:$C$254,$A13)) | F13: =IF($A13="","",N($C13)+N($D13)-N($E13)) | G13: 0 | H13: =IF($A13="","",IF(AND(N($C13)=0,N($D13)=0),"SIN DATOS",IF($F13<=$G13,"COMPRAR YA","OK")))
A14: Crema de leche | B14: =IFERROR(IF($A14="","",INDEX(INSUMOS!$G$5:$G$84,MATCH($A14,INSUMOS!$B$5:$B$84,0))),"") | E14: =IF($A14="","",SUMIFS(RECETAS!$J$5:$J$254,RECETAS!$C$5:$C$254,$A14)) | F14: =IF($A14="","",N($C14)+N($D14)-N($E14)) | G14: 0 | H14: =IF($A14="","",IF(AND(N($C14)=0,N($D14)=0),"SIN DATOS",IF($F14<=$G14,"COMPRAR YA","OK")))
A15: Galleta Oreo | B15: =IFERROR(IF($A15="","",INDEX(INSUMOS!$G$5:$G$84,MATCH($A15,INSUMOS!$B$5:$B$84,0))),"") | E15: =IF($A15="","",SUMIFS(RECETAS!$J$5:$J$254,RECETAS!$C$5:$C$254,$A15)) | F15: =IF($A15="","",N($C15)+N($D15)-N($E15)) | G15: 0 | H15: =IF($A15="","",IF(AND(N($C15)=0,N($D15)=0),"SIN DATOS",IF($F15<=$G15,"COMPRAR YA","OK")))
A16: Nutella | B16: =IFERROR(IF($A16="","",INDEX(INSUMOS!$G$5:$G$84,MATCH($A16,INSUMOS!$B$5:$B$84,0))),"") | E16: =IF($A16="","",SUMIFS(RECETAS!$J$5:$J$254,RECETAS!$C$5:$C$254,$A16)) | F16: =IF($A16="","",N($C16)+N($D16)-N($E16)) | G16: 0 | H16: =IF($A16="","",IF(AND(N($C16)=0,N($D16)=0),"SIN DATOS",IF($F16<=$G16,"COMPRAR YA","OK")))
... A29: Funda de despacho | B29: =IFERROR(IF($A29="","",INDEX(INSUMOS!$G$5:$G$84,MATCH($A29,INSUMOS!$B$5:$B$84,0))),"") | E29: =IF($A29="","",SUMIFS(RECETAS!$J$5:$J$254,RECETAS!$C$5:$C$254,$A29)) | F29: =IF($A29="","",N($C29)+N($D29)-N($E29)) | G29: 0 | H29: =IF($A29="","",IF(AND(N($C29)=0,N($D29)=0),"SIN DATOS",IF($F29<=$G29,"COMPRAR YA","OK")))
B30: =IFERROR(IF($A30="","",INDEX(INSUMOS!$G$5:$G$84,MATCH($A30,INSUMOS!$B$5:$B$84,0))),"") | E30: =IF($A30="","",SUMIFS(RECETAS!$J$5:$J$254,RECETAS!$C$5:$C$254,$A30)) | F30: =IF($A30="","",N($C30)+N($D30)-N($E30)) | H30: =IF($A30="","",IF(AND(N($C30)=0,N($D30)=0),"SIN DATOS",IF($F30<=$G30,"COMPRAR YA","OK")))
B31: =IFERROR(IF($A31="","",INDEX(INSUMOS!$G$5:$G$84,MATCH($A31,INSUMOS!$B$5:$B$84,0))),"") | E31: =IF($A31="","",SUMIFS(RECETAS!$J$5:$J$254,RECETAS!$C$5:$C$254,$A31)) | F31: =IF($A31="","",N($C31)+N($D31)-N($E31)) | H31: =IF($A31="","",IF(AND(N($C31)=0,N($D31)=0),"SIN DATOS",IF($F31<=$G31,"COMPRAR YA","OK")))
B32: =IFERROR(IF($A32="","",INDEX(INSUMOS!$G$5:$G$84,MATCH($A32,INSUMOS!$B$5:$B$84,0))),"") | E32: =IF($A32="","",SUMIFS(RECETAS!$J$5:$J$254,RECETAS!$C$5:$C$254,$A32)) | F32: =IF($A32="","",N($C32)+N($D32)-N($E32)) | H32: =IF($A32="","",IF(AND(N($C32)=0,N($D32)=0),"SIN DATOS",IF($F32<=$G32,"COMPRAR YA","OK")))
B33: =IFERROR(IF($A33="","",INDEX(INSUMOS!$G$5:$G$84,MATCH($A33,INSUMOS!$B$5:$B$84,0))),"") | E33: =IF($A33="","",SUMIFS(RECETAS!$J$5:$J$254,RECETAS!$C$5:$C$254,$A33)) | F33: =IF($A33="","",N($C33)+N($D33)-N($E33)) | H33: =IF($A33="","",IF(AND(N($C33)=0,N($D33)=0),"SIN DATOS",IF($F33<=$G33,"COMPRAR YA","OK")))
B34: =IFERROR(IF($A34="","",INDEX(INSUMOS!$G$5:$G$84,MATCH($A34,INSUMOS!$B$5:$B$84,0))),"") | E34: =IF($A34="","",SUMIFS(RECETAS!$J$5:$J$254,RECETAS!$C$5:$C$254,$A34)) | F34: =IF($A34="","",N($C34)+N($D34)-N($E34)) | H34: =IF($A34="","",IF(AND(N($C34)=0,N($D34)=0),"SIN DATOS",IF($F34<=$G34,"COMPRAR YA","OK")))
B35: =IFERROR(IF($A35="","",INDEX(INSUMOS!$G$5:$G$84,MATCH($A35,INSUMOS!$B$5:$B$84,0))),"") | E35: =IF($A35="","",SUMIFS(RECETAS!$J$5:$J$254,RECETAS!$C$5:$C$254,$A35)) | F35: =IF($A35="","",N($C35)+N($D35)-N($E35)) | H35: =IF($A35="","",IF(AND(N($C35)=0,N($D35)=0),"SIN DATOS",IF($F35<=$G35,"COMPRAR YA","OK")))
B36: =IFERROR(IF($A36="","",INDEX(INSUMOS!$G$5:$G$84,MATCH($A36,INSUMOS!$B$5:$B$84,0))),"") | E36: =IF($A36="","",SUMIFS(RECETAS!$J$5:$J$254,RECETAS!$C$5:$C$254,$A36)) | F36: =IF($A36="","",N($C36)+N($D36)-N($E36)) | H36: =IF($A36="","",IF(AND(N($C36)=0,N($D36)=0),"SIN DATOS",IF($F36<=$G36,"COMPRAR YA","OK")))
B37: =IFERROR(IF($A37="","",INDEX(INSUMOS!$G$5:$G$84,MATCH($A37,INSUMOS!$B$5:$B$84,0))),"") | E37: =IF($A37="","",SUMIFS(RECETAS!$J$5:$J$254,RECETAS!$C$5:$C$254,$A37)) | F37: =IF($A37="","",N($C37)+N($D37)-N($E37)) | H37: =IF($A37="","",IF(AND(N($C37)=0,N($D37)=0),"SIN DATOS",IF($F37<=$G37,"COMPRAR YA","OK")))
B38: =IFERROR(IF($A38="","",INDEX(INSUMOS!$G$5:$G$84,MATCH($A38,INSUMOS!$B$5:$B$84,0))),"") | E38: =IF($A38="","",SUMIFS(RECETAS!$J$5:$J$254,RECETAS!$C$5:$C$254,$A38)) | F38: =IF($A38="","",N($C38)+N($D38)-N($E38)) | H38: =IF($A38="","",IF(AND(N($C38)=0,N($D38)=0),"SIN DATOS",IF($F38<=$G38,"COMPRAR YA","OK")))
B39: =IFERROR(IF($A39="","",INDEX(INSUMOS!$G$5:$G$84,MATCH($A39,INSUMOS!$B$5:$B$84,0))),"") | E39: =IF($A39="","",SUMIFS(RECETAS!$J$5:$J$254,RECETAS!$C$5:$C$254,$A39)) | F39: =IF($A39="","",N($C39)+N($D39)-N($E39)) | H39: =IF($A39="","",IF(AND(N($C39)=0,N($D39)=0),"SIN DATOS",IF($F39<=$G39,"COMPRAR YA","OK")))
B40: =IFERROR(IF($A40="","",INDEX(INSUMOS!$G$5:$G$84,MATCH($A40,INSUMOS!$B$5:$B$84,0))),"") | E40: =IF($A40="","",SUMIFS(RECETAS!$J$5:$J$254,RECETAS!$C$5:$C$254,$A40)) | F40: =IF($A40="","",N($C40)+N($D40)-N($E40)) | H40: =IF($A40="","",IF(AND(N($C40)=0,N($D40)=0),"SIN DATOS",IF($F40<=$G40,"COMPRAR YA","OK")))
B41: =IFERROR(IF($A41="","",INDEX(INSUMOS!$G$5:$G$84,MATCH($A41,INSUMOS!$B$5:$B$84,0))),"") | E41: =IF($A41="","",SUMIFS(RECETAS!$J$5:$J$254,RECETAS!$C$5:$C$254,$A41)) | F41: =IF($A41="","",N($C41)+N($D41)-N($E41)) | H41: =IF($A41="","",IF(AND(N($C41)=0,N($D41)=0),"SIN DATOS",IF($F41<=$G41,"COMPRAR YA","OK")))
... B84: =IFERROR(IF($A84="","",INDEX(INSUMOS!$G$5:$G$84,MATCH($A84,INSUMOS!$B$5:$B$84,0))),"") | E84: =IF($A84="","",SUMIFS(RECETAS!$J$5:$J$254,RECETAS!$C$5:$C$254,$A84)) | F84: =IF($A84="","",N($C84)+N($D84)-N($E84)) | H84: =IF($A84="","",IF(AND(N($C84)=0,N($D84)=0),"SIN DATOS",IF($F84<=$G84,"COMPRAR YA","OK")))

Sheet GASTOS_FIJOS
A1: GASTOS FIJOS MENSUALES
A2: Lo que pagas SI O SI cada mes, vendas o no vendas. Alimenta el punto de equilibrio.
A4: # | B4: Concepto | C4: Monto mensual | D4: ¿Activo? | E4: Notas
A5: 1 | B5: Arriendo del local | C5: 300 | D5: SI | E5: Estimado analisis-costos.md
A6: 2 | B6: Luz + agua | C6: 80 | D6: SI | E6: Sube con la maquina granizadora encendida todo el dia
A7: 3 | B7: Internet / camara | C7: 30 | D7: SI
A8: 4 | B8: Publicidad (Instagram/TikTok) | C8: 50 | D8: SI
A9: 5 | B9: Descartables base (colchon mensual) | C9: 60 | D9: SI | E9: Si ya los cargas en RECETAS, ponlo en NO para no duplicar
A10: 6 | B10: Sueldo empleado 1 | C10: 460 | D10: NO | E10: Salario basico Ecuador. Poner SI cuando contrates
A11: 7 | B11: Sueldo empleado 2 (cocina) | C11: 460 | D11: NO | E11: Cuando entre la linea de comida
A12: 8 | B12: Contador / tramites | C12: 30 | D12: NO
A13: 9 | B13: Mantenimiento equipos | C13: 25 | D13: NO | E13: Maquina granizadora y licuadora
B26: TOTAL FIJOS ACTIVOS / MES | C26: =SUMIFS($C$5:$C$24,$D$5:$D$24,"SI")
B27: Costo fijo por dia de operacion | C27: =IFERROR($C$26/INICIO!$C$7,0)
B29: IMPORTANTE: esta hoja es tu PLAN de fijos (sirve para el punto de equilibrio y las proyecciones).
B30: Cuando REALMENTE pagues el arriendo o la luz, registralo ademas en la hoja GASTOS. No es duplicar: uno es plan, el otro es real.

Sheet EQUILIBRIO
A1: PUNTO DE EQUILIBRIO
A2: Cuanto tienes que vender para no perder plata. El numero mas importante del negocio.
B4: DATOS DEL MES ANALIZADO (viene de VENTAS del mes en INICIO)
B5: Ingreso neto del mes (sin IVA) | C5: =SUMIFS(VENTAS!$H$5:$H$504,VENTAS!$B$5:$B$504,INICIO!$C$8) | D5: Lo que realmente entra a tu bolsillo
B6: Costo de ventas del mes | C6: =SUMIFS(VENTAS!$I$5:$I$504,VENTAS!$B$5:$B$504,INICIO!$C$8) | D6: Insumos consumidos
B7: Unidades vendidas | C7: =SUMIFS(VENTAS!$D$5:$D$504,VENTAS!$B$5:$B$504,INICIO!$C$8)
B8: Ticket promedio neto por unidad | C8: =IFERROR($C$5/$C$7,0)
B9: Costo promedio por unidad | C9: =IFERROR($C$6/$C$7,0)
B10: MARGEN DE CONTRIBUCION por unidad | C10: =$C$8-$C$9 | D10: Lo que deja cada venta para pagar los fijos
B11: Margen de contribucion % | C11: =IFERROR($C$10/$C$8,0)
B13: COSTOS FIJOS
B14: Total gastos fijos activos / mes | C14: =GASTOS_FIJOS!$C$26 | D14: Editable en la hoja GASTOS_FIJOS
B15: Dias de operacion al mes | C15: =INICIO!$C$7 | D15: Editable en INICIO
B17: PUNTO DE EQUILIBRIO
B18: Unidades a vender AL MES para no perder | C18: =IFERROR(ROUNDUP($C$14/$C$10,0),0)
B19: Unidades a vender AL DIA para no perder | C19: =IFERROR(ROUNDUP($C$18/$C$15,0),0) | D19: ESTE es el numero que tienes que tener en la cabeza
B20: Venta (con IVA) necesaria al mes | C20: =IFERROR($C$18*$C$8*(1+INICIO!$C$5),0)
B21: Venta (con IVA) necesaria al dia | C21: =IFERROR($C$20/$C$15,0)
B23: COMO VAS ESTE MES
B24: Unidades vendidas vs punto de equilibrio | C24: =IFERROR($C$7/$C$18,0) | D24: 100% = ya cubriste costos. Todo lo demas es ganancia
B25: Utilidad neta del mes | C25: =$C$5-$C$6-GASTOS_FIJOS!$C$26 | D25: Ingreso neto - costo de ventas - fijos
B26: Estado | C26: =IF($C$25>0,"GANANDO",IF($C$25=0,"EN EL LIMITE","PERDIENDO PLATA"))
D27: Nota: aqui se usan los fijos PLANIFICADOS (GASTOS_FIJOS). El DASHBOARD usa los gastos REALES que registraste.
B28: SIMULADOR: ¿que pasa si...?
B29: Unidades al dia (escribe aqui) | C29: 30
B30: Utilidad neta proyectada al mes | C30: =IFERROR($C$29*$C$15*$C$10-$C$14,0) | D30: Con el margen de contribucion actual
B31: Venta bruta proyectada (c/IVA) al mes | C31: =IFERROR($C$29*$C$15*$C$8*(1+INICIO!$C$5),0)

Sheet PYG
A1: ESTADO DE RESULTADOS (P&G) — REAL
A2: Se llena solo con lo que registras en VENTAS y GASTOS. No escribes nada aqui.
A4: Mes | B4: Venta bruta (c/IVA) | C4: IVA cobrado | D4: INGRESO NETO | E4: Costo de ventas | F4: UTILIDAD BRUTA | G4: Margen bruto | H4: Gastos operativos | I4: UTILIDAD NETA
A5: 2026-09 | B5: =SUMIFS(VENTAS!$F$5:$F$504,VENTAS!$B$5:$B$504,$A5) | C5: =SUMIFS(VENTAS!$G$5:$G$504,VENTAS!$B$5:$B$504,$A5) | D5: =SUMIFS(VENTAS!$H$5:$H$504,VENTAS!$B$5:$B$504,$A5) | E5: =SUMIFS(VENTAS!$I$5:$I$504,VENTAS!$B$5:$B$504,$A5) | F5: =$D5-$E5 | G5: =IFERROR($F5/$D5,0) | H5: =SUMIFS(GASTOS!$E$5:$E$304,GASTOS!$B$5:$B$304,$A5)-SUMIFS(GASTOS!$E$5:$E$304,GASTOS!$B$5:$B$304,$A5,GASTOS!$C$5:$C$304,"Insumos")-SUMIFS(GASTOS!$E$5:$E$304,GASTOS!$B$5:$B$304,$A5,GASTOS!$C$5:$C$304,"Descartables") | I5: =$F5-$H5
A6: 2026-10 | B6: =SUMIFS(VENTAS!$F$5:$F$504,VENTAS!$B$5:$B$504,$A6) | C6: =SUMIFS(VENTAS!$G$5:$G$504,VENTAS!$B$5:$B$504,$A6) | D6: =SUMIFS(VENTAS!$H$5:$H$504,VENTAS!$B$5:$B$504,$A6) | E6: =SUMIFS(VENTAS!$I$5:$I$504,VENTAS!$B$5:$B$504,$A6) | F6: =$D6-$E6 | G6: =IFERROR($F6/$D6,0) | H6: =SUMIFS(GASTOS!$E$5:$E$304,GASTOS!$B$5:$B$304,$A6)-SUMIFS(GASTOS!$E$5:$E$304,GASTOS!$B$5:$B$304,$A6,GASTOS!$C$5:$C$304,"Insumos")-SUMIFS(GASTOS!$E$5:$E$304,GASTOS!$B$5:$B$304,$A6,GASTOS!$C$5:$C$304,"Descartables") | I6: =$F6-$H6
A7: 2026-11 | B7: =SUMIFS(VENTAS!$F$5:$F$504,VENTAS!$B$5:$B$504,$A7) | C7: =SUMIFS(VENTAS!$G$5:$G$504,VENTAS!$B$5:$B$504,$A7) | D7: =SUMIFS(VENTAS!$H$5:$H$504,VENTAS!$B$5:$B$504,$A7) | E7: =SUMIFS(VENTAS!$I$5:$I$504,VENTAS!$B$5:$B$504,$A7) | F7: =$D7-$E7 | G7: =IFERROR($F7/$D7,0) | H7: =SUMIFS(GASTOS!$E$5:$E$304,GASTOS!$B$5:$B$304,$A7)-SUMIFS(GASTOS!$E$5:$E$304,GASTOS!$B$5:$B$304,$A7,GASTOS!$C$5:$C$304,"Insumos")-SUMIFS(GASTOS!$E$5:$E$304,GASTOS!$B$5:$B$304,$A7,GASTOS!$C$5:$C$304,"Descartables") | I7: =$F7-$H7
A8: 2026-12 | B8: =SUMIFS(VENTAS!$F$5:$F$504,VENTAS!$B$5:$B$504,$A8) | C8: =SUMIFS(VENTAS!$G$5:$G$504,VENTAS!$B$5:$B$504,$A8) | D8: =SUMIFS(VENTAS!$H$5:$H$504,VENTAS!$B$5:$B$504,$A8) | E8: =SUMIFS(VENTAS!$I$5:$I$504,VENTAS!$B$5:$B$504,$A8) | F8: =$D8-$E8 | G8: =IFERROR($F8/$D8,0) | H8: =SUMIFS(GASTOS!$E$5:$E$304,GASTOS!$B$5:$B$304,$A8)-SUMIFS(GASTOS!$E$5:$E$304,GASTOS!$B$5:$B$304,$A8,GASTOS!$C$5:$C$304,"Insumos")-SUMIFS(GASTOS!$E$5:$E$304,GASTOS!$B$5:$B$304,$A8,GASTOS!$C$5:$C$304,"Descartables") | I8: =$F8-$H8
A9: 2027-01 | B9: =SUMIFS(VENTAS!$F$5:$F$504,VENTAS!$B$5:$B$504,$A9) | C9: =SUMIFS(VENTAS!$G$5:$G$504,VENTAS!$B$5:$B$504,$A9) | D9: =SUMIFS(VENTAS!$H$5:$H$504,VENTAS!$B$5:$B$504,$A9) | E9: =SUMIFS(VENTAS!$I$5:$I$504,VENTAS!$B$5:$B$504,$A9) | F9: =$D9-$E9 | G9: =IFERROR($F9/$D9,0) | H9: =SUMIFS(GASTOS!$E$5:$E$304,GASTOS!$B$5:$B$304,$A9)-SUMIFS(GASTOS!$E$5:$E$304,GASTOS!$B$5:$B$304,$A9,GASTOS!$C$5:$C$304,"Insumos")-SUMIFS(GASTOS!$E$5:$E$304,GASTOS!$B$5:$B$304,$A9,GASTOS!$C$5:$C$304,"Descartables") | I9: =$F9-$H9
A10: 2027-02 | B10: =SUMIFS(VENTAS!$F$5:$F$504,VENTAS!$B$5:$B$504,$A10) | C10: =SUMIFS(VENTAS!$G$5:$G$504,VENTAS!$B$5:$B$504,$A10) | D10: =SUMIFS(VENTAS!$H$5:$H$504,VENTAS!$B$5:$B$504,$A10) | E10: =SUMIFS(VENTAS!$I$5:$I$504,VENTAS!$B$5:$B$504,$A10) | F10: =$D10-$E10 | G10: =IFERROR($F10/$D10,0) | H10: =SUMIFS(GASTOS!$E$5:$E$304,GASTOS!$B$5:$B$304,$A10)-SUMIFS(GASTOS!$E$5:$E$304,GASTOS!$B$5:$B$304,$A10,GASTOS!$C$5:$C$304,"Insumos")-SUMIFS(GASTOS!$E$5:$E$304,GASTOS!$B$5:$B$304,$A10,GASTOS!$C$5:$C$304,"Descartables") | I10: =$F10-$H10
A11: 2027-03 | B11: =SUMIFS(VENTAS!$F$5:$F$504,VENTAS!$B$5:$B$504,$A11) | C11: =SUMIFS(VENTAS!$G$5:$G$504,VENTAS!$B$5:$B$504,$A11) | D11: =SUMIFS(VENTAS!$H$5:$H$504,VENTAS!$B$5:$B$504,$A11) | E11: =SUMIFS(VENTAS!$I$5:$I$504,VENTAS!$B$5:$B$504,$A11) | F11: =$D11-$E11 | G11: =IFERROR($F11/$D11,0) | H11: =SUMIFS(GASTOS!$E$5:$E$304,GASTOS!$B$5:$B$304,$A11)-SUMIFS(GASTOS!$E$5:$E$304,GASTOS!$B$5:$B$304,$A11,GASTOS!$C$5:$C$304,"Insumos")-SUMIFS(GASTOS!$E$5:$E$304,GASTOS!$B$5:$B$304,$A11,GASTOS!$C$5:$C$304,"Descartables") | I11: =$F11-$H11
A12: 2027-04 | B12: =SUMIFS(VENTAS!$F$5:$F$504,VENTAS!$B$5:$B$504,$A12) | C12: =SUMIFS(VENTAS!$G$5:$G$504,VENTAS!$B$5:$B$504,$A12) | D12: =SUMIFS(VENTAS!$H$5:$H$504,VENTAS!$B$5:$B$504,$A12) | E12: =SUMIFS(VENTAS!$I$5:$I$504,VENTAS!$B$5:$B$504,$A12) | F12: =$D12-$E12 | G12: =IFERROR($F12/$D12,0) | H12: =SUMIFS(GASTOS!$E$5:$E$304,GASTOS!$B$5:$B$304,$A12)-SUMIFS(GASTOS!$E$5:$E$304,GASTOS!$B$5:$B$304,$A12,GASTOS!$C$5:$C$304,"Insumos")-SUMIFS(GASTOS!$E$5:$E$304,GASTOS!$B$5:$B$304,$A12,GASTOS!$C$5:$C$304,"Descartables") | I12: =$F12-$H12
A13: 2027-05 | B13: =SUMIFS(VENTAS!$F$5:$F$504,VENTAS!$B$5:$B$504,$A13) | C13: =SUMIFS(VENTAS!$G$5:$G$504,VENTAS!$B$5:$B$504,$A13) | D13: =SUMIFS(VENTAS!$H$5:$H$504,VENTAS!$B$5:$B$504,$A13) | E13: =SUMIFS(VENTAS!$I$5:$I$504,VENTAS!$B$5:$B$504,$A13) | F13: =$D13-$E13 | G13: =IFERROR($F13/$D13,0) | H13: =SUMIFS(GASTOS!$E$5:$E$304,GASTOS!$B$5:$B$304,$A13)-SUMIFS(GASTOS!$E$5:$E$304,GASTOS!$B$5:$B$304,$A13,GASTOS!$C$5:$C$304,"Insumos")-SUMIFS(GASTOS!$E$5:$E$304,GASTOS!$B$5:$B$304,$A13,GASTOS!$C$5:$C$304,"Descartables") | I13: =$F13-$H13
A14: 2027-06 | B14: =SUMIFS(VENTAS!$F$5:$F$504,VENTAS!$B$5:$B$504,$A14) | C14: =SUMIFS(VENTAS!$G$5:$G$504,VENTAS!$B$5:$B$504,$A14) | D14: =SUMIFS(VENTAS!$H$5:$H$504,VENTAS!$B$5:$B$504,$A14) | E14: =SUMIFS(VENTAS!$I$5:$I$504,VENTAS!$B$5:$B$504,$A14) | F14: =$D14-$E14 | G14: =IFERROR($F14/$D14,0) | H14: =SUMIFS(GASTOS!$E$5:$E$304,GASTOS!$B$5:$B$304,$A14)-SUMIFS(GASTOS!$E$5:$E$304,GASTOS!$B$5:$B$304,$A14,GASTOS!$C$5:$C$304,"Insumos")-SUMIFS(GASTOS!$E$5:$E$304,GASTOS!$B$5:$B$304,$A14,GASTOS!$C$5:$C$304,"Descartables") | I14: =$F14-$H14
A15: 2027-07 | B15: =SUMIFS(VENTAS!$F$5:$F$504,VENTAS!$B$5:$B$504,$A15) | C15: =SUMIFS(VENTAS!$G$5:$G$504,VENTAS!$B$5:$B$504,$A15) | D15: =SUMIFS(VENTAS!$H$5:$H$504,VENTAS!$B$5:$B$504,$A15) | E15: =SUMIFS(VENTAS!$I$5:$I$504,VENTAS!$B$5:$B$504,$A15) | F15: =$D15-$E15 | G15: =IFERROR($F15/$D15,0) | H15: =SUMIFS(GASTOS!$E$5:$E$304,GASTOS!$B$5:$B$304,$A15)-SUMIFS(GASTOS!$E$5:$E$304,GASTOS!$B$5:$B$304,$A15,GASTOS!$C$5:$C$304,"Insumos")-SUMIFS(GASTOS!$E$5:$E$304,GASTOS!$B$5:$B$304,$A15,GASTOS!$C$5:$C$304,"Descartables") | I15: =$F15-$H15
A16: 2027-08 | B16: =SUMIFS(VENTAS!$F$5:$F$504,VENTAS!$B$5:$B$504,$A16) | C16: =SUMIFS(VENTAS!$G$5:$G$504,VENTAS!$B$5:$B$504,$A16) | D16: =SUMIFS(VENTAS!$H$5:$H$504,VENTAS!$B$5:$B$504,$A16) | E16: =SUMIFS(VENTAS!$I$5:$I$504,VENTAS!$B$5:$B$504,$A16) | F16: =$D16-$E16 | G16: =IFERROR($F16/$D16,0) | H16: =SUMIFS(GASTOS!$E$5:$E$304,GASTOS!$B$5:$B$304,$A16)-SUMIFS(GASTOS!$E$5:$E$304,GASTOS!$B$5:$B$304,$A16,GASTOS!$C$5:$C$304,"Insumos")-SUMIFS(GASTOS!$E$5:$E$304,GASTOS!$B$5:$B$304,$A16,GASTOS!$C$5:$C$304,"Descartables") | I16: =$F16-$H16
A17: TOTAL | B17: =SUM(B5:B16) | C17: =SUM(C5:C16) | D17: =SUM(D5:D16) | E17: =SUM(E5:E16) | F17: =SUM(F5:F16) | G17: =IFERROR($F17/$D17,0) | H17: =SUM(H5:H16) | I17: =SUM(I5:I16)
A19: Gastos operativos = todos los GASTOS del mes MENOS insumos y descartables (esos ya estan en el costo de ventas via recetas).

Sheet PROYECCIONES
A1: PROYECCIONES A 12 MESES
A2: 3 escenarios. Cambia los supuestos en AZUL y mira que pasa con la caja.
B4: SUPUESTOS
B5: Escenario | C5: Ventas/dia mes 1 | D5: Ticket promedio c/IVA | E5: Crecimiento mensual
B6: Pesimista | C6: 15 | D6: 2 | E6: 0.02
B7: Realista | C7: 25 | D7: 2.2 | E7: 0.05
B8: Optimista | C8: 45 | D8: 2.5 | E8: 0.08
B10: Margen de contribucion % (viene de EQUILIBRIO) | C10: =IFERROR(EQUILIBRIO!$C$11,0.75) | D10: Si aun no tienes ventas registradas usa 75% por defecto.
B11: Gastos fijos / mes | C11: =GASTOS_FIJOS!$C$26
B13: ESCENARIO PESIMISTA
B14: Mes | C14: Ventas/dia | D14: Venta bruta c/IVA | E14: Ingreso neto | F14: Margen contrib. $ | G14: Gastos fijos | H14: UTILIDAD NETA | I14: Caja acumulada
B15: Mes 1 | C15: =$C$6 | D15: =$C15*INICIO!$C$7*$D$6 | E15: =$D15/(1+INICIO!$C$5) | F15: =$E15*$C$10 | G15: =$C$11 | H15: =$F15-$G15 | I15: =$H15
B16: Mes 2 | C16: =$C15*(1+$E$6) | D16: =$C16*INICIO!$C$7*$D$6 | E16: =$D16/(1+INICIO!$C$5) | F16: =$E16*$C$10 | G16: =$C$11 | H16: =$F16-$G16 | I16: =$I15+$H16
B17: Mes 3 | C17: =$C16*(1+$E$6) | D17: =$C17*INICIO!$C$7*$D$6 | E17: =$D17/(1+INICIO!$C$5) | F17: =$E17*$C$10 | G17: =$C$11 | H17: =$F17-$G17 | I17: =$I16+$H17
B18: Mes 4 | C18: =$C17*(1+$E$6) | D18: =$C18*INICIO!$C$7*$D$6 | E18: =$D18/(1+INICIO!$C$5) | F18: =$E18*$C$10 | G18: =$C$11 | H18: =$F18-$G18 | I18: =$I17+$H18
B19: Mes 5 | C19: =$C18*(1+$E$6) | D19: =$C19*INICIO!$C$7*$D$6 | E19: =$D19/(1+INICIO!$C$5) | F19: =$E19*$C$10 | G19: =$C$11 | H19: =$F19-$G19 | I19: =$I18+$H19
B20: Mes 6 | C20: =$C19*(1+$E$6) | D20: =$C20*INICIO!$C$7*$D$6 | E20: =$D20/(1+INICIO!$C$5) | F20: =$E20*$C$10 | G20: =$C$11 | H20: =$F20-$G20 | I20: =$I19+$H20
B21: Mes 7 | C21: =$C20*(1+$E$6) | D21: =$C21*INICIO!$C$7*$D$6 | E21: =$D21/(1+INICIO!$C$5) | F21: =$E21*$C$10 | G21: =$C$11 | H21: =$F21-$G21 | I21: =$I20+$H21
B22: Mes 8 | C22: =$C21*(1+$E$6) | D22: =$C22*INICIO!$C$7*$D$6 | E22: =$D22/(1+INICIO!$C$5) | F22: =$E22*$C$10 | G22: =$C$11 | H22: =$F22-$G22 | I22: =$I21+$H22
B23: Mes 9 | C23: =$C22*(1+$E$6) | D23: =$C23*INICIO!$C$7*$D$6 | E23: =$D23/(1+INICIO!$C$5) | F23: =$E23*$C$10 | G23: =$C$11 | H23: =$F23-$G23 | I23: =$I22+$H23
B24: Mes 10 | C24: =$C23*(1+$E$6) | D24: =$C24*INICIO!$C$7*$D$6 | E24: =$D24/(1+INICIO!$C$5) | F24: =$E24*$C$10 | G24: =$C$11 | H24: =$F24-$G24 | I24: =$I23+$H24
B25: Mes 11 | C25: =$C24*(1+$E$6) | D25: =$C25*INICIO!$C$7*$D$6 | E25: =$D25/(1+INICIO!$C$5) | F25: =$E25*$C$10 | G25: =$C$11 | H25: =$F25-$G25 | I25: =$I24+$H25
B26: Mes 12 | C26: =$C25*(1+$E$6) | D26: =$C26*INICIO!$C$7*$D$6 | E26: =$D26/(1+INICIO!$C$5) | F26: =$E26*$C$10 | G26: =$C$11 | H26: =$F26-$G26 | I26: =$I25+$H26
B29: ESCENARIO REALISTA
B30: Mes | C30: Ventas/dia | D30: Venta bruta c/IVA | E30: Ingreso neto | F30: Margen contrib. $ | G30: Gastos fijos | H30: UTILIDAD NETA | I30: Caja acumulada
B31: Mes 1 | C31: =$C$7 | D31: =$C31*INICIO!$C$7*$D$7 | E31: =$D31/(1+INICIO!$C$5) | F31: =$E31*$C$10 | G31: =$C$11 | H31: =$F31-$G31 | I31: =$H31
B32: Mes 2 | C32: =$C31*(1+$E$7) | D32: =$C32*INICIO!$C$7*$D$7 | E32: =$D32/(1+INICIO!$C$5) | F32: =$E32*$C$10 | G32: =$C$11 | H32: =$F32-$G32 | I32: =$I31+$H32
B33: Mes 3 | C33: =$C32*(1+$E$7) | D33: =$C33*INICIO!$C$7*$D$7 | E33: =$D33/(1+INICIO!$C$5) | F33: =$E33*$C$10 | G33: =$C$11 | H33: =$F33-$G33 | I33: =$I32+$H33
B34: Mes 4 | C34: =$C33*(1+$E$7) | D34: =$C34*INICIO!$C$7*$D$7 | E34: =$D34/(1+INICIO!$C$5) | F34: =$E34*$C$10 | G34: =$C$11 | H34: =$F34-$G34 | I34: =$I33+$H34
B35: Mes 5 | C35: =$C34*(1+$E$7) | D35: =$C35*INICIO!$C$7*$D$7 | E35: =$D35/(1+INICIO!$C$5) | F35: =$E35*$C$10 | G35: =$C$11 | H35: =$F35-$G35 | I35: =$I34+$H35
B36: Mes 6 | C36: =$C35*(1+$E$7) | D36: =$C36*INICIO!$C$7*$D$7 | E36: =$D36/(1+INICIO!$C$5) | F36: =$E36*$C$10 | G36: =$C$11 | H36: =$F36-$G36 | I36: =$I35+$H36
B37: Mes 7 | C37: =$C36*(1+$E$7) | D37: =$C37*INICIO!$C$7*$D$7 | E37: =$D37/(1+INICIO!$C$5) | F37: =$E37*$C$10 | G37: =$C$11 | H37: =$F37-$G37 | I37: =$I36+$H37
B38: Mes 8 | C38: =$C37*(1+$E$7) | D38: =$C38*INICIO!$C$7*$D$7 | E38: =$D38/(1+INICIO!$C$5) | F38: =$E38*$C$10 | G38: =$C$11 | H38: =$F38-$G38 | I38: =$I37+$H38
B39: Mes 9 | C39: =$C38*(1+$E$7) | D39: =$C39*INICIO!$C$7*$D$7 | E39: =$D39/(1+INICIO!$C$5) | F39: =$E39*$C$10 | G39: =$C$11 | H39: =$F39-$G39 | I39: =$I38+$H39
B40: Mes 10 | C40: =$C39*(1+$E$7) | D40: =$C40*INICIO!$C$7*$D$7 | E40: =$D40/(1+INICIO!$C$5) | F40: =$E40*$C$10 | G40: =$C$11 | H40: =$F40-$G40 | I40: =$I39+$H40
B41: Mes 11 | C41: =$C40*(1+$E$7) | D41: =$C41*INICIO!$C$7*$D$7 | E41: =$D41/(1+INICIO!$C$5) | F41: =$E41*$C$10 | G41: =$C$11 | H41: =$F41-$G41 | I41: =$I40+$H41
B42: Mes 12 | C42: =$C41*(1+$E$7) | D42: =$C42*INICIO!$C$7*$D$7 | E42: =$D42/(1+INICIO!$C$5) | F42: =$E42*$C$10 | G42: =$C$11 | H42: =$F42-$G42 | I42: =$I41+$H42
B45: ESCENARIO OPTIMISTA
B46: Mes | C46: Ventas/dia | D46: Venta bruta c/IVA | E46: Ingreso neto | F46: Margen contrib. $ | G46: Gastos fijos | H46: UTILIDAD NETA | I46: Caja acumulada
B47: Mes 1 | C47: =$C$8 | D47: =$C47*INICIO!$C$7*$D$8 | E47: =$D47/(1+INICIO!$C$5) | F47: =$E47*$C$10 | G47: =$C$11 | H47: =$F47-$G47 | I47: =$H47
B48: Mes 2 | C48: =$C47*(1+$E$8) | D48: =$C48*INICIO!$C$7*$D$8 | E48: =$D48/(1+INICIO!$C$5) | F48: =$E48*$C$10 | G48: =$C$11 | H48: =$F48-$G48 | I48: =$I47+$H48
B49: Mes 3 | C49: =$C48*(1+$E$8) | D49: =$C49*INICIO!$C$7*$D$8 | E49: =$D49/(1+INICIO!$C$5) | F49: =$E49*$C$10 | G49: =$C$11 | H49: =$F49-$G49 | I49: =$I48+$H49
B50: Mes 4 | C50: =$C49*(1+$E$8) | D50: =$C50*INICIO!$C$7*$D$8 | E50: =$D50/(1+INICIO!$C$5) | F50: =$E50*$C$10 | G50: =$C$11 | H50: =$F50-$G50 | I50: =$I49+$H50
B51: Mes 5 | C51: =$C50*(1+$E$8) | D51: =$C51*INICIO!$C$7*$D$8 | E51: =$D51/(1+INICIO!$C$5) | F51: =$E51*$C$10 | G51: =$C$11 | H51: =$F51-$G51 | I51: =$I50+$H51
B52: Mes 6 | C52: =$C51*(1+$E$8) | D52: =$C52*INICIO!$C$7*$D$8 | E52: =$D52/(1+INICIO!$C$5) | F52: =$E52*$C$10 | G52: =$C$11 | H52: =$F52-$G52 | I52: =$I51+$H52
B53: Mes 7 | C53: =$C52*(1+$E$8) | D53: =$C53*INICIO!$C$7*$D$8 | E53: =$D53/(1+INICIO!$C$5) | F53: =$E53*$C$10 | G53: =$C$11 | H53: =$F53-$G53 | I53: =$I52+$H53
B54: Mes 8 | C54: =$C53*(1+$E$8) | D54: =$C54*INICIO!$C$7*$D$8 | E54: =$D54/(1+INICIO!$C$5) | F54: =$E54*$C$10 | G54: =$C$11 | H54: =$F54-$G54 | I54: =$I53+$H54
B55: Mes 9 | C55: =$C54*(1+$E$8) | D55: =$C55*INICIO!$C$7*$D$8 | E55: =$D55/(1+INICIO!$C$5) | F55: =$E55*$C$10 | G55: =$C$11 | H55: =$F55-$G55 | I55: =$I54+$H55
B56: Mes 10 | C56: =$C55*(1+$E$8) | D56: =$C56*INICIO!$C$7*$D$8 | E56: =$D56/(1+INICIO!$C$5) | F56: =$E56*$C$10 | G56: =$C$11 | H56: =$F56-$G56 | I56: =$I55+$H56
B57: Mes 11 | C57: =$C56*(1+$E$8) | D57: =$C57*INICIO!$C$7*$D$8 | E57: =$D57/(1+INICIO!$C$5) | F57: =$E57*$C$10 | G57: =$C$11 | H57: =$F57-$G57 | I57: =$I56+$H57
B58: Mes 12 | C58: =$C57*(1+$E$8) | D58: =$C58*INICIO!$C$7*$D$8 | E58: =$D58/(1+INICIO!$C$5) | F58: =$E58*$C$10 | G58: =$C$11 | H58: =$F58-$G58 | I58: =$I57+$H58
B61: La columna 'Caja acumulada' es la que importa: te dice en que mes dejas de poner plata de tu bolsillo.
